Workbook

Sheet Plano mestre 95 % 2025 5% - (4)
R1: PLANEJAMENTO FABRICA | AF1: PLANEJAMENTO FABRICA | AT1: PLANEJAMENTO FABRICA | BH1: PLANEJAMENTO FABRICA | BV1: PLANEJAMENTO FABRICA | CH1: Férias 18/12 - 29/12 | CJ1: PLANEJAMENTO FABRICA | CX1: PLANEJAMENTO FABRICA
D2: 2019 | R2: 2020 | AF2: 2021 | AT2: 2022 | BH2: 2023 | BV2: 2024 | CH2: COMPENSAÇÃO 30 ,31 ,02 e 03 | CJ2: /--------------------------------------------2025 | CX2: 2026
A3: Dias Uteis Produção | C3: =A3 -> Dias Uteis Produção | CH3: 12 dias de férias | CJ3: 23 | CK3: 20 | CL3: 21 | CM3: 22 | CN3: 22 | CO3: 21 | CP3: 23 | CQ3: 21 | CR3: 21 | CS3: 23 | CT3: 20 | CU3: 13 | CX3: 23 | CY3: 20 | CZ3: 21 | DA3: 22 | DB3: 22 | DC3: 21 | DD3: 23 | DE3: 21 | DF3: 21 | DG3: 23 | DH3: 20 | DI3: 13
A4: (-) FÉRIAS | C4: =A4 -> (-) FÉRIAS | CH4: 4 dias de compensação | CJ4: 3 | CL4: 1.5 | CX4: 3 | CY4: 5
A5: (+) SABADO | C5: =A5 -> (+) SABADO | CH5: dias de compensação 9/11 , 23/11 , 7/12 e 14/12 | CJ5: 2 | CK5: 3 | CL5: 1.5 | CM5: 0 | CN5: 0 | CO5: 1.5 | CP5: 1 | CQ5: 1.5 | CR5: 1.5 | CS5: 1.5 | CT5: 0 | DA5: 0 | DB5: 0 | DC5: 0 | DD5: 0 | DE5: 0 | DF5: 0 | DG5: 1 | DH5: 0
A6: (-)FERIADO | C6: =A6 -> (-)FERIADO | CG6: 2 grupos a partir de dezembro | CL6: 2 | CM6: 2 | CN6: 1 | CO6: 1 | CR6: 1 | CS6: 1 | CT6: 1 | CZ6: 2 | DA6: 2 | DB6: 1 | DC6: 1 | DF6: 1 | DG6: 1 | DH6: 1
A7: Dias Trabalhados | C7: =A7 -> Dias Trabalhados | D7: 16 | E7: 21 | F7: 18 | G7: 21 | H7: 22 | I7: 19 | J7: 23 | K7: 21 | L7: 21 | M7: 26 | N7: 24 | O7: 15 | R7: 22 | S7: 20 | T7: 14 | U7: 1 | V7: 12 | W7: 22 | X7: 23 | Y7: 21 | Z7: 21 | AA7: 21 | AB7: 20 | AC7: 17 | AF7: 18 | AG7: 20 | AH7: 20 | AI7: 20 | AJ7: 22 | AK7: 20 | AL7: 22 | AM7: 22 | AN7: 21 | AO7: 20 | AP7: 20 | AQ7: 12 | AT7: 19 | AU7: 19 | AV7: 18 | AW7: 19 | AX7: 22 | AY7: 21 | AZ7: 21 | BA7: 22 | BB7: 22 | BC7: 21 | BD7: 20 | BE7: 10 | BH7: 20 | BI7: 17 | BJ7: 23 | BK7: 18 | BL7: 22 | BM7: 23 | BN7: 21 | BO7: 21 | BP7: 20 | BQ7: 21 | BR7: 20 | BS7: 14 | BT7: 20 | BV7: 19 | BW7: 19 | BX7: 21 | BY7: =22+2 -> 24 | BZ7: =21+2 -> 23 | CA7: =20+2 -> 22 | CB7: =23+2 -> 25 | CC7: =21+3 -> 24 | CD7: =21+3 -> 24 | CE7: =23+1 -> 24 | CF7: =19+3 -> 22 | CG7: =12+1 -> 13 | CJ7: =CJ3+CJ5-CJ6-CJ4 -> 22 | CK7: =CK3+CK5-CK6-CK4 -> 23 | CL7: 19 | CM7: =CM3+CM5-CM6-CM4 -> 20 | CN7: =CN3+CN5-CN6-CN4 -> 21 | CO7: =CO3+CO5-CO6-CO4 -> 21.5 | CP7: =CP3+CP5-CP6 -> 24 | CQ7: =CQ3+CQ5-CQ6 -> 22.5 | CR7: =CR3+CR5-CR6 -> 21.5 | CS7: =CS3+CS5-CS6 -> 23.5 | CT7: =CT3+CT5-CT6 -> 19 | CU7: =CU3+CU5-CU6 -> 13 | CX7: =CX3+CX5-CX6-CX4 -> 20 | CY7: =CY3+CY5-CY6-CY4 -> 15 | CZ7: =CZ3+CZ5-CZ6-CZ4 -> 19 | DA7: =DA3+DA5-DA6-DA4 -> 20 | DB7: =DB3+DB5-DB6-DB4 -> 21 | DC7: =DC3+DC5-DC6-DC4 -> 20 | DD7: =DD3+DD5-DD6 -> 23 | DE7: =DE3+DE5-DE6 -> 21 | DF7: =DF3+DF5-DF6 -> 20 | DG7: =DG3+DG5-DG6 -> 23 | DH7: =DH3+DH5-DH6 -> 19 | DI7: =DI3+DI5-DI6 -> 13
D8: JAN | E8: FEV | F8: MAR | G8: ABR | H8: MAI | I8: JUN | J8: JUL | K8: AGO | L8: SET | M8: OUT | N8: NOV | O8: DEZ | P8: TOTAL | R8: JAN | S8: FEV | T8: MAR | U8: ABR | V8: MAI | W8: JUN | X8: JUL | Y8: AGO | Z8: SET | AA8: OUT | AB8: NOV | AC8: DEZ | AD8: TOTAL | AF8: JAN | AG8: FEV | AH8: MAR | AI8: ABR | AJ8: MAI | AK8: JUN | AL8: JUL | AM8: AGO | AN8: SET | AO8: OUT | AP8: NOV | AQ8: DEZ | AR8: TOTAL | AT8: JAN | AU8: FEV | AV8: MAR | AW8: ABR | AX8: MAI | AY8: JUN | AZ8: JUL | BA8: AGO | BB8: SET | BC8: OUT | BD8: NOV | BE8: DEZ | BF8: TOTAL | BH8: JAN | BI8: FEV | BJ8: MAR | BK8: ABR | BL8: MAI | BM8: JUN | BN8: JUL | BO8: AGO | BP8: SET | BQ8: OUT | BR8: NOV | BS8: DEZ | BT8: TOTAL | BV8: JAN | BW8: FEV | BX8: MAR | BY8: ABR | BZ8: MAI | CA8: JUN | CB8: JUL | CC8: AGO | CD8: SET | CE8: OUT | CF8: NOV | CG8: DEZ | CH8: TOTAL | CJ8: JAN | CK8: FEV | CL8: MAR | CM8: ABR | CN8: MAI | CO8: JUN | CP8: JUL | CQ8: AGO | CR8: SET | CS8: OUT | CT8: NOV | CU8: DEZ | CV8: TOTAL | CX8: JAN | CY8: FEV | CZ8: MAR | DA8: ABR | DB8: MAI | DC8: JUN | DD8: JUL | DE8: AGO | DF8: SET | DG8: OUT | DH8: NOV | DI8: DEZ | DJ8: TOTAL
CI9: redução de meta | CW9: redução de meta
A10: ESTOQUE FÍSICO | B10: Total (1+2) DISPONÍVEL TOTAL | D10: =SUM(D15:D17) -> 304786 | E10: =SUM(E15:E17) -> 311986 | F10: =SUM(F15:F17) -> 328231 | G10: =SUM(G15:G17) -> 317873 | H10: =SUM(H15:H17) -> 347196 | I10: =SUM(I15:I17) -> 402253 | J10: =SUM(J15:J17) -> 454488 | K10: =SUM(K15:K17) -> 447182 | ... O10: =SUM(O15:O17) -> 188264 | R10: =SUM(R15:R17) -> 283359 | S10: =SUM(S15:S17) -> 342718 | T10: =SUM(T15:T17) -> 313212 | U10: =SUM(U15:U17) -> 298093 | V10: =SUM(V15:V17) -> 206617 | W10: =SUM(W15:W17) -> 235875 | X10: =SUM(X15:X17) -> 360135 | Y10: =SUM(Y15:Y17) -> 361665 | ... AC10: =SUM(AC15:AC17) -> 197551 | AF10: =SUM(AF15:AF19) -> 255339 | AG10: =SUM(AG15:AG19) -> 292621 | AH10: =SUM(AH15:AH19) -> 397976 | AI10: =SUM(AI15:AI19) -> 388165 | AJ10: =SUM(AJ15:AJ19) -> 409301 | AK10: =SUM(AK15:AK19) -> 490913 | AL10: =SUM(AL15:AL19) -> 563229 | AM10: =SUM(AM15:AM19) -> 559169 | ... AQ10: =SUM(AQ15:AQ19) -> 531679 | AR10: =AQ10 -> 531679 | AT10: =SUM(AT15:AT19) -> 471378 | AU10: =SUM(AU15:AU19) -> 473307 | AV10: =SUM(AV15:AV19) -> 412518 | AW10: =SUM(AW15:AW19) -> 398039 | AX10: =SUM(AX15:AX19) -> 417827 | AY10: =SUM(AY15:AY19) -> 507968 | AZ10: =SUM(AZ15:AZ19) -> 477530 | BA10: =SUM(BA15:BA19) -> 520708 | ... BE10: =SUM(BE15:BE19) -> 356505 | BF10: =BE10 -> 356505 | BH10: =SUM(BH15:BH19) -> 357143 | BI10: =SUM(BI15:BI19) -> 355011 | BJ10: =SUM(BJ15:BJ19) -> 344281 | BK10: =SUM(BK15:BK19) -> 389628 | BL10: =SUM(BL15:BL19) -> 324889 | BM10: =SUM(BM15:BM19) -> 352666 | BN10: =SUM(BN15:BN19) -> 418721 | BO10: =SUM(BO15:BO19) -> 356602 | ... BR10: =SUM(BR15:BR19) -> 228035 | BS10: =BS15+BS16+BS19 -> 201165 | BT10: =BS10 -> 201165 | BV10: =BV11+BV16+BV19 -> 247713 | BW10: =BW11+BW16+BW19 -> 278707 | BX10: =BX11+BX16+BX19 -> 281829 | BY10: =BY11+BY16+BY19 -> 317753 | BZ10: =BZ11+BZ16+BZ19 -> 270339 | CA10: =CA11+CA16+CA19 -> 310383 | CB10: =CB11+CB16+CB19 -> 328365 | CC10: =CC11+CC16+CC19 -> 333476 | ... CG10: =CG11+CG16+CG19 -> 182266 | CH10: =CH15+CH16+CH19 -> 161447 | CJ10: =CH10+CJ71-CJ27 -> 145024.06 | CK10: =CJ10+CK71-CK27 -> 167771.39 | CL10: =CK10+CL71-CL27 -> 152974.71 | CM10: =CL10+CM71-CM27 -> 172918.05 | CN10: =CM10+CN71-CN27 -> 208116.1 | CO10: =CN10+CO71-CO27 -> 281435.22 | CP10: =CO10+CP71-CP27 -> 271715.13 | CQ10: =CP10+CQ71-CQ27 -> 271819.82 | CR10: =CQ10+CR71-CR27 -> 212966.18 | ... CU10: =CT10+CU71-CU27 -> 228180.35 | CV10: 116080.11 | CX10: =CV10+CX71-CX27 -> 109586.02 | CY10: =CX10+CY71-CY27 -> 73440.716 | CZ10: =CY10+CZ71-CZ27 -> 53154.202 | DA10: =CZ10+DA71-DA27 -> 69094.709 | DB10: =DA10+DB71-DB27 -> 100802.66 | DC10: =DB10+DC71-DC27 -> 158612.74 | DD10: =DC10+DD71-DD27 -> 133206.64 | DE10: =DD10+DE71-DE27 -> 109166.57 | DF10: =DE10+DF71-DF27 -> 23680.246 | ... DI10: =DH10+DI71-DI27 -> 9525.1244 | DJ10: 116080.11
A11: 0 | B11: ESTOQUE FISICO EM LINHA | BV11: 204006 | BW11: 241182 | BX11: 245950 | BY11: 281974 | BZ11: 202865 | CA11: 240895 | CB11: 273565 | CC11: 288981 | CD11: 273990 | CE11: 237556 | CF11: 168313 | CG11: 150819 | CH11: =CG11 -> 150819 | CJ11: 205037 | CK11: 230430 | CL11: 234343 | CM11: 262404
A12: 0 | B12: PEDIDOS EM CARTEIRA | BV12: 80956 | BW12: 110544 | BX12: 134506 | BY12: 127959 | BZ12: 66136 | CA12: 72582 | CB12: 94286 | CC12: 133081 | CD12: 148174 | CE12: 154201 | CF12: 97365 | CG12: 30184 | CJ12: 132209 | CK12: 180000 | CL12: 177643 | CM12: 148159
A13: 0 | B13: PROCESSO | CJ13: 150321 | CK13: 133602 | CL13: 135672 | CM13: 127653
A14: 0 | B14: ESTOQUE NEGATIVO | CJ14: 36757 | CK14: 55826 | CL14: 60438 | CM14: 50114
A15: 1 | B15: EM LINHA DISPONIVEL | D15: 197000 | E15: 223027 | F15: 230513 | G15: 231174 | H15: 255028 | I15: =316386+3241 -> 319627 | J15: 377712 | K15: 382411 | L15: 394107 | M15: 267954 | O15: 143875 | R15: 208084 | S15: 268431 | T15: 250616 | U15: 237088 | V15: 147777 | W15: 215818 | X15: 273510 | Y15: 299059 | Z15: 304980 | AA15: 231197 | AB15: 143086 | AC15: 172491 | AF15: 198695 | AG15: 234210 | AH15: 327560 | AI15: 332523 | AJ15: 356667 | AK15: 384165 | AL15: 317268 | AM15: 370708 | AN15: 354503 | AO15: 314605 | AP15: 90490 | AQ15: 58348 | AR15: =AQ15 -> 58348 | AT15: 158701 | AU15: 115369 | AV15: 142379 | AW15: 118765 | AX15: 113246 | AY15: 106776 | AZ15: 175234 | BA15: 151553 | BB15: 167082 | BC15: 150959 | BD15: 119787 | BE15: 65426 | BF15: =BE15 -> 65426 | BH15: 166918 | BI15: 167160 | BJ15: 204571 | BK15: 153197 | BL15: 196798 | BM15: 145596 | BN15: 166021 | BO15: 211305 | BP15: 201071 | BQ15: 177743 | BR15: 144020 | BS15: 154347 | BT15: =BS15 -> 154347 | BV15: 151471 | BW15: 155653 | BX15: 151611 | BY15: 177044 | BZ15: 170481 | CA15: 221665 | CB15: 218105 | CC15: 188153 | CD15: 147751 | CE15: 112996 | CF15: 135968 | CG15: 130000 | CH15: =CG15 -> 130000 | CI15: 114000 | CJ15: 109585 | CK15: 103815 | CL15: 117138 | CM15: =CL15+CM71-CM27 -> 137081.34 | CN15: =CM15+CN71-CN27 -> 172279.39 | CO15: =CN15+CO71-CO27 -> 245598.51 | CP15: =CO15+CP71-CP27 -> 235878.42 | CQ15: =CP15+CQ71-CQ27 -> 235983.11 | CR15: =CQ15+CR71-CR27 -> 177129.47 | CS15: =CR15+CS71-CS27 -> 163912.55 | CT15: =CS15+CT71-CT27 -> 175927.46 | CU15: =CT15+CU71-CU27 -> 192343.64 | CX15: =CU15+CX71-CX27 -> 185849.55 | CY15: =CX15+CY71-CY27 -> 149704.25 | CZ15: =CY15+CZ71-CZ27 -> 129417.74 | DA15: =CZ15+DA71-DA27 -> 145358.24 | DB15: =DA15+DB71-DB27 -> 177066.2 | DC15: =DB15+DC71-DC27 -> 234876.27 | DD15: =DC15+DD71-DD27 -> 209470.18 | DE15: =DD15+DE71-DE27 -> 185430.1 | DF15: =DE15+DF71-DF27 -> 99943.779 | ... DI15: =DH15+DI71-DI27 -> 85788.657 | DJ15: 0
A16: 2 | B16: EM LINHA NAO COMPRAR MP DISPONIVEL | D16: 73670 | E16: 59682 | F16: 54710 | G16: 56175 | H16: 58933 | I16: 42784 | J16: 35755 | K16: 33547 | L16: 22824 | M16: 26162 | O16: 44389 | R16: 39759 | S16: 38325 | T16: 26634 | U16: =14430+2754+7859 -> 25043 | V16: 23840 | W16: 20057 | X16: 80502 | Y16: 56483 | Z16: 44233 | AA16: 38155 | AB16: 27540 | AC16: 25060 | AF16: 21326 | AG16: 17804 | AH16: 27157 | AI16: 19677 | AJ16: 18817 | AK16: 25034 | AL16: 28090 | AM16: 25660 | AN16: 33752 | AO16: 24699 | AP16: 19340 | AQ16: 29842 | AR16: =AQ16 -> 29842 | AT16: 46493 | AU16: 37125 | AV16: 38574 | AW16: 43626 | AX16: 39641 | AY16: 55553 | AZ16: 48023 | BA16: 55043 | BB16: 50383 | BC16: 54355 | BD16: 82473 | BE16: 65398 | BF16: =BE16 -> 65398 | BH16: 68747 | BI16: 62843 | BJ16: 62154 | BK16: 49337 | BL16: 27730 | BM16: 42459 | BN16: 44049 | BO16: 29196 | BP16: 36882 | BQ16: 35965 | BR16: 31343 | BS16: 23087 | BT16: =BS16 -> 23087 | BV16: 15202 | BW16: 12471 | BX16: 11483 | BY16: 14071 | BZ16: 49617 | CA16: 36385 | CB16: 25473 | CC16: 16933 | CD16: 12684 | CE16: 21084 | CF16: 15172 | CG16: 11469 | CH16: =CG16 -> 11469 | CI16: =7500*5 -> 37500 | CJ16: 9465 | CK16: 13722 | CL16: 10771 | CM16: 8991 | CV16: 0 | DJ16: 0
A17: 3 | B17: EM LINHA PARADO (cob >3) DISPONIVEL | D17: 34116 | E17: 29277 | F17: 43008 | G17: 30524 | H17: 33235 | I17: 39842 | J17: 41021 | K17: 31224 | M17: 10286 | R17: 35516 | S17: 35962 | T17: 35962 | U17: 35962 | V17: 35000 | X17: 6123 | Y17: 6123 | Z17: 4187 | AA17: 2745 | AF17: 8366 | AG17: 11534 | AH17: 11507 | AI17: 9148 | AJ17: 8524 | AK17: 25290 | AL17: 91080 | AM17: 66830 | AN17: 36866 | AO17: 16173 | AP17: 178274 | AQ17: 210665 | AR17: =AQ17 -> 210665 | AT17: 121075 | AU17: 149376 | AV17: 104538 | AW17: 105262 | AX17: 121073 | AY17: 163931 | AZ17: 109964 | BA17: 148266 | BB17: 130697 | BC17: 113779 | BD17: 91119 | BE17: 103286 | BF17: =BE17 -> 103286 | BH17: 49631 | BI17: 52953 | BJ17: 28440 | BK17: 83601 | BL17: 25812 | BM17: 59545 | BN17: 83435 | BO17: 34041 | BP17: 22399 | BQ17: 24887 | BR17: 12183 | BS17: 12183 | BT17: =BS17 -> 12183 | BV17: 5216 | BX17: 65273 | BY17: 70182 | BZ17: 57659 | CA17: 71669 | CB17: 73078 | CC17: 85302 | CD17: 25343 | CE17: 19030 | CF17: 19422 | CG17: 25927 | CH17: =CG17 -> 25927 | CI17: 29000 | CJ17: 21580 | CK17: 18052 | CL17: 30722 | CM17: 55095 | CV17: 0 | DJ17: 0
A18: 4 | B18: EM LINHA PARADO (cob >6) DISPONIVEL | D18: 34116 | E18: 29277 | F18: 43008 | G18: 30524 | H18: 33235 | I18: 39842 | J18: 41021 | K18: 31224 | M18: 10286 | R18: 35516 | S18: 35962 | T18: 35962 | U18: 35962 | V18: 35000 | X18: 6123 | Y18: 6123 | Z18: 4187 | AA18: 2745 | AF18: 8366 | AG18: 11534 | AH18: 11507 | AI18: 9148 | AJ18: 8524 | AK18: 25290 | AL18: 91080 | AM18: 66830 | AN18: 36866 | AO18: 16173 | AP18: 178274 | AQ18: 210665 | AR18: =AQ18 -> 210665 | AT18: 121075 | AU18: 149376 | AV18: 104538 | AW18: 105262 | AX18: 121073 | AY18: 163931 | AZ18: 109964 | BA18: 148266 | BB18: 130697 | BC18: 113779 | BD18: 91119 | BE18: 103286 | BF18: =BE18 -> 103286 | BH18: 49631 | BI18: 52953 | BJ18: 28440 | BK18: 83601 | BL18: 25812 | BM18: 59545 | BN18: 83435 | BO18: 34041 | BP18: 22399 | BQ18: 24887 | BR18: 12183 | BS18: 12183 | BT18: =BS18 -> 12183 | CD18: 6361 | CE18: 7759 | CF18: 6573 | CG18: 9541 | CH18: =CG18 -> 9541 | CI18: =CI15+CI16-CI17 -> 122500 | CJ18: 9582 | CK18: 7266 | CL18: 11364 | CM18: 15500 | CV18: 0 | DJ18: 0
A19: 1 | B19: FL (OPORTUNIDADES) DISPONIVEL | D19: 6409 | E19: 6860 | F19: 4970 | G19: 31203 | H19: 31499 | I19: 25903 | J19: 18606 | K19: 16014 | L19: 13416 | M19: 40079 | O19: 0 | R19: 3376 | S19: 11736 | T19: 22454 | U19: 21384 | V19: 66870 | W19: 73769 | X19: 13944 | Y19: 32750 | Z19: 18536 | AA19: 40211 | AB19: 44457 | AC19: 24504 | AF19: 18586 | AG19: 17539 | AH19: 20245 | AI19: 17669 | AJ19: 16769 | AK19: 31134 | AL19: 35711 | AM19: 29141 | AN19: 25307 | AO19: 35964 | AP19: 37378 | AQ19: 22159 | AR19: =AQ19 -> 22159 | AT19: 24034 | AU19: 22061 | AV19: 22489 | AW19: 25124 | AX19: 22794 | AY19: 17777 | AZ19: 34345 | BA19: 17580 | BB19: 26992 | BC19: 21373 | BD19: 21202 | BE19: 19109 | BF19: =BE19 -> 19109 | BH19: 22216 | BI19: 19102 | BJ19: 20676 | BK19: 19892 | BL19: 48737 | BM19: 45521 | BN19: 41781 | BO19: 48019 | BP19: 43955 | BQ19: 41505 | BR19: 28306 | BS19: 23731 | BT19: =BS19 -> 23731 | BV19: 28505 | BW19: 25054 | BX19: 24396 | BY19: 21708 | BZ19: 17857 | CA19: 33103 | CB19: 29327 | CC19: 27562 | CD19: 19590 | CE19: 11730 | CF19: 10529 | CG19: 19978 | CH19: =CG19 -> 19978 | CJ19: 18456 | CK19: 15409 | CL19: 18755 | CM19: 15700 | CV19: 0 | DJ19: 0
A20: 0 | B20: EM LINHA NAO COMPRAR MP FISICO | CE20: 34501 | CF20: 18809 | CG20: 12618 | CJ20: 11940 | CK20: 19956 | CL20: 15650 | CM20: 11745
A21: 0 | B21: FL(OPORTUNIDADE) FISICO | CE21: 12837 | CF21: 11839 | CG21: 20519 | CJ21: 17816 | CK21: 17432 | CL21: 21670 | CM21: 19814
B22: SALDO UTIL DE ESTOQUE | D22: =D10-D17 -> 270670 | E22: =E10-E17 -> 282709 | F22: =F10-F17 -> 285223 | G22: =G10-G17 -> 287349 | H22: =H10-H17 -> 313961 | I22: =I10-I17 -> 362411 | J22: =J10-J17 -> 413467 | K22: =K10-K17 -> 415958 | ... O22: =O10-O17 -> 188264 | R22: =R10-R17 -> 247843 | S22: =S10-S17 -> 306756 | T22: =T10-T17 -> 277250 | U22: =U10-U17 -> 262131 | V22: =V10-V17 -> 171617 | W22: =W10-W17 -> 235875 | X22: =X10-X17 -> 354012 | Y22: =Y10-Y17 -> 355542 | ... AB22: =AB10-AB17 -> 170626 | AF22: =AF10-AF17 -> 246973 | AG22: =AG10-AG17 -> 281087 | AH22: =AH10-AH17 -> 386469 | AI22: =AI10-AI17 -> 379017 | AJ22: =AJ10-AJ17 -> 400777 | AK22: =AK10-AK17 -> 465623 | AL22: =AL10-AL17 -> 472149 | AM22: =AM10-AM17 -> 492339 | ... AQ22: =AQ10-AQ17 -> 321014 | AR22: =AQ22 -> 321014 | AT22: =AT10-AT17 -> 350303 | AU22: =AU10-AU17 -> 323931 | AV22: =AV10-AV17 -> 307980 | AW22: =AW10-AW17 -> 292777 | AX22: =AX10-AX17 -> 296754 | AY22: =AY10-AY17 -> 344037 | AZ22: =AZ10-AZ17 -> 367566 | BA22: =BA10-BA17 -> 372442 | ... BE22: =BE10-BE17 -> 253219 | BF22: =BE22 -> 253219 | BH22: =BH10-BH17 -> 307512 | BI22: =BI10-BI17 -> 302058 | BJ22: =BJ10-BJ17 -> 315841 | BK22: =BK10-BK17 -> 306027 | BL22: =BL10-BL17 -> 299077 | BM22: =BM10-BM17 -> 293121 | BN22: =BN10-BN17 -> 335286 | BO22: =BO10-BO17 -> 322561 | ... BS22: =BS10-BS17 -> 188982 | BT22: =BS22 -> 188982 | BV22: =BV15-BV17-BV18 -> 146255 | BW22: =BW15-BW17-BW18 -> 155653 | BX22: =BX15-BX17-BX18 -> 86338 | BY22: =BY15-BY17-BY18 -> 106862 | BZ22: =BZ15-BZ17-BZ18 -> 112822 | CA22: =CA15-CA17-CA18 -> 149996 | CB22: =CB15-CB17-CB18 -> 145027 | CC22: =CC15-CC17-CC18 -> 102851 | ... CH22: =CH15-CH17-CH18 -> 94532 | CJ22: =CJ15-CJ17-CJ18 -> 78423 | CK22: =CK15-CK17-CK18 -> 78497 | CL22: =CL15-CL17-CL18 -> 75052 | CM22: =CM15-CM17-CM18 -> 66486.34 | CN22: =CN15-CN17-CN18 -> 172279.39 | CO22: =CO15-CO17-CO18 -> 245598.51 | CP22: =CP15-CP17-CP18 -> 235878.42 | CQ22: =CQ15-CQ17-CQ18 -> 235983.11 | ... CU22: =CU15-CU17-CU18 -> 192343.64 | CV22: 116080.11 | CX22: 242497 | CY22: 234422.08 | CZ22: 194348.71 | DA22: 223062.99 | DB22: 228884.87 | DC22: 240669.79 | DD22: 234679.66 | DE22: 197008.01 | DF22: 148007.96 | DG22: 111276.3 | DH22: 93072.106 | DI22: 116080.11 | DJ22: 116080.11
A23: ESTOQUE EM LINHA | C23: (1-3-5) | D23: =D15-D17 -> 162884 | E23: =E15+E19-E17-E60 -> 200610 | F23: =F15+F19-F17-F60 -> 192475 | G23: =G15+G19-G17-G60 -> 231853 | H23: =H15+H19-H17-H60 -> 253292 | I23: =I15+I19-I17-I60 -> 305688 | J23: =J15+J19-J17-J60 -> 355297 | K23: =K15+K19-K17-K60 -> 367201 | L23: =L15+L19-L17-L60 -> 407523 | ... O23: =O15+O19-O17-O60 -> 143875 | P23: =J23 -> 355297 | R23: =R15-R17 -> 172568 | S23: =S15+S19-S17-S60 -> 244205 | T23: =T15+T19-T17-T60 -> 237108 | U23: =U15+U19-U17-U60 -> 222510 | V23: =V15+V19-V17-V60 -> 179647 | W23: =W15+W19-W17-W60 -> 289587 | X23: =X15+X19-X17-X60 -> 281331 | Y23: =Y15+Y19-Y17-Y60 -> 325686 | Z23: =Z15+Z19-Z17-Z60 -> 319329 | ... AC23: =AC15+AC19-AC17-AC60 -> 196995 | AD23: =X23 -> 281331 | AF23: =AF15+AF17+AF16 -> 228387 | AG23: =AG15+AG17+AG16 -> 263548 | AH23: =AH15+AH17+AH16 -> 366224 | AI23: =AI15+AI17+AI16 -> 361348 | AJ23: =AJ15+AJ17+AJ16 -> 384008 | AK23: =AK15+AK17+AK16 -> 434489 | AL23: =AL15+AL17+AL16 -> 436438 | AM23: =AM15+AM17+AM16 -> 463198 | ... AQ23: =AQ15+AQ17+AQ16 -> 298855 | AR23: =AQ23 -> 298855 | AT23: =AT15+AT17+AT16 -> 326269 | AU23: =AU15+AU17+AU16 -> 301870 | AV23: =AV15+AV17+AV16 -> 285491 | AW23: =AW15+AW17+AW16 -> 267653 | AX23: =AX15+AX17+AX16 -> 273960 | AY23: =AY15+AY17+AY16 -> 326260 | AZ23: =AZ15+AZ17+AZ16 -> 333221 | BA23: =BA15+BA17+BA16 -> 354862 | ... BE23: =BE15+BE17+BE16 -> 234110 | BF23: =SUM(AT23:BE23) -> 3664330 | BH23: =BH15+BH17+BH16 -> 285296 | BI23: =BI15+BI17+BI16 -> 282956 | BJ23: =BJ15+BJ17+BJ16 -> 295165 | BK23: =BK15+BK17+BK16 -> 286135 | BL23: =BL15+BL17+BL16 -> 250340 | BM23: =BM15+BM17+BM16 -> 247600 | BN23: =BN15+BN17+BN16 -> 293505 | BO23: =BO15+BO17+BO16 -> 274542 | ... BS23: =BS15+BS17+BS16 -> 189617 | BT23: =BS23 -> 189617 | BV23: =BV15+BV17+BV16 -> 171889 | BW23: =BW15+BW19+BW16 -> 193178 | BX23: =BX15+BX17+BX16 -> 228367 | BY23: =BY15+BY17+BY16 -> 261297 | BZ23: =BZ15+BZ17+BZ16 -> 277757 | CA23: =CA15+CA17+CA16 -> 329719 | CB23: =CB15+CB17+CB16 -> 316656 | CC23: =CC15+CC17+CC16 -> 290388 | CD23: =CD15+CD17+CD16 -> 185778 | CE23: =CE15+CE17+CE16 -> 153110 | ... CG23: =CG15+CG17+CG16 -> 167396 | CH23: =CG23 -> 167396 | CJ23: 224424 | CK23: 0 | CL23: 0 | CM23: 0 | CN23: 0 | CO23: 0 | CP23: 0 | CQ23: 0 | CR23: 0 | CS23: 0 | CT23: 0 | CU23: 0 | CV23: 0 | CX23: 224424 | CY23: 0 | CZ23: 0 | DA23: 0 | DB23: 0 | DC23: 0 | DD23: 0 | DE23: 0 | DF23: 0 | DG23: 0 | DH23: 0 | DI23: 0 | DJ23: 0
A24: ESTOQUE EM LINHA SEM SALDO PARADO | C24: (1-3-5-6+7) | D24: =D10-D19-D17 -> 264261 | E24: =E10-E19-E17 -> 275849 | F24: =F10-F19-F17 -> 280253 | G24: =G10-G19-G17 -> 256146 | H24: =H10-H19-H17 -> 282462 | I24: =I10-I19-I17 -> 336508 | J24: =J10-J19-J17 -> 394861 | K24: =K10-K19-K17 -> 399944 | ... O24: =O10-O19-O17 -> 188264 | P24: =O24 -> 188264 | R24: =R10-R19-R17 -> 244467 | S24: =S10-S19-S17 -> 295020 | T24: =T10-T19-T17 -> 254796 | U24: =U10-U19-U17 -> 240747 | V24: =V10-V19-V17 -> 104747 | W24: =W10-W19-W17 -> 162106 | X24: =X10-X19-X17 -> 340068 | Y24: =Y10-Y19-Y17 -> 322792 | ... AC24: =AC10-AC19-AC17 -> 173047 | AD24: =AC24 -> 173047 | AF24: =AF23-AF17 -> 220021 | AG24: =AG23-AG17 -> 252014 | AH24: =AH23-AH17 -> 354717 | AI24: =AI23-AI17 -> 352200 | AJ24: =AJ23-AJ17 -> 375484 | AK24: =AK23-AK17 -> 409199 | AL24: =AL23-AL17 -> 345358 | AM24: =AM23-AM17 -> 396368 | ... AQ24: =AQ23-AQ17 -> 88190 | AR24: =AQ24 -> 88190 | AT24: =AT23-AT17 -> 205194 | AU24: =AU23-AU17 -> 152494 | AV24: =AV23-AV17 -> 180953 | AW24: =AW23-AW17 -> 162391 | AX24: =AX23-AX17 -> 152887 | AY24: =AY23-AY17 -> 162329 | AZ24: =AZ23-AZ17 -> 223257 | BA24: =BA23-BA17 -> 206596 | ... BE24: =BE23-BE17 -> 130824 | BF24: =SUM(AT24:BE24) -> 2201964 | BG24: =SUM(AT27:AY27)/SUM(AF61:AK61)-1 -> 0.22832581 | BH24: =BH23-BH17 -> 235665 | BI24: =BI23-BI17 -> 230003 | BJ24: =BJ23-BJ17 -> 266725 | BK24: =BK23-BK17 -> 202534 | BL24: =BL23-BL17 -> 224528 | BM24: =BM23-BM17 -> 188055 | BN24: =BN23-BN17 -> 210070 | BO24: =BO23-BO17 -> 240501 | ... BS24: =BS23-BS17 -> 177434 | BT24: =BS24 -> 177434 | BV24: =BV23-BV17 -> 166673 | BW24: =BW23-BW17 -> 193178 | BX24: =BX23-BX17 -> 163094 | BY24: =BY23-BY17 -> 191115 | BZ24: =BZ23-BZ17 -> 220098 | CA24: =CA23-CA17 -> 258050 | CB24: =CB23-CB17 -> 243578 | CC24: =CC23-CC17 -> 205086 | ... CG24: =CG23-CG17 -> 141469 | CH24: =CG24 -> 141469 | CJ24: 219208 | CK24: 0 | CL24: 0 | CM24: 0 | CN24: 0 | CO24: 0 | CP24: 0 | CQ24: 0 | CR24: 0 | CS24: 0 | CT24: 0 | CU24: 0 | CV24: 0 | CX24: 219208 | CY24: 0 | CZ24: 0 | DA24: 0 | DB24: 0 | DC24: 0 | DD24: 0 | DE24: 0 | DF24: 0 | DG24: 0 | DH24: 0 | DI24: 0 | DJ24: 0
A25: PROJEÇÃO DOS ESTOQUES DISPONIVEL | C25: (1-5-6+7) | D25: =D10 -> 304786 | E25: =E10 -> 311986 | F25: =F10 -> 328231 | G25: =G10 -> 317873 | H25: =H10 -> 347196 | I25: =I10 -> 402253 | J25: =J10 -> 454488 | K25: =K10 -> 447182 | ... O25: =O10 -> 188264 | P25: =O25 -> 188264 | R25: =R10 -> 283359 | S25: =S10 -> 342718 | T25: =T10 -> 313212 | U25: =U10 -> 298093 | V25: =V10 -> 206617 | W25: =W10 -> 235875 | X25: =X10 -> 360135 | Y25: =Y10 -> 361665 | ... AC25: =AC10 -> 197551 | AD25: =AC25 -> 197551 | AF25: =AF10-AF60 -> 255339 | AG25: =AG10-AG60 -> 292621 | AH25: =AH10-AH60 -> 397976 | AI25: =AI10-AI60 -> 388165 | AJ25: =AJ10-AJ60 -> 409301 | AK25: =AK10-AK60 -> 490913 | AL25: =AL10-AL60 -> 563229 | AM25: =AM10-AM60 -> 559169 | ... AQ25: =AQ10-AQ60 -> 522741 | AR25: =AQ25 -> 522741 | AT25: =AT10-AT60 -> 364736 | AU25: =AU10-AU60 -> 382608 | AV25: =AV10-AV60 -> 322837 | AW25: =AW10-AW60 -> 339249 | AX25: =AX10-AX60 -> 382307 | AY25: =AY10-AY60 -> 446417 | AZ25: =AZ10-AZ60 -> 406019 | BA25: =BA10-BA60 -> 457091 | BB25: =BB10-BB60 -> 439103 | BC25: =BB25-BC27+BC71-BC60 -> 267702.71 | BD25: =BC25-BD27+BD71-BD60 -> 224792.12 | BE25: =BD25-BE27+BE71-BE60 -> 209302.51 | BF25: =BE25 -> 209302.51 | BG25: =BG27/AR27 -> 0.070333736 | BH25: =BH10-BH60 -> 287739 | BI25: =BI10-BI60 -> 274599 | BJ25: =BJ10-BJ60 -> 249895 | BK25: =BK10-BK60 -> 311315 | BL25: =BL10-BL60 -> 277855 | BM25: =BM10-BM60 -> 301815 | BN25: =BN10-BN60 -> 325519 | BO25: =BO10-BO60 -> 255915 | ... BS25: =BS10-BS60 -> 201165 | BT25: =BS25 -> 201165 | BV25: =BV10-BV60 -> 247713 | BW25: =BW10-BW60 -> 278707 | BX25: =BX10-BX60 -> 281829 | BY25: =BY10-BY60 -> 317753 | BZ25: =BZ10-BZ60 -> 270339 | CA25: =CA10-CA60 -> 310383 | CB25: =CB10-CB60 -> 328365 | CC25: =CC10-CC60 -> 333476 | ... CG25: =CG10-CG60 -> 182266 | CH25: =CG25 -> 182266 | CJ25: 247713 | CK25: 234422.08 | CL25: 194348.71 | CM25: 223062.99 | CN25: 228884.87 | CO25: 240669.79 | CP25: 234679.66 | CQ25: 197008.01 | CR25: 148007.96 | CS25: 111276.3 | CT25: 93072.106 | CU25: 116080.11 | CV25: 116080.11 | CW25: =CV27-459000 -> 1692766.6 | CX25: 247713 | CY25: 234422.08 | CZ25: 194348.71 | DA25: 223062.99 | DB25: 228884.87 | DC25: 240669.79 | DD25: 234679.66 | DE25: 197008.01 | DF25: 148007.96 | DG25: 111276.3 | DH25: 93072.106 | DI25: 116080.11 | DJ25: 116080.11
B26: Cobertura de Estoque | AF26: =AF10/AG27 -> 1.4346741 | AG26: =AG10/AH27 -> 3.9745328 | AH26: =AH10/AI27 -> 4.4537255 | AI26: =AI10/AJ27 -> 3.1781895 | AJ26: =AJ10/AK27 -> 2.7551225 | AK26: =AK10/AL27 -> 3.229797 | AL26: =AL10/AM27 -> 2.3575635 | AM26: =AM10/AN27 -> 2.1413161 | ... AP26: =AP10/AQ27 -> 5.1487735 | AQ26: =AQ10/AT27 -> 3.4807307 | AR26: =AQ26 -> 3.4807307 | AT26: =AT10/AU27 -> 2.7971286 | AU26: =AU10/AV27 -> 3.0710064 | AV26: =AV10/AW27 -> 2.584778 | AW26: =AW10/AX27 -> 3.3142308 | AX26: =AX10/AY27 -> 3.0202081 | AY26: =AY10/(AZ57+AZ56) -> 3.0375411 | AZ26: =AZ10/(BA57+BA56) -> 1.7862994 | BA26: =BA10/(BB57+BB56) -> 2.3917338 | BB26: =BB10/(BC57+BC56) -> 2.0297187 | BC26: =BC10/(BD57+BD56) -> 2.9418602 | BD26: =BD10/(BE57+BE56) -> 5.3595753 | BE26: =BE10/BH27 -> 2.3338658 | BH26: =BH10/BI27 -> 2.4324842 | BI26: =BI10/BJ27 -> 2.069479 | BJ26: =BJ10/BK27 -> 2.1548304 | BK26: =BK10/BL27 -> 2.9406585 | BL26: =BL10/BM27 -> 2.5009495 | BM26: =BM10/BN27 -> 2.0577587 | BN26: =BN10/BO27 -> 2.332053 | BV26: 0 | BW26: 0 | BX26: 0 | BY26: 0 | BZ26: 0 | CA26: 0 | CB26: 0 | CC26: 0 | CD26: 0 | CE26: 0 | CF26: 0 | CJ26: 0 | CK26: 0 | CL26: 0 | CM26: 0 | CN26: 0 | CO26: 0 | CP26: 0 | CQ26: 0 | CR26: 0 | CS26: 0 | CT26: 0 | CX26: 0 | CY26: 0 | CZ26: 0 | DA26: 0 | DB26: 0 | DC26: 0 | DD26: 0 | DE26: 0 | DF26: 0 | DG26: 0 | DH26: 0
A27: 6 | B27: Estimativa Vendas Comercial | D27: =SUM(D31:D54) -> 82250 | E27: =SUM(E31:E54) -> 117000 | F27: =SUM(F31:F54) -> 121750 | G27: =SUM(G31:G54) -> 150000 | H27: =SUM(H31:H54) -> 99500 | I27: =SUM(I31:I54) -> 102000 | J27: =SUM(J31:J54) -> 177632 | K27: =SUM(K31:K54) -> 178158 | ... P27: =SUM(P31:P54) -> 1617764 | R27: =R31+R55 -> 136177.34 | S27: =S31+S55 -> 143840.33 | T27: =T31+T55 -> 142553.77 | U27: =U31+U55 -> 19814.9 | V27: =V31+V55 -> 52085 | W27: =W31+W55 -> 70169.382 | X27: =X31+X55 -> 144463.33 | Y27: =Y31+Y55 -> 226547.08 | ... AC27: =AC31+AC55 -> 0 | AD27: =SUM(R27:AC27) -> 1418438.6 | AF27: =AF31+AF55 -> 128646 | AG27: =AG31+AG55 -> 177977 | AH27: =AH31+AH55 -> 73624 | AI27: =AI31+AI55 -> 89358 | AJ27: =AJ31+AJ55 -> 122134 | AK27: =AK31+AK55 -> 148560 | AL27: =AL31+AL55 -> 151995 | AM27: =AM31+AM55 -> 238903 | ... AQ27: =AQ31+AQ55 -> 97840 | AR27: =SUM(AF27:AQ27) -> 1874710.3 | AT27: =AT31+AT55 -> 152749.25 | AU27: =AU31+AU55 -> 168522.1 | AV27: =AV31+AV55 -> 154121.14 | AW27: =AW31+AW55 -> 159595.14 | AX27: =AX31+AX55 -> 120099.97 | AY27: =AY31+AY55 -> 138343.78 | AZ27: =AZ31+AZ55 -> 166673.78 | BA27: =BA31+BA55 -> 242442.3 | ... BD27: =BD31+BD55 -> 134555.59 | BE27: =BE31+BE56 -> 72686.613 | BF27: =SUM(AT27:BE27) -> 2006565.7 | BG27: =BF27-AR27 -> 131855.38 | BH27: =BH28+BH55 -> 152753 | BI27: =BI28+BI55 -> 146822.33 | BJ27: =BJ28+BJ55 -> 171546.07 | BK27: =BK28+BK55 -> 159771.74 | BL27: =BL28+BL55 -> 132496.85 | BM27: =BM28+BM55 -> 129906.26 | BN27: =BN28+BN55 -> 171383.56 | BO27: =BO28+BO56 -> 179550.38 | BP27: =BP28+BP56 -> 202053.75 | BQ27: =BQ28+BQ56 -> 163865 | BR27: =BR28+BR56 -> 175620.6 | BS27: 92285.6 | BT27: =SUM(BH27:BS27) -> 1878055.1 | BV27: =BV31+(BV56)*$CI$27 -> 161157.87 | BW27: =BW31+(BW56)*$CI$27 -> 155966.83 | BX27: =BX31+(BX56)*$CI$27 -> 196111.54 | BY27: =BY31+(BY56)*$CI$27 -> 159169.23 | BZ27: =BZ31+(BZ56)*$CI$27 -> 151482.39 | CA27: =CA31+(CA56)*$CI$27 -> 141442.13 | CB27: =CB31+(CB56)*$CI$27 -> 176986.21 | CC27: =CC31+(CC56)*$CI$27 -> 201301.09 | ... CG27: =CG31+(CG56)*$CI$27 -> 87483.817 | CH27: =SUM(BV27:CG27) -> 2030972.3 | CI27: 0.95 | CJ27: =CJ31+CJ65 -> 181422.94 | CK27: =CK31+CK65 -> 165852.67 | CL27: =CL31+CL65 -> 185796.68 | CM27: =CM31+CM65 -> 160056.66 | CN27: =CN31+CN65 -> 153801.95 | CO27: =CO31+CO65 -> 120180.88 | CP27: =CP31+CP65 -> 225720.09 | CQ27: =CQ31+CQ65 -> 206895.31 | ... CU27: =CU31+CU65 -> 103183.82 | CV27: =SUM(CJ27:CU27) -> 2151766.6 | CW27: 10% DE CRESCIMENTO | CX27: =CJ27*1.05 -> 190494.09 | CY27: =CK27*1.05 -> 174145.3 | CZ27: =CL27*1.05 -> 195086.51 | DA27: =CM27*1.05 -> 168059.49 | DB27: =CN27*1.05 -> 161492.05 | DC27: =CO27*1.05 -> 126189.92 | DD27: =CP27*1.05 -> 237006.09 | DE27: =CQ27*1.05 -> 217240.08 | ... DI27: =CU27*1.05 -> 108343.01 | DJ27: 1957097.2
B28: Estimativa de Venda para plano de produção | AY28: =AY31+AY56 -> 119777.78 | AZ28: =AZ31+AZ56 -> 150777.78 | BA28: =BA31+BA56 -> 233098.5 | BB28: =BB29/BB30 -> 210777.78 | BC28: =BC31+BC56 -> 249806.29 | BD28: =BD31+BD56*0.85 -> 122960.59 | BE28: =BE31+BE56*0.85 -> 66386.613 | BF28: =SUM(AT28:BE28) -> 1153585.3 | BH28: =BH29/BH30-0.1*BH29/BH30 -> 116600 | BI28: =BI29/BI30-0.1*BI29/BI30 -> 111533.33 | BJ28: =BJ29/BJ30-0.05*BJ29/BJ30 -> 135674.07 | BK28: =BK29/BK30-0.05*BK29/BK30 -> 121740.74 | BL28: =BL29/BL30-0.05*BL29/BL30 -> 93926.852 | BM28: =BM29/BM30-0.05*BM29/BM30 -> 90679.259 | BN28: =BN29/BN30-0.05*BN29/BN30 -> 130255.56 | BO28: =BO29/BO30-0.05*BO29/BO30 -> 150550.38 | BP28: =BP29/BP30-0.05*BP29/BP30 -> 161830.75 | BQ28: 127130 | BR28: 138687.6 | BS28: 43639.2 | BT28: =SUM(BH28:BS28) -> 1422247.7 | BV28: =BV31+BV55 -> 166555.78 | BW28: =BW31+BW55 -> 152835.37 | BX28: =BX31+BX55 -> 195319.21 | BY28: =BY31+BY55 -> 158396.19 | BZ28: =BZ31+BZ55 -> 152371.51 | CA28: =CA31+CA55 -> 147696.01 | CB28: =CB31+CB55 -> 189465.05 | CC28: =CC31+CC55 -> 202914.1 | ... CG28: =CG31+CG55 -> 88389.319 | CH28: =SUM(BV28:CG28) -> 2065409.9 | CI28: =(CH28-BT62)/BT62 -> 0.48621753 | CW28: =(CV28-CH62)/CH62 -> -1 | CX28: 166555.78 | CY28: 152835.37 | CZ28: 195319.21 | DA28: 158396.19 | DB28: 152371.51 | DC28: 147696.01 | DD28: 189465.05 | DE28: 202914.1 | DF28: 214499.62 | DG28: 217683 | DH28: 179284.72 | DI28: 88389.319 | DJ28: 2065409.9
B29: Estimativa Varejo em R$ | AN29: 6715000 | AO29: 6555000 | AP29: 2640000 | AQ29: 1302000 | AT29: 3264695 | AU29: 3863760 | AV29: 3429225 | AW29: 3525360 | AX29: 2509485 | AY29: 2829000 | AZ29: 3666000 | BA29: 5705000 | BB29: 5691000 | BC29: 5600000 | BD29: 2430000 | BE29: 800000 | BF29: =SUM(AT29:BE29) -> 43313525 | BH29: 3498000 | BI29: 3346000 | BJ29: 3856000 | BK29: 3460000 | BL29: 2669500 | BM29: 2577200 | BN29: 3702000 | BO29: 4278800.2 | BP29: 4599400.2 | BQ29: =BQ28*BQ30 -> 3432510 | BR29: 2954493.2 | BS29: 984831.07 | BT29: =SUM(BH29:BS29) -> 39358735 | BV29: =BV30*BV31 -> 3399704.6 | BW29: =BW30*BW31 -> 3264737.6 | BX29: =BX30*BX31 -> 4185000 | BY29: =BY30*BY31 -> 3348000 | BZ29: =BZ30*BZ31 -> 3074042.2 | CA29: =CA30*CA31 -> 2812995.4 | CB29: =CB30*CB31 -> 3737141.6 | CC29: =CC30*CC31 -> 4437000.7 | ... CG29: =CG30*CG31 -> 792579.23 | CH29: =SUM(BV29:CG29) -> 41966781 | CJ29: =CJ30*CJ31 -> 4023031.5 | CK29: =CK30*CK31 -> 3734347.7 | CL29: =CL30*CL31 -> 4223923.1 | CM29: =CM30*CM31 -> 3507679 | CN29: =CN30*CN31 -> 3217429.2 | CO29: =CO30*CO31 -> 2332522.6 | CP29: =CP30*CP31 -> 5138020.6 | CQ29: =CQ30*CQ31 -> 4640709 | ... CV29: =CV30*CV31 -> 46446711 | CX29: 3399704.6 | CY29: 3264737.6 | CZ29: 4185000 | DA29: 3348000 | DB29: 3074042.2 | DC29: 2812995.4 | DD29: 3737141.6 | DE29: 4437000.7 | DF29: 4710370.4 | DG29: 4744197 | DH29: 3461011.9 | DI29: 792579.23 | DJ29: 41966781
B30: Ticket Médio R$ | AN30: =30 -> 30 | AO30: =30 -> 30 | AP30: =30 -> 30 | AQ30: =30 -> 30 | AT30: 28 | AU30: 29 | AV30: 29 | AW30: 29 | AX30: 29 | AY30: 27 | AZ30: 27 | BA30: 27 | BB30: 27 | BC30: 26.07 | BD30: 26.07 | BE30: 26.07 | BH30: 27 | BI30: 27 | BJ30: 27 | BK30: 27 | BL30: 27 | BM30: 27 | BN30: 27 | BO30: 27 | BP30: 27 | BQ30: 27 | BR30: 27 | BS30: 27 | BV30: 26 | BW30: 26 | BX30: 26 | BY30: 26 | BZ30: 26 | CA30: 26 | CB30: 26 | CC30: 26 | CD30: 26 | CE30: 26 | CF30: 26 | CG30: 26 | CJ30: 26.32 | CK30: =CJ30 -> 26.32 | CL30: =CK30 -> 26.32 | CM30: =CL30 -> 26.32 | CN30: =CM30 -> 26.32 | CO30: =CN30 -> 26.32 | CP30: =CO30 -> 26.32 | CQ30: =CP30 -> 26.32 | CR30: =CQ30 -> 26.32 | ... CV30: =CU30 -> 26.32 | CX30: 26 | CY30: 26 | CZ30: 26 | DA30: 26 | DB30: 26 | DC30: 26 | DD30: 26 | DE30: 26 | DF30: 26 | DG30: 26 | DH30: 26 | DI30: 26
B31: Estimativa Varejo Multimarcas | D31: 82250 | E31: 117000 | F31: 121750 | G31: 150000 | H31: 99500 | I31: 102000 | J31: 177632 | K31: 178158 | L31: 199211 | M31: 229474 | N31: 122368 | O31: 38421 | P31: =SUM(D31:O31) -> 1617764 | R31: 115619.8 | S31: 123327.78 | T31: 128854 | U31: =126016*0.15 -> 18902.4 | V31: 35234 | W31: 56469.382 | X31: 118413.33 | Y31: 198797.08 | Z31: 242087.5 | AA31: 140000 | AB31: 0 | AC31: -45300 | AD31: =SUM(R31:AC31) -> 1132405.3 | AF31: 90146 | AG31: 155577 | AH31: 62953 | AI31: 73261 | AJ31: 91856 | AK31: 120000 | AL31: 110295 | AM31: 200203 | AN31: =AN29/AN30 -> 223833.33 | AO31: =AO29/AO30 -> 218500 | AP31: =AP29/AP30 -> 88000 | AQ31: =AQ29/AQ30 -> 43400 | AR31: =SUM(AF31:AQ31) -> 1478024.3 | AT31: =AT29/AT30 -> 116596.25 | AU31: =AU29/AU30 -> 133233.1 | AV31: =AV29/AV30 -> 118249.14 | AW31: =AW29/AW30 -> 121564.14 | AX31: =AX29/AX30 -> 86533.966 | AY31: =AY29/AY30 -> 104777.78 | AZ31: =AZ29/AZ30 -> 135777.78 | BA31: =BA29/BA30 -> 211296.3 | ... BE31: =BE29/BE30 -> 30686.613 | BF31: =SUM(AT31:BE31) -> 1577509.7 | BG31: =BF31-AR31 -> 99485.382 | BH31: =BH28 -> 116600 | BI31: =BI28 -> 111533.33 | BJ31: =BJ28 -> 135674.07 | BK31: =BK28 -> 121740.74 | BL31: =BL28 -> 93926.852 | BM31: =BM28 -> 90679.259 | BN31: =BN28 -> 130255.56 | BO31: =BO28 -> 150550.38 | ... BT31: =BT28 -> 1422247.7 | BV31: ='META EM PEÇAS'!S73 -> 130757.87 | BW31: ='META EM PEÇAS'!T73 -> 125566.83 | BX31: ='META EM PEÇAS'!U73 -> 160961.54 | BY31: ='META EM PEÇAS'!V73 -> 128769.23 | BZ31: ='META EM PEÇAS'!W73 -> 118232.39 | CA31: ='META EM PEÇAS'!X73 -> 108192.13 | CB31: ='META EM PEÇAS'!Y73 -> 143736.21 | CC31: ='META EM PEÇAS'!Z73 -> 170653.87 | ... CG31: ='META EM PEÇAS'!AD73 -> 30483.817 | CH31: 45 | CI31: =CH31*26 -> 1170 | CJ31: =BV62*1.19 -> 152850.74 | CK31: =BW62*1.19 -> 141882.51 | CL31: =BX62*1.19 -> 160483.4 | CM31: =BY62*1.19 -> 133270.48 | CN31: =BZ62*1.19 -> 122242.75 | CO31: =CA62*1.19 -> 88621.68 | CP31: =CB62*1.19 -> 195213.55 | CQ31: =CC62*1.19 -> 176318.73 | ... CU31: =CG62*1.19 -> 47560.73 | CV31: =SUM(CJ31:CU31) -> 1764692.6 | CW31: =CV31*26 -> 45882009 | CX31: 130757.87 | CY31: 125566.83 | CZ31: 160961.54 | DA31: 128769.23 | DB31: 118232.39 | DC31: 108192.13 | DD31: 143736.21 | DE31: 170653.87 | DF31: 181168.09 | DG31: 182469.12 | DH31: 133115.84 | DI31: 30483.817 | DJ31: 1614106.9
CJ32: =BV62 -> 128446 | CK32: =BW62 -> 119229 | CL32: =BX62 -> 134860 | CM32: =BY62 -> 111992 | CN32: =BZ62 -> 102725 | CO32: =CA62 -> 74472 | CP32: =CB62 -> 164045 | CQ32: =CC62 -> 148167 | ... CU32: =CG62 -> 39967 | CV32: =SUM(CJ32:CU32) -> 1482935
CJ33: =(CJ31-CJ32)/CJ32 -> 0.19 | CK33: =(CK31-CK32)/CK32 -> 0.19 | CL33: =(CL31-CL32)/CL32 -> 0.19 | CM33: =(CM31-CM32)/CM32 -> 0.19 | CN33: =(CN31-CN32)/CN32 -> 0.19 | CO33: =(CO31-CO32)/CO32 -> 0.19 | CP33: =(CP31-CP32)/CP32 -> 0.19 | CQ33: =(CQ31-CQ32)/CQ32 -> 0.19 | ... CU33: =(CU31-CU32)/CU32 -> 0.19
A34: 1 | B34: Loja Maraponga | P34: =SUM(D34:O34) -> 0 | R34: 7017.5439 | S34: 7017.5439 | T34: =7017.54385964912/2 -> 3508.7719 | U34: =96*U7 -> 96 | V34: 3000 | W34: 7200 | X34: 8500 | Y34: 8500 | Z34: 8500 | AA34: 9000 | AB34: 9500 | AC34: 8500 | AD34: =SUM(R34:AC34) -> 80339.86 | AF34: 8000 | AG34: 4000 | AH34: 5673 | AI34: 4500 | AJ34: 7892 | AK34: 6400 | AL34: 8000 | AM34: 8000 | AN34: 8000 | AO34: 8000 | AP34: 8800 | AQ34: 6400 | AR34: =SUM(AF34:AQ34) -> 83665 | AT34: 4861 | AU34: 5809 | AV34: 5072 | AW34: 4725 | AX34: 5832 | AY34: 5832 | AZ34: 5567 | BA34: 5567 | BB34: 5832 | BC34: 6892 | BD34: 7422 | BE34: 4241 | BF34: =SUM(AT34:BE34) -> 67652 | BG34: =BF34/AR34-1 -> -0.19139425 | BT34: 36051 | BV34: 4782.99 | BW34: 2945.31 | BX34: ='META EM PEÇAS'!U26-('META EM PEÇAS'!U26*0.05) -> 7080.369 | BY34: ='META EM PEÇAS'!V26-('META EM PEÇAS'!V26*0.05) -> 4355.655 | BZ34: ='META EM PEÇAS'!W26-('META EM PEÇAS'!W26*0.05) -> 5839.935 | CA34: ='META EM PEÇAS'!X26-('META EM PEÇAS'!X26*0.05) -> 5900.8965 | CB34: ='META EM PEÇAS'!Y26-('META EM PEÇAS'!Y26*0.05) -> 5279.796 | CC34: ='META EM PEÇAS'!Z26-('META EM PEÇAS'!Z26*0.05) -> 4897.2405 | CD34: ='META EM PEÇAS'!AA26-('META EM PEÇAS'!AA26*0.05) -> 5018.28 | CE34: ='META EM PEÇAS'!AB26-('META EM PEÇAS'!AB26*0.05) -> 4641.0255 | ... CG34: ='META EM PEÇAS'!AD26-('META EM PEÇAS'!AD26*0.05) -> 3929.808 | CH34: 4136.64 | CJ34: 4782.99 | CK34: 2945.31 | CL34: 7080.369 | CM34: 4355.655 | CN34: 5839.935 | CO34: 5900.8965 | CP34: 5279.796 | CQ34: 4897.2405 | CR34: 5018.28 | CS34: 4641.0255 | CT34: 6521.1135 | CU34: 3929.808 | CV34: 4136.64 | CX34: 4782.99 | CY34: 2945.31 | CZ34: 7080.369 | DA34: 4355.655 | DB34: 5839.935 | DC34: 5900.8965 | DD34: 5279.796 | DE34: 4897.2405 | DF34: 5018.28 | DG34: 4641.0255 | DH34: 6521.1135 | DI34: 3929.808 | DJ34: 4136.64
A35: 2 | B35: Loja Iguatemi | P35: =SUM(D35:O35) -> 0 | R35: 2909 | S35: 2545 | T35: =2727/1.2 -> 2272.5 | U35: =2*U7 -> 2 | V35: 500 | W35: 1300 | X35: 3200 | Y35: 3200 | Z35: 3600 | AA35: 3600 | AB35: 3600 | AC35: 4500 | AD35: =SUM(R35:AC35) -> 31228.5 | AF35: 4000 | AG35: 1500 | AH35: 189 | AI35: 1842 | AJ35: 3764 | AK35: 3200 | AL35: 6000 | AM35: 5000 | AN35: 5000 | AO35: 5000 | AP35: 5000 | AQ35: 9000 | AR35: =SUM(AF35:AQ35) -> 49495 | AT35: 5468 | AU35: 5468 | AV35: 6249 | AW35: 6249 | AX35: 3923 | AY35: 3923 | AZ35: 3745 | BA35: 3745 | BB35: 3923 | BC35: 4636 | BD35: 4993 | BE35: 7133 | BF35: =SUM(AT35:BE35) -> 59455 | BG35: =BF35/AR35-1 -> 0.20123245 | BT35: 40562 | BV35: 4442.61 | BW35: 3433.56 | BX35: ='META EM PEÇAS'!U27-('META EM PEÇAS'!U27*0.05) -> 3860.0115 | BY35: ='META EM PEÇAS'!V27-('META EM PEÇAS'!V27*0.05) -> 3578.175 | BZ35: ='META EM PEÇAS'!W27-('META EM PEÇAS'!W27*0.05) -> 4015.5075 | CA35: ='META EM PEÇAS'!X27-('META EM PEÇAS'!X27*0.05) -> 4835.3955 | CB35: ='META EM PEÇAS'!Y27-('META EM PEÇAS'!Y27*0.05) -> 5815.197 | CC35: ='META EM PEÇAS'!Z27-('META EM PEÇAS'!Z27*0.05) -> 3888.2835 | CD35: ='META EM PEÇAS'!AA27-('META EM PEÇAS'!AA27*0.05) -> 4032.294 | CE35: ='META EM PEÇAS'!AB27-('META EM PEÇAS'!AB27*0.05) -> 4375.092 | ... CG35: ='META EM PEÇAS'!AD27-('META EM PEÇAS'!AD27*0.05) -> 7897.6065 | CH35: =SUM(BV35:CG35) -> 55778.656 | CJ35: 4442.61 | CK35: 3433.56 | CL35: 3860.0115 | CM35: 3578.175 | CN35: 4015.5075 | CO35: 4835.3955 | CP35: 5815.197 | CQ35: 3888.2835 | CR35: 4032.294 | CS35: 4375.092 | CT35: 5604.924 | CU35: 7897.6065 | CV35: 55778.656 | CX35: 4442.61 | CY35: 3433.56 | CZ35: 3860.0115 | DA35: 3578.175 | DB35: 4015.5075 | DC35: 4835.3955 | DD35: 5815.197 | DE35: 3888.2835 | DF35: 4032.294 | DG35: 4375.092 | DH35: 5604.924 | DI35: 7897.6065 | DJ35: 55778.656
A36: 3 | B36: Loja Monsenhor Tabosa | P36: =SUM(D36:O36) -> 0 | R36: 746 | S36: 653 | T36: 700 | U36: 0 | V36: 200 | W36: 400 | X36: 900 | Y36: 900 | Z36: 900 | AA36: 900 | AB36: 900 | AC36: 1200 | AD36: =SUM(R36:AC36) -> 8399 | AF36: 1800 | AG36: 1200 | AH36: 230 | AI36: 472 | AJ36: 1495 | AK36: 1200 | AL36: 1500 | AM36: 1500 | AN36: 1500 | AO36: 1500 | AP36: 1650 | AQ36: 2400 | AR36: =SUM(AF36:AQ36) -> 16447 | AT36: 2438 | AU36: 1501 | AV36: 1566 | AW36: 2127 | AX36: 1928 | AY36: 1928 | AZ36: 1840 | BA36: 1840 | BB36: 1928 | BC36: 2278 | BD36: 2454 | BE36: 3505 | BF36: =SUM(AT36:BE36) -> 25333 | BG36: =BF36/AR36-1 -> 0.5402809 | BT36: 7784 | BV36: 451 | BW36: 348.6 | BX36: ='META EM PEÇAS'!U28-('META EM PEÇAS'!U28*0.05) -> 391.97 | BY36: ='META EM PEÇAS'!V28-('META EM PEÇAS'!V28*0.05) -> 363.28 | BZ36: ='META EM PEÇAS'!W28-('META EM PEÇAS'!W28*0.05) -> 407.55 | CA36: ='META EM PEÇAS'!X28-('META EM PEÇAS'!X28*0.05) -> 490.77 | CB36: ='META EM PEÇAS'!Y28-('META EM PEÇAS'!Y28*0.05) -> 590.33 | CC36: ='META EM PEÇAS'!Z28-('META EM PEÇAS'!Z28*0.05) -> 394.63 | CD36: ='META EM PEÇAS'!AA28-('META EM PEÇAS'!AA28*0.05) -> 409.26 | CE36: ='META EM PEÇAS'!AB28-('META EM PEÇAS'!AB28*0.05) -> 444.22 | ... CG36: ='META EM PEÇAS'!AD28-('META EM PEÇAS'!AD28*0.05) -> 801.8 | CH36: =SUM(BV36:CG36) -> 5662.46 | CJ36: 451 | CK36: 348.6 | CL36: 391.97 | CM36: 363.28 | CN36: 407.55 | CO36: 490.77 | CP36: 590.33 | CQ36: 394.63 | CR36: 409.26 | CS36: 444.22 | CT36: 569.05 | CU36: 801.8 | CV36: 5662.46 | CX36: 451 | CY36: 348.6 | CZ36: 391.97 | DA36: 363.28 | DB36: 407.55 | DC36: 490.77 | DD36: 590.33 | DE36: 394.63 | DF36: 409.26 | DG36: 444.22 | DH36: 569.05 | DI36: 801.8 | DJ36: 5662.46
A37: 4 | B37: Loja North Shopping | P37: =SUM(D37:O37) -> 0 | R37: 1455 | S37: =2036 -> 2036 | T37: =2182/2 -> 1091 | U37: 0 | V37: 200 | W37: 900 | X37: 1600 | Y37: 1600 | Z37: 1600 | AA37: 1600 | AB37: 2200 | AC37: 2500 | AD37: =SUM(R37:AC37) -> 16782 | AF37: 2200 | AG37: 1500 | AH37: 121 | AI37: 565 | AJ37: 1514 | AK37: 1760 | AL37: 1800 | AM37: 2200 | AN37: 2200 | AO37: 2200 | AP37: 2420 | AQ37: 3520 | AR37: =SUM(AF37:AQ37) -> 22000 | AT37: 1529 | AU37: 1516 | AV37: 1586 | AW37: 1979 | AX37: 1283 | AY37: 1283 | AZ37: 1224 | BA37: 1224 | BB37: 1283 | BC37: 1516 | BD37: 1632 | BE37: 2332 | BF37: =SUM(AT37:BE37) -> 18387 | BG37: =BF37/AR37-1 -> -0.16422727 | BT37: 9018 | BV37: 1143.9 | BW37: 884.43 | BX37: ='META EM PEÇAS'!U29-('META EM PEÇAS'!U29*0.05) -> 993.9375 | BY37: ='META EM PEÇAS'!V29-('META EM PEÇAS'!V29*0.05) -> 921.4905 | BZ37: ='META EM PEÇAS'!W29-('META EM PEÇAS'!W29*0.05) -> 1033.695 | CA37: ='META EM PEÇAS'!X29-('META EM PEÇAS'!X29*0.05) -> 1244.8515 | CB37: ='META EM PEÇAS'!Y29-('META EM PEÇAS'!Y29*0.05) -> 1497.5325 | CC37: ='META EM PEÇAS'!Z29-('META EM PEÇAS'!Z29*0.05) -> 1001.0055 | CD37: ='META EM PEÇAS'!AA29-('META EM PEÇAS'!AA29*0.05) -> 1038.1125 | CE37: ='META EM PEÇAS'!AB29-('META EM PEÇAS'!AB29*0.05) -> 1126.4625 | ... CG37: ='META EM PEÇAS'!AD29-('META EM PEÇAS'!AD29*0.05) -> 2033.817 | CH37: =SUM(BV37:CG37) -> 14362.873 | CJ37: 1143.9 | CK37: 884.43 | CL37: 993.9375 | CM37: 921.4905 | CN37: 1033.695 | CO37: 1244.8515 | CP37: 1497.5325 | CQ37: 1001.0055 | CR37: 1038.1125 | CS37: 1126.4625 | CT37: 1443.639 | CU37: 2033.817 | CV37: 14362.873 | CX37: 1143.9 | CY37: 884.43 | CZ37: 993.9375 | DA37: 921.4905 | DB37: 1033.695 | DC37: 1244.8515 | DD37: 1497.5325 | DE37: 1001.0055 | DF37: 1038.1125 | DG37: 1126.4625 | DH37: 1443.639 | DI37: 2033.817 | DJ37: 14362.873
A38: 5 | B38: Loja Dom Luis | P38: =SUM(D38:O38) -> 0 | R38: 1353 | S38: 1184 | T38: 1268 | U38: =10*U7 -> 10 | V38: =10*V7 -> 120 | W38: 600 | X38: 1600 | Y38: 1600 | Z38: 1600 | AA38: 1600 | AB38: 1600 | AC38: 2200 | AD38: =SUM(R38:AC38) -> 14735 | AF38: 1800 | AG38: 1200 | AH38: 181 | AI38: 628 | AJ38: 1169 | AK38: 960 | AL38: 1500 | AM38: 1200 | AN38: 1200 | AO38: 1200 | AP38: 1320 | AQ38: 1920 | AR38: =SUM(AF38:AQ38) -> 14278 | AT38: 1496 | AU38: 1200 | AV38: 1227 | AW38: 1655 | AX38: 1141 | AY38: 1141 | AZ38: 1089 | BA38: 1089 | BB38: 1141 | BC38: 1349 | BD38: 1453 | BE38: 2075 | BF38: =SUM(AT38:BE38) -> 16056 | BG38: =BF38/AR38-1 -> 0.12452724 | BT38: 10591 | BV38: 1474.98 | BW38: 1140.18 | BX38: ='META EM PEÇAS'!U30-('META EM PEÇAS'!U30*0.05) -> 1281.9585 | BY38: ='META EM PEÇAS'!V30-('META EM PEÇAS'!V30*0.05) -> 1188.3075 | BZ38: ='META EM PEÇAS'!W30-('META EM PEÇAS'!W30*0.05) -> 1333.2015 | CA38: ='META EM PEÇAS'!X30-('META EM PEÇAS'!X30*0.05) -> 1606.203 | CB38: ='META EM PEÇAS'!Y30-('META EM PEÇAS'!Y30*0.05) -> 1931.331 | CC38: ='META EM PEÇAS'!Z30-('META EM PEÇAS'!Z30*0.05) -> 1291.677 | CD38: ='META EM PEÇAS'!AA30-('META EM PEÇAS'!AA30*0.05) -> 1339.386 | CE38: ='META EM PEÇAS'!AB30-('META EM PEÇAS'!AB30*0.05) -> 1453.3575 | ... CG38: ='META EM PEÇAS'!AD30-('META EM PEÇAS'!AD30*0.05) -> 2623.1115 | CH38: =SUM(BV38:CG38) -> 18525.228 | CJ38: 1474.98 | CK38: 1140.18 | CL38: 1281.9585 | CM38: 1188.3075 | CN38: 1333.2015 | CO38: 1606.203 | CP38: 1931.331 | CQ38: 1291.677 | CR38: 1339.386 | CS38: 1453.3575 | CT38: 1861.5345 | CU38: 2623.1115 | CV38: 18525.228 | CX38: 1474.98 | CY38: 1140.18 | CZ38: 1281.9585 | DA38: 1188.3075 | DB38: 1333.2015 | DC38: 1606.203 | DD38: 1931.331 | DE38: 1291.677 | DF38: 1339.386 | DG38: 1453.3575 | DH38: 1861.5345 | DI38: 2623.1115 | DJ38: 18525.228
A39: 6 | B39: Loja Parangaba | P39: =SUM(D39:O39) -> 0 | R39: 1455 | S39: 1273 | T39: 1364 | U39: 0 | V39: 200 | W39: 800 | X39: 1600 | Y39: 1600 | Z39: 1600 | AA39: 1600 | AB39: 1800 | AC39: 2400 | AD39: =SUM(R39:AC39) -> 15692 | AF39: 1500 | AG39: 1200 | AH39: 127 | AI39: 426 | AJ39: 1063 | AK39: 960 | AL39: 1500 | AM39: 1200 | AN39: 1200 | AO39: 1200 | AP39: 1320 | AQ39: 1920 | AR39: =SUM(AF39:AQ39) -> 13616 | AT39: 1222 | AU39: 1200 | AV39: 1117 | AW39: 1463 | AX39: 1087 | AY39: 1087 | AZ39: 1038 | BA39: 1038 | BB39: 1087 | BC39: 1285 | BD39: 1384 | BE39: 1977 | BF39: =SUM(AT39:BE39) -> 14985 | BG39: =BF39/AR39-1 -> 0.10054348 | BT39: 10087 | BV39: 1214.58 | BW39: 939.3 | BX39: ='META EM PEÇAS'!U31-('META EM PEÇAS'!U31*0.05) -> 1055.7825 | BY39: ='META EM PEÇAS'!V31-('META EM PEÇAS'!V31*0.05) -> 978.0345 | BZ39: ='META EM PEÇAS'!W31-('META EM PEÇAS'!W31*0.05) -> 1098.1905 | CA39: ='META EM PEÇAS'!X31-('META EM PEÇAS'!X31*0.05) -> 1322.5995 | CB39: ='META EM PEÇAS'!Y31-('META EM PEÇAS'!Y31*0.05) -> 1590.3 | CC39: ='META EM PEÇAS'!Z31-('META EM PEÇAS'!Z31*0.05) -> 1062.8505 | CD39: ='META EM PEÇAS'!AA31-('META EM PEÇAS'!AA31*0.05) -> 1102.608 | CE39: ='META EM PEÇAS'!AB31-('META EM PEÇAS'!AB31*0.05) -> 1196.259 | ... CG39: ='META EM PEÇAS'!AD31-('META EM PEÇAS'!AD31*0.05) -> 2160.1575 | CH39: =SUM(BV39:CG39) -> 15253.534 | CJ39: 1214.58 | CK39: 939.3 | CL39: 1055.7825 | CM39: 978.0345 | CN39: 1098.1905 | CO39: 1322.5995 | CP39: 1590.3 | CQ39: 1062.8505 | CR39: 1102.608 | CS39: 1196.259 | CT39: 1532.8725 | CU39: 2160.1575 | CV39: 15253.534 | CX39: 1214.58 | CY39: 939.3 | CZ39: 1055.7825 | DA39: 978.0345 | DB39: 1098.1905 | DC39: 1322.5995 | DD39: 1590.3 | DE39: 1062.8505 | DF39: 1102.608 | DG39: 1196.259 | DH39: 1532.8725 | DI39: 2160.1575 | DJ39: 15253.534
A40: 7 | B40: Loja Rio Mar | P40: =SUM(D40:O40) -> 0 | R40: 2000 | S40: =2182 -> 2182 | T40: =2455/2 -> 1227.5 | U40: =4*U7 -> 4 | V40: 200 | W40: 700 | X40: 1600 | Y40: 1600 | Z40: 1600 | AA40: 1600 | AB40: 2500 | AC40: 3200 | AD40: =SUM(R40:AC40) -> 18413.5 | AF40: 2600 | AG40: 1000 | AH40: 195 | AI40: 844 | AJ40: 1973 | AK40: 1840 | AL40: 2000 | AM40: 2300 | AN40: 2300 | AO40: 2300 | AP40: 2530 | AQ40: 3680 | AR40: =SUM(AF40:AQ40) -> 23562 | AT40: 1888 | AU40: 1414 | AV40: 2073 | AW40: 2338 | AX40: 1857 | AY40: 1857 | AZ40: 1772 | BA40: 1772 | BB40: 1857 | BC40: 2194 | BD40: 2363 | BE40: 3376 | BF40: =SUM(AT40:BE40) -> 24761 | BG40: =BF40/AR40-1 -> 0.050887021 | BT40: 22941 | BV40: 3211.29 | BW40: 2482.17 | BX40: ='META EM PEÇAS'!U32-('META EM PEÇAS'!U32*0.05) -> 2790.093 | BY40: ='META EM PEÇAS'!V32-('META EM PEÇAS'!V32*0.05) -> 2586.0045 | BZ40: ='META EM PEÇAS'!W32-('META EM PEÇAS'!W32*0.05) -> 2902.2975 | CA40: ='META EM PEÇAS'!X32-('META EM PEÇAS'!X32*0.05) -> 3495.126 | CB40: ='META EM PEÇAS'!Y32-('META EM PEÇAS'!Y32*0.05) -> 4203.693 | CC40: ='META EM PEÇAS'!Z32-('META EM PEÇAS'!Z32*0.05) -> 2810.4135 | CD40: ='META EM PEÇAS'!AA32-('META EM PEÇAS'!AA32*0.05) -> 2914.6665 | CE40: ='META EM PEÇAS'!AB32-('META EM PEÇAS'!AB32*0.05) -> 3162.93 | ... CG40: ='META EM PEÇAS'!AD32-('META EM PEÇAS'!AD32*0.05) -> 5709.177 | CH40: =SUM(BV40:CG40) -> 40319.592 | CJ40: 3211.29 | CK40: 2482.17 | CL40: 2790.093 | CM40: 2586.0045 | CN40: 2902.2975 | CO40: 3495.126 | CP40: 4203.693 | CQ40: 2810.4135 | CR40: 2914.6665 | CS40: 3162.93 | CT40: 4051.731 | CU40: 5709.177 | CV40: 40319.592 | CX40: 3211.29 | CY40: 2482.17 | CZ40: 2790.093 | DA40: 2586.0045 | DB40: 2902.2975 | DC40: 3495.126 | DD40: 4203.693 | DE40: 2810.4135 | DF40: 2914.6665 | DG40: 3162.93 | DH40: 4051.731 | DI40: 5709.177 | DJ40: 40319.592
A41: 9 | B41: Loja Joquei | P41: =SUM(D41:O41) -> 0 | R41: 1636 | S41: 1636 | T41: =1818/2 -> 909 | U41: 0 | V41: 200 | W41: 300 | X41: 1000 | Y41: 1200 | Z41: 1600 | AA41: 1600 | AB41: 1800 | AC41: 2300 | AD41: =SUM(R41:AC41) -> 14181 | AF41: 1500 | AG41: 1000 | AH41: 126 | AI41: 387 | AJ41: 895 | AK41: 800 | AL41: 1500 | AM41: 1000 | AN41: 1000 | AO41: 1000 | AP41: 1100 | AQ41: 1600 | AR41: =SUM(AF41:AQ41) -> 11908 | AT41: 1182 | AU41: 1200 | AV41: 932 | AW41: 1020 | AX41: 0 | AY41: 0 | AZ41: 0 | BA41: 0 | BB41: 0 | BC41: 0 | BD41: 0 | BE41: 0 | BF41: =SUM(AT41:BE41) -> 4334 | BG41: =BF41/AR41-1 -> -0.636043 | BT41: 7070 | BV41: 928.14 | BW41: 717.96 | BX41: ='META EM PEÇAS'!U37-('META EM PEÇAS'!U37*0.05) -> 806.6355 | BY41: ='META EM PEÇAS'!V37-('META EM PEÇAS'!V37*0.05) -> 747.441 | BZ41: ='META EM PEÇAS'!W37-('META EM PEÇAS'!W37*0.05) -> 839.325 | CA41: ='META EM PEÇAS'!X37-('META EM PEÇAS'!X37*0.05) -> 1010.724 | CB41: ='META EM PEÇAS'!Y37-('META EM PEÇAS'!Y37*0.05) -> 1214.8125 | CC41: ='META EM PEÇAS'!Z37-('META EM PEÇAS'!Z37*0.05) -> 812.82 | CD41: ='META EM PEÇAS'!AA37-('META EM PEÇAS'!AA37*0.05) -> 842.859 | CE41: ='META EM PEÇAS'!AB37-('META EM PEÇAS'!AB37*0.05) -> 914.4225 | ... CG41: ='META EM PEÇAS'!AD37-('META EM PEÇAS'!AD37*0.05) -> 1650.378 | CH41: =SUM(BV41:CG41) -> 11657.038 | CJ41: 928.14 | CK41: 717.96 | CL41: 806.6355 | CM41: 747.441 | CN41: 839.325 | CO41: 1010.724 | CP41: 1214.8125 | CQ41: 812.82 | CR41: 842.859 | CS41: 914.4225 | CT41: 1171.521 | CU41: 1650.378 | CV41: 11657.038 | CX41: 928.14 | CY41: 717.96 | CZ41: 806.6355 | DA41: 747.441 | DB41: 839.325 | DC41: 1010.724 | DD41: 1214.8125 | DE41: 812.82 | DF41: 842.859 | DG41: 914.4225 | DH41: 1171.521 | DI41: 1650.378 | DJ41: 11657.038
A42: 10 | B42: Loja Barra da Tijuca | P42: =SUM(D42:O42) -> 0 | R42: 1636 | S42: 1636 | T42: =1818/2 -> 909 | U42: =0.5*U7 -> 0.5 | V42: 200 | W42: 300 | X42: 1000 | Y42: 1200 | Z42: 1600 | AA42: 1600 | AB42: 1800 | AC42: 2300 | AD42: =SUM(R42:AC42) -> 14181.5 | AF42: 1500 | AG42: 1000 | AH42: 764 | AI42: 561 | AJ42: 1353 | AK42: 960 | AL42: 1500 | AM42: 1200 | AN42: 1200 | AO42: 1200 | AP42: 1320 | AQ42: 1920 | AR42: =SUM(AF42:AQ42) -> 14478 | AT42: 1285 | AU42: 957 | AV42: 1426 | AW42: 1595 | AX42: 1767 | AY42: 1767 | AZ42: 1686 | BA42: 1686 | BB42: 1767 | BC42: 2088 | BD42: 2248 | BE42: 3212 | BF42: =SUM(AT42:BE42) -> 21484 | BG42: =BF42/AR42-1 -> 0.48390662 | BT42: 16952 | BV42: 2631.9 | BW42: 2034.84 | BX42: ='META EM PEÇAS'!U33-('META EM PEÇAS'!U33*0.05) -> 2287.3815 | BY42: ='META EM PEÇAS'!V33-('META EM PEÇAS'!V33*0.05) -> 2119.5165 | BZ42: ='META EM PEÇAS'!W33-('META EM PEÇAS'!W33*0.05) -> 2379.2655 | CA42: ='META EM PEÇAS'!X33-('META EM PEÇAS'!X33*0.05) -> 2865.1905 | CB42: ='META EM PEÇAS'!Y33-('META EM PEÇAS'!Y33*0.05) -> 3445.65 | CC42: ='META EM PEÇAS'!Z33-('META EM PEÇAS'!Z33*0.05) -> 2303.2845 | CD42: ='META EM PEÇAS'!AA33-('META EM PEÇAS'!AA33*0.05) -> 2388.984 | CE42: ='META EM PEÇAS'!AB33-('META EM PEÇAS'!AB33*0.05) -> 2592.189 | ... CG42: ='META EM PEÇAS'!AD33-('META EM PEÇAS'!AD33*0.05) -> 4679.8995 | CH42: =SUM(BV42:CG42) -> 33049.177 | CJ42: 2631.9 | CK42: 2034.84 | CL42: 2287.3815 | CM42: 2119.5165 | CN42: 2379.2655 | CO42: 2865.1905 | CP42: 3445.65 | CQ42: 2303.2845 | CR42: 2388.984 | CS42: 2592.189 | CT42: 3321.0765 | CU42: 4679.8995 | CV42: 33049.177 | CX42: 2631.9 | CY42: 2034.84 | CZ42: 2287.3815 | DA42: 2119.5165 | DB42: 2379.2655 | DC42: 2865.1905 | DD42: 3445.65 | DE42: 2303.2845 | DF42: 2388.984 | DG42: 2592.189 | DH42: 3321.0765 | DI42: 4679.8995 | DJ42: 33049.177
A43: 10 | B43: Loja Kennedy | P43: =SUM(D43:O43) -> 0 | R43: 0 | S43: 0 | T43: 0 | U43: 0 | V43: 3500 | W43: 350 | X43: 800 | Y43: 1000 | Z43: 1600 | AA43: 2000 | AB43: 2400 | AC43: 3000 | AD43: =SUM(R43:AC43) -> 14650 | AF43: 2500 | AG43: 1000 | AH43: =2500*0.15 -> 375 | AI43: 787 | AJ43: 1569 | AK43: 2000 | AL43: 2500 | AM43: 2500 | AN43: 2500 | AO43: 2500 | AP43: 2750 | AQ43: 4000 | AR43: =SUM(AF43:AQ43) -> 24981 | AT43: 1806 | AU43: 2046 | AV43: 1646 | AW43: 1902 | AX43: 1545 | AY43: 1545 | AZ43: 1475 | BA43: 1475 | BB43: 1545 | BC43: 1826 | BD43: 0 | BE43: 0 | BF43: =SUM(AT43:BE43) -> 16811 | BG43: =BF43/AR43-1 -> -0.32704856 | BT43: 10230 | BV43: 1335.48 | BW43: 1032.3 | BX43: ='META EM PEÇAS'!U39-('META EM PEÇAS'!U39*0.05) -> 1160.0355 | BY43: ='META EM PEÇAS'!V39-('META EM PEÇAS'!V39*0.05) -> 1075.2195 | BZ43: ='META EM PEÇAS'!W39-('META EM PEÇAS'!W39*0.05) -> 1206.861 | CA43: ='META EM PEÇAS'!X39-('META EM PEÇAS'!X39*0.05) -> 1453.3575 | CB43: ='META EM PEÇAS'!Y39-('META EM PEÇAS'!Y39*0.05) -> 1747.563 | CC43: ='META EM PEÇAS'!Z39-('META EM PEÇAS'!Z39*0.05) -> 1168.8705 | CD43: ='META EM PEÇAS'!AA39-('META EM PEÇAS'!AA39*0.05) -> 1212.162 | CE43: ='META EM PEÇAS'!AB39-('META EM PEÇAS'!AB39*0.05) -> 1314.648 | ... CG43: ='META EM PEÇAS'!AD39-('META EM PEÇAS'!AD39*0.05) -> 2373.9645 | CH43: =SUM(BV43:CG43) -> 16765.296 | CJ43: 1335.48 | CK43: 1032.3 | CL43: 1160.0355 | CM43: 1075.2195 | CN43: 1206.861 | CO43: 1453.3575 | CP43: 1747.563 | CQ43: 1168.8705 | CR43: 1212.162 | CS43: 1314.648 | CT43: 1684.8345 | CU43: 2373.9645 | CV43: 16765.296 | CX43: 1335.48 | CY43: 1032.3 | CZ43: 1160.0355 | DA43: 1075.2195 | DB43: 1206.861 | DC43: 1453.3575 | DD43: 1747.563 | DE43: 1168.8705 | DF43: 1212.162 | DG43: 1314.648 | DH43: 1684.8345 | DI43: 2373.9645 | DJ43: 16765.296
A44: 11 | B44: Loja Iguatemi Intimate | P44: =SUM(D44:O44) -> 0 | R44: 0 | S44: 0 | T44: 0 | U44: 0 | V44: 4000 | W44: 100 | X44: 800 | Y44: 800 | Z44: 1200 | AA44: 1200 | AB44: 1800 | AC44: 2300 | AD44: =SUM(R44:AC44) -> 12200 | AF44: 1500 | AG44: 1000 | AH44: =1500*0.15 -> 225 | AI44: 324 | AJ44: 869 | AK44: 800 | AL44: 1500 | AM44: 1000 | AN44: 1000 | AO44: 1000 | AP44: 1100 | AQ44: 1600 | AR44: =SUM(AF44:AQ44) -> 11918 | AT44: 1191 | AU44: 1191 | AV44: 1191 | AW44: 1191 | AX44: 876 | AY44: 876 | AZ44: 836 | BA44: 836 | BB44: 876 | BC44: 1035 | BD44: 0 | BE44: 0 | BF44: =SUM(AT44:BE44) -> 10099 | BG44: =BF44/AR44-1 -> -0.15262628 | BT44: 7342 | BV44: 1643.31 | BW44: 1270.38 | BX44: ='META EM PEÇAS'!U40-('META EM PEÇAS'!U40*0.05) -> 1427.736 | BY44: ='META EM PEÇAS'!V40-('META EM PEÇAS'!V40*0.05) -> 1323.483 | BZ44: ='META EM PEÇAS'!W40-('META EM PEÇAS'!W40*0.05) -> 1485.1635 | CA44: ='META EM PEÇAS'!X40-('META EM PEÇAS'!X40*0.05) -> 1788.204 | CB44: ='META EM PEÇAS'!Y40-('META EM PEÇAS'!Y40*0.05) -> 2151.3225 | CC44: ='META EM PEÇAS'!Z40-('META EM PEÇAS'!Z40*0.05) -> 1438.338 | CD44: ='META EM PEÇAS'!AA40-('META EM PEÇAS'!AA40*0.05) -> 1491.348 | CE44: ='META EM PEÇAS'!AB40-('META EM PEÇAS'!AB40*0.05) -> 1618.572 | ... CG44: ='META EM PEÇAS'!AD40-('META EM PEÇAS'!AD40*0.05) -> 2921.7345 | CH44: =SUM(BV44:CG44) -> 20633.166 | CJ44: 1643.31 | CK44: 1270.38 | CL44: 1427.736 | CM44: 1323.483 | CN44: 1485.1635 | CO44: 1788.204 | CP44: 2151.3225 | CQ44: 1438.338 | CR44: 1491.348 | CS44: 1618.572 | CT44: 2073.5745 | CU44: 2921.7345 | CV44: 20633.166 | CX44: 1643.31 | CY44: 1270.38 | CZ44: 1427.736 | DA44: 1323.483 | DB44: 1485.1635 | DC44: 1788.204 | DD44: 2151.3225 | DE44: 1438.338 | DF44: 1491.348 | DG44: 1618.572 | DH44: 2073.5745 | DI44: 2921.7345 | DJ44: 20633.166
A45: 12 | B45: Loja Salvador Shopping | P45: =SUM(D45:O45) -> 0 | R45: 0 | S45: 0 | T45: 0 | U45: 0 | V45: 4000 | W45: 0 | X45: 800 | Y45: 1000 | Z45: 1200 | AA45: 1200 | AB45: 1800 | AC45: 2300 | AD45: =SUM(R45:AC45) -> 12300 | AF45: 1500 | AG45: 1200 | AH45: =1500*0.15 -> 225 | AI45: 332 | AJ45: 945 | AK45: 960 | AL45: 1500 | AM45: 1200 | AN45: 1200 | AO45: 1200 | AP45: 1320 | AQ45: 1920 | AR45: =SUM(AF45:AQ45) -> 13502 | AT45: 1254 | AU45: 1254 | AV45: 1254 | AW45: 1254 | AX45: 1236 | AY45: 1236 | AZ45: 0 | BA45: 0 | BB45: 0 | BC45: 0 | BD45: 0 | BE45: 0 | BF45: =SUM(AT45:BE45) -> 7488 | BG45: =BF45/AR45-1 -> -0.44541549 | BT45: 16899 | BV45: 2552.85 | BW45: 1973.46 | BX45: ='META EM PEÇAS'!U34-('META EM PEÇAS'!U34*0.05) -> 2218.4685 | BY45: ='META EM PEÇAS'!V34-('META EM PEÇAS'!V34*0.05) -> 2056.788 | BZ45: ='META EM PEÇAS'!W34-('META EM PEÇAS'!W34*0.05) -> 2307.702 | CA45: ='META EM PEÇAS'!X34-('META EM PEÇAS'!X34*0.05) -> 2778.6075 | CB45: ='META EM PEÇAS'!Y34-('META EM PEÇAS'!Y34*0.05) -> 3342.2805 | CC45: ='META EM PEÇAS'!Z34-('META EM PEÇAS'!Z34*0.05) -> 2234.3715 | CD45: ='META EM PEÇAS'!AA34-('META EM PEÇAS'!AA34*0.05) -> 2317.4205 | CE45: ='META EM PEÇAS'!AB34-('META EM PEÇAS'!AB34*0.05) -> 2514.441 | ... CG45: ='META EM PEÇAS'!AD34-('META EM PEÇAS'!AD34*0.05) -> 4539.423 | CH45: =SUM(BV45:CG45) -> 32057.053 | CJ45: 2552.85 | CK45: 1973.46 | CL45: 2218.4685 | CM45: 2056.788 | CN45: 2307.702 | CO45: 2778.6075 | CP45: 3342.2805 | CQ45: 2234.3715 | CR45: 2317.4205 | CS45: 2514.441 | CT45: 3221.241 | CU45: 4539.423 | CV45: 32057.053 | CX45: 2552.85 | CY45: 1973.46 | CZ45: 2218.4685 | DA45: 2056.788 | DB45: 2307.702 | DC45: 2778.6075 | DD45: 3342.2805 | DE45: 2234.3715 | DF45: 2317.4205 | DG45: 2514.441 | DH45: 3221.241 | DI45: 4539.423 | DJ45: 32057.053
A46: 13 | B46: Loja Shopping Morumbi | P46: =SUM(D46:O46) -> 0 | R46: 0 | S46: 0 | T46: 0 | U46: 0 | V46: 0 | W46: 0 | X46: 2000 | Y46: 800 | Z46: 800 | AA46: 1200 | AB46: 1800 | AC46: 2300 | AD46: =SUM(R46:AC46) -> 8900 | AF46: 1800 | AG46: 1200 | AH46: =1800*0.15 -> 270 | AI46: 896 | AJ46: 1339 | AK46: 1600 | AL46: 1800 | AM46: 2000 | AN46: 2000 | AO46: 2000 | AP46: 2200 | AQ46: 3200 | AR46: =SUM(AF46:AQ46) -> 20305 | AT46: 1980 | AU46: 1980 | AV46: 1980 | AW46: 1980 | AX46: 1409 | AY46: 1409 | AZ46: 1345 | BA46: 1345 | BB46: 1409 | BC46: 1665 | BD46: 1793 | BE46: 2562 | BF46: =SUM(AT46:BE46) -> 20857 | BG46: =BF46/AR46-1 -> 0.027185422 | BT46: 11555 | BV46: 1903.71 | BW46: 1471.26 | BX46: ='META EM PEÇAS'!U35-('META EM PEÇAS'!U35*0.05) -> 1654.7955 | BY46: ='META EM PEÇAS'!V35-('META EM PEÇAS'!V35*0.05) -> 1533.756 | BZ46: ='META EM PEÇAS'!W35-('META EM PEÇAS'!W35*0.05) -> 1721.058 | CA46: ='META EM PEÇAS'!X35-('META EM PEÇAS'!X35*0.05) -> 2071.8075 | CB46: ='META EM PEÇAS'!Y35-('META EM PEÇAS'!Y35*0.05) -> 2492.3535 | CC46: ='META EM PEÇAS'!Z35-('META EM PEÇAS'!Z35*0.05) -> 1666.281 | CD46: ='META EM PEÇAS'!AA35-('META EM PEÇAS'!AA35*0.05) -> 1728.126 | CE46: ='META EM PEÇAS'!AB35-('META EM PEÇAS'!AB35*0.05) -> 1874.787 | ... CG46: ='META EM PEÇAS'!AD35-('META EM PEÇAS'!AD35*0.05) -> 3384.6885 | CH46: =SUM(BV46:CG46) -> 23904.859 | CJ46: 1903.71 | CK46: 1471.26 | CL46: 1654.7955 | CM46: 1533.756 | CN46: 1721.058 | CO46: 2071.8075 | CP46: 2492.3535 | CQ46: 1666.281 | CR46: 1728.126 | CS46: 1874.787 | CT46: 2402.2365 | CU46: 3384.6885 | CV46: 23904.859 | CX46: 1903.71 | CY46: 1471.26 | CZ46: 1654.7955 | DA46: 1533.756 | DB46: 1721.058 | DC46: 2071.8075 | DD46: 2492.3535 | DE46: 1666.281 | DF46: 1728.126 | DG46: 1874.787 | DH46: 2402.2365 | DI46: 3384.6885 | DJ46: 23904.859
A47: 14 | B47: Loja Recife | R47: 0 | S47: 0 | T47: 0 | U47: 0 | V47: 0 | W47: 0 | X47: 0 | Y47: 2000 | Z47: 800 | AA47: 800 | AB47: 1200 | AC47: 1800 | AD47: =SUM(R47:AC47) -> 6600 | AF47: 1500 | AG47: 1200 | AH47: =1500*0.15 -> 225 | AI47: 374 | AJ47: 990 | AK47: 960 | AL47: 1800 | AM47: 1200 | AN47: 1200 | AO47: 1200 | AP47: 1320 | AQ47: 1920 | AR47: =SUM(AF47:AQ47) -> 13889 | AT47: 1518 | AU47: 1518 | AV47: 1518 | AW47: 1518 | AX47: 1276 | AY47: 1276 | AZ47: 1218 | BA47: 1218 | BB47: 1276 | BC47: 1508 | BD47: 1624 | BE47: 2320 | BF47: =SUM(AT47:BE47) -> 17788 | BG47: =BF47/AR47-1 -> 0.28072575 | BT47: 19018 | BV47: 2737.92 | BW47: 2116.68 | BX47: ='META EM PEÇAS'!U36-('META EM PEÇAS'!U36*0.05) -> 2379.2655 | BY47: ='META EM PEÇAS'!V36-('META EM PEÇAS'!V36*0.05) -> 2205.216 | BZ47: ='META EM PEÇAS'!W36-('META EM PEÇAS'!W36*0.05) -> 2474.6835 | CA47: ='META EM PEÇAS'!X36-('META EM PEÇAS'!X36*0.05) -> 2980.0455 | CB47: ='META EM PEÇAS'!Y36-('META EM PEÇAS'!Y36*0.05) -> 3584.3595 | CC47: ='META EM PEÇAS'!Z36-('META EM PEÇAS'!Z36*0.05) -> 2396.052 | CD47: ='META EM PEÇAS'!AA36-('META EM PEÇAS'!AA36*0.05) -> 2485.2855 | CE47: ='META EM PEÇAS'!AB36-('META EM PEÇAS'!AB36*0.05) -> 2696.442 | ... CG47: ='META EM PEÇAS'!AD36-('META EM PEÇAS'!AD36*0.05) -> 4868.085 | CH47: =SUM(BV47:CG47) -> 34378.519 | CJ47: 2737.92 | CK47: 2116.68 | CL47: 2379.2655 | CM47: 2205.216 | CN47: 2474.6835 | CO47: 2980.0455 | CP47: 3584.3595 | CQ47: 2396.052 | CR47: 2485.2855 | CS47: 2696.442 | CT47: 3454.485 | CU47: 4868.085 | CV47: 34378.519 | CX47: 2737.92 | CY47: 2116.68 | CZ47: 2379.2655 | DA47: 2205.216 | DB47: 2474.6835 | DC47: 2980.0455 | DD47: 3584.3595 | DE47: 2396.052 | DF47: 2485.2855 | DG47: 2696.442 | DH47: 3454.485 | DI47: 4868.085 | DJ47: 34378.519
A48: 15 | B48: Porto Alegre - RS | R48: 0 | S48: 0 | T48: 0 | U48: 0 | V48: 0 | W48: 0 | X48: 0 | Y48: 0 | Z48: 2000 | AA48: 800 | AB48: 800 | AC48: 1500 | AD48: =SUM(R48:AC48) -> 5100 | AF48: 1800 | AG48: 1200 | AH48: =1800*0.4 -> 720 | AI48: 1147 | AJ48: 1155 | AK48: 1600 | AL48: 1800 | AM48: 2000 | AN48: 2000 | AO48: 2000 | AP48: 2200 | AQ48: 3200 | AR48: =SUM(AF48:AQ48) -> 20822 | AT48: 1544 | AU48: 1544 | AV48: 1544 | AW48: 1544 | AX48: 862 | AY48: 862 | AZ48: 823 | BA48: 823 | BB48: 862 | BC48: 1019 | BD48: 1098 | BE48: 1568 | BF48: =SUM(AT48:BE48) -> 14093 | BG48: =BF48/AR48-1 -> -0.3231678 | BT48: 21133 | BV48: 3593.52 | BW48: 2776.98 | BX48: ='META EM PEÇAS'!U38-('META EM PEÇAS'!U38*0.05) -> 3122.289 | BY48: ='META EM PEÇAS'!V38-('META EM PEÇAS'!V38*0.05) -> 2893.4625 | BZ48: ='META EM PEÇAS'!W38-('META EM PEÇAS'!W38*0.05) -> 3247.746 | CA48: ='META EM PEÇAS'!X38-('META EM PEÇAS'!X38*0.05) -> 3910.371 | CB48: ='META EM PEÇAS'!Y38-('META EM PEÇAS'!Y38*0.05) -> 4703.754 | CC48: ='META EM PEÇAS'!Z38-('META EM PEÇAS'!Z38*0.05) -> 3144.3765 | CD48: ='META EM PEÇAS'!AA38-('META EM PEÇAS'!AA38*0.05) -> 3260.9985 | CE48: ='META EM PEÇAS'!AB38-('META EM PEÇAS'!AB38*0.05) -> 3539.301 | ... CG48: ='META EM PEÇAS'!AD38-('META EM PEÇAS'!AD38*0.05) -> 6387.705 | CH48: =SUM(BV48:CG48) -> 45113.742 | CJ48: 3593.52 | CK48: 2776.98 | CL48: 3122.289 | CM48: 2893.4625 | CN48: 3247.746 | CO48: 3910.371 | CP48: 4703.754 | CQ48: 3144.3765 | CR48: 3260.9985 | CS48: 3539.301 | CT48: 4533.2385 | CU48: 6387.705 | CV48: 45113.742 | CX48: 3593.52 | CY48: 2776.98 | CZ48: 3122.289 | DA48: 2893.4625 | DB48: 3247.746 | DC48: 3910.371 | DD48: 4703.754 | DE48: 3144.3765 | DF48: 3260.9985 | DG48: 3539.301 | DH48: 4533.2385 | DI48: 6387.705 | DJ48: 45113.742
A49: 16 | B49: E-Commerce | AA49: 800 | AB49: 800 | AC49: 1500 | AF49: 1500 | AG49: 1200 | AH49: =1500*0.15 -> 225 | AI49: 192 | AJ49: 663 | AK49: 800 | AL49: 1500 | AM49: 1000 | AN49: 1000 | AO49: 1000 | AP49: 1100 | AQ49: 1600 | AR49: =SUM(AF49:AQ49) -> 11780 | AT49: 960 | AU49: 960 | AV49: 960 | AW49: 960 | AX49: 1414 | AY49: 1414 | AZ49: 1350 | BA49: 1350 | BB49: 1414 | BC49: 1671 | BD49: 1800 | BE49: 2571 | BF49: =SUM(AT49:BE49) -> 16824 | BG49: =BF49/AR49-1 -> 0.42818336 | BH49: 900 | BI49: 643 | BJ49: 891 | BK49: 679 | BL49: 940 | BM49: 948 | BN49: 1124 | BO49: 913 | BP49: 911 | BQ49: 898 | BR49: 1465 | BS49: 1278 | BT49: =SUM(BH49:BS49) -> 11590 | BV49: ='META EM PEÇAS'!T47 -> 1749.7325 | BW49: ='META EM PEÇAS'!T48 -> 1701.1288 | BX49: ='META EM PEÇAS'!T49 -> 1846.9398 | BY49: ='META EM PEÇAS'!T50 -> 1701.1288 | BZ49: ='META EM PEÇAS'!T51 -> 1846.9398 | CA49: ='META EM PEÇAS'!T52 -> 1749.7325 | CB49: ='META EM PEÇAS'!T53 -> 2138.5619 | CC49: ='META EM PEÇAS'!T54 -> 1749.7325 | CD49: ='META EM PEÇAS'!T55 -> 1749.7325 | CE49: ='META EM PEÇAS'!T56 -> 1749.7325 | CF49: ='META EM PEÇAS'!T57 -> 2721.8061 | CG49: ='META EM PEÇAS'!T58 -> 1944.1472 | CH49: =SUM(BV49:CG49) -> 22649.315 | CJ49: 1749.7325 | CK49: 1701.1288 | CL49: 1846.9398 | CM49: 1701.1288 | CN49: 1846.9398 | CO49: 1749.7325 | CP49: 2138.5619 | CQ49: 1749.7325 | CR49: 1749.7325 | CS49: 1749.7325 | CT49: 2721.8061 | CU49: 1944.1472 | CV49: 22649.315 | CX49: 1749.7325 | CY49: 1701.1288 | CZ49: 1846.9398 | DA49: 1701.1288 | DB49: 1846.9398 | DC49: 1749.7325 | DD49: 2138.5619 | DE49: 1749.7325 | DF49: 1749.7325 | DG49: 1749.7325 | DH49: 2721.8061 | DI49: 1944.1472 | DJ49: 22649.315
AF50: 0 | AG50: 0 | AH50: 0 | AI50: 0 | AJ50: 0 | AK50: 400 | AL50: 500 | AM50: 500 | AN50: 600 | AO50: 600 | AP50: 660 | AQ50: 960 | AR50: =SUM(AF50:AQ50) -> 4220 | AT50: 960 | AU50: 960 | AV50: 960 | AW50: 960 | AX50: 580 | AY50: 580 | AZ50: 554 | BA50: 554 | BB50: 580 | BC50: 686 | BD50: 739 | BE50: 1055 | BF50: =SUM(AT50:BE50) -> 9168 | BG50: =BF50/AR50-1 -> 1.1725118
AF51: 0 | AG51: 0 | AH51: 0 | AI51: 0 | AJ51: 0 | AK51: 0 | AL51: 2500 | AM51: 2000 | AN51: 500 | AO51: 600 | AP51: 660 | AQ51: 960 | AR51: =SUM(AF51:AQ51) -> 7220 | AT51: 1518 | AU51: 1518 | AV51: 1518 | AW51: 1518 | AX51: 1943 | AY51: 1943 | AZ51: 1854 | BA51: 1854 | BB51: 1943 | BC51: 2296 | BD51: 2472 | BE51: 3532 | BF51: =SUM(AT51:BE51) -> 23909 | BG51: =BF51/AR51-1 -> 2.3114958
AF52: 0 | AG52: 0 | AH52: 0 | AI52: 0 | AJ52: 0 | AK52: 0 | AL52: 0 | AM52: 0 | AN52: 0 | AO52: 0 | AP52: 0 | AQ52: 0 | AR52: =SUM(AF52:AQ52) -> 0 | AT52: 0 | AU52: 0 | AV52: 0 | AW52: 0 | AX52: 800 | AY52: 800 | AZ52: 800 | BA52: 1050 | BB52: 1100 | BC52: 1300 | BD52: 1400 | BE52: 2000 | BF52: =SUM(AT52:BE52) -> 9250 | BG52: =BF52/AR52-1 -> #DIV/0!
BD53: 600 | BE53: 700 | BF53: =SUM(AT53:BE53) -> 1300 | CB53: 60 | CJ53: =(CJ55-CJ54)/CJ54 -> 0.03 | CK53: =(CK55-CK54)/CK54 -> 0.03 | CL53: =(CL55-CL54)/CL54 -> 0.03 | CM53: =(CM55-CM54)/CM54 -> 0.03 | CN53: =(CN55-CN54)/CN54 -> 0.03 | CO53: =(CO55-CO54)/CO54 -> 0.03 | CP53: =(CP55-CP54)/CP54 -> 0.03 | CQ53: =(CQ55-CQ54)/CQ54 -> 0.03 | ... CU53: =(CU55-CU54)/CU54 -> 0.03
B54: E-Commerce | P54: =SUM(D54:O54) -> 0 | R54: 350 | S54: 350 | T54: 450 | U54: 800 | V54: 531 | W54: 750 | X54: 650 | Y54: 750 | Z54: 900 | AA54: 1000 | AB54: 1200 | AC54: 1500 | AD54: =SUM(R54:AC54) -> 9231 | AF54: 1500 | AG54: 800 | AH54: 800 | AI54: 1820 | AJ54: 1630 | AK54: 1360 | AL54: 1000 | AM54: 1700 | AN54: 1700 | AO54: 1700 | AP54: 1870 | AQ54: 2720 | AR54: =SUM(AF54:AQ54) -> 18600 | AT54: 2053 | AU54: 2053 | AV54: 2053 | AW54: 2053 | AX54: 2807 | AY54: 2807 | AZ54: 2680 | BA54: 2680 | BB54: 2807 | BC54: 3318 | BD54: 5870 | BE54: 5104 | BF54: =SUM(AT54:BE54) -> 36285 | BG54: =BF54/AR54-1 -> 0.95080645 | BT54: =SUM(BH54:BS54) -> 0 | CJ54: =BV64 -> 38900 | CK54: =BW64 -> 31376 | CL54: =BX64 -> 29886 | CM54: =BY64 -> 30671 | CN54: =BZ64 -> 34553 | CO54: =CA64 -> 36515 | CP54: =CB64 -> 38915 | CQ54: =CC64 -> 34615 | ... CU54: =CG64 -> 60875
B55: Estimativa Lojas | D55: =SUM(D34:D54) -> 0 | E55: =SUM(E34:E54) -> 0 | F55: =SUM(F34:F54) -> 0 | G55: =SUM(G34:G54) -> 0 | H55: =SUM(H34:H54) -> 0 | I55: =SUM(I34:I54) -> 0 | J55: =SUM(J34:J54) -> 0 | K55: =SUM(K34:K54) -> 0 | ... O55: =SUM(O34:O54) -> 0 | P55: =SUM(D55:O55) -> 0 | R55: =SUM(R34:R54) -> 20557.544 | S55: =SUM(S34:S54) -> 20512.544 | T55: =SUM(T34:T54) -> 13699.772 | U55: =SUM(U34:U54) -> 912.5 | V55: =SUM(V34:V54) -> 16851 | W55: =SUM(W34:W54) -> 13700 | X55: =SUM(X34:X54) -> 26050 | Y55: =SUM(Y34:Y54) -> 27750 | ... AC55: =SUM(AC34:AC54) -> 45300 | AD55: =SUM(R55:AC55) -> 286033.36 | AF55: =SUM(AF34:AF54) -> 38500 | AG55: =SUM(AG34:AG54) -> 22400 | AH55: =SUM(AH34:AH54) -> 10671 | AI55: =SUM(AI34:AI54) -> 16097 | AJ55: =SUM(AJ34:AJ54) -> 30278 | AK55: =SUM(AK34:AK54) -> 28560 | AL55: =SUM(AL34:AL54) -> 41700 | AM55: =SUM(AM34:AM54) -> 38700 | ... AQ55: =SUM(AQ34:AQ54) -> 54440 | AR55: =SUM(AF55:AQ55) -> 396686 | AT55: =SUM(AT34:AT54) -> 36153 | AU55: =SUM(AU34:AU54) -> 35289 | AV55: =SUM(AV34:AV54) -> 35872 | AW55: =SUM(AW34:AW54) -> 38031 | AX55: =SUM(AX34:AX54) -> 33566 | AY55: =SUM(AY34:AY54) -> 33566 | AZ55: =SUM(AZ34:AZ54) -> 30896 | BA55: =SUM(BA34:BA54) -> 31146 | ... BE55: =SUM(BE34:BE54) -> 49263 | BF55: =SUM(AT55:BE55) -> 436319 | BG55: =BF55-AR55 -> 39633 | BH55: 36153 | BI55: 35289 | BJ55: 35872 | BK55: 38031 | BL55: 38570 | BM55: 39227 | BN55: 41128 | BO55: 38191 | BP55: 38191 | BQ55: 40225 | BR55: 43272 | BS55: 60327 | BT55: =SUM(BH55:BS55) -> 484476 | BV55: =SUM(BV34:BV51) -> 35797.912 | BW55: =SUM(BW34:BW51) -> 27268.539 | BX55: =SUM(BX34:BX51) -> 34357.669 | BY55: =SUM(BY34:BY51) -> 29626.958 | BZ55: =SUM(BZ34:BZ51) -> 34139.121 | CA55: =SUM(CA34:CA51) -> 39503.882 | CB55: =SUM(CB34:CB51) -> 45728.837 | CC55: =SUM(CC34:CC51) -> 32260.227 | ... CG55: =SUM(CG34:CG51) -> 57905.503 | CH55: =SUM(BV55:CG55) -> 451302.93 | CI55: =(CH55-BT64)/BT64 -> 0.051833719 | CJ55: =BV64*1.03 -> 40067 | CK55: =BW64*1.03 -> 32317.28 | CL55: =BX64*1.03 -> 30782.58 | CM55: =BY64*1.03 -> 31591.13 | CN55: =BZ64*1.03 -> 35589.59 | CO55: =CA64*1.03 -> 37610.45 | CP55: =CB64*1.03 -> 40082.45 | CQ55: =CC64*1.03 -> 35653.45 | ... CU55: =CG64*1.03 -> 62701.25 | CV55: =SUM(CJ55:CU55) -> 459766.25 | CW55: =(CV55-CH64)/CH64 -> 0.03 | CX55: 35797.912 | CY55: 27268.539 | CZ55: 34357.669 | DA55: 29626.958 | DB55: 34139.121 | DC55: 39503.882 | DD55: 45728.837 | DE55: 32260.227 | DF55: 33331.523 | DG55: 35213.881 | DH55: 46168.878 | DI55: 57905.503 | DJ55: 451302.93
B56: Estimativa lojas - Transferência - expectativa de 80% a menos que a venda | AY56: 15000 | AZ56: 15000 | BA56: =BA55*70% -> 21802.2 | BB56: =BB55*70% -> 22841 | BC56: 35000 | BD56: 35000 | BE56: 42000 | BF56: =SUM(AT56:BE56) -> 186643.2 | BH56: =BH55*0.8 -> 28922.4 | BI56: =BI55*0.8 -> 28231.2 | BJ56: =BJ55*0.8 -> 28697.6 | BK56: =BK55*0.8 -> 30424.8 | BL56: =BL55*0.8 -> 30856 | BM56: =BM55*0.8 -> 31381.6 | BN56: =BN55*0.85 -> 34958.8 | BO56: 29000 | BP56: 40223 | BQ56: 36735 | BR56: 36933 | BS56: 52283 | BT56: =SUM(BH56:BS56) -> 408646.4 | BV56: 32000 | BW56: 32000 | BX56: 37000 | BY56: 32000 | BZ56: 35000 | CA56: 35000 | CB56: 35000 | CC56: =CC55*1 -> 32260.227 | CD56: =CD55*1 -> 33331.523 | CE56: =CE55 -> 35213.881 | CF56: 40000 | CG56: 60000 | CJ56: 32000 | CK56: 30000 | CL56: 31500 | CM56: 32000 | CN56: 35000 | CO56: 35000 | CP56: 36000 | CQ56: 35000 | CR56: 35000 | CS56: 40000 | CT56: 51000 | CU56: 60000 | CV56: =SUM(CJ56:CU56) -> 452500 | CX56: 28638.33 | CY56: 21814.831 | CZ56: 27486.135 | DA56: 23701.567 | DB56: 27311.297 | DC56: 31603.106 | DD56: 36583.07 | DE56: 25808.182 | DF56: 26665.218 | DG56: 28171.105 | DH56: 36935.102 | DI56: 46324.402
A57: FATURAMENTO EXPEDIÇÃO META | AL57: =AL55/AVERAGE($AF$55:$AQ$55) -> 1.2614511 | AP57: =AP55/AVERAGE($AF$55:$AQ$55) -> 1.2293855 | AQ57: =AQ55/AVERAGE($AF$55:$AQ$55) -> 1.6468441 | AT57: 109190 | AU57: 153667 | AV57: 178778 | AW57: 151970 | AX57: 142416 | AY57: 177335 | AZ57: 152230 | BA57: 245527 | BB57: =5261504/27 -> 194870.52 | BC57: =5784000/27 -> 214222.22 | BD57: =3224000/27 -> 119407.41 | BE57: =909800/27 -> 33696.296 | BF57: =SUM(AT57:BE57) -> 1873309.4 | BH57: 156208 | BI57: 147340 | BJ57: 166759 | BK57: 152352 | BL57: 128446 | BM57: 126790 | BN57: 173761 | BO57: =144510.599073001+BO56 -> 173510.6 | BP57: =162574.422556972+BP56 -> 202797.42 | BQ57: =166187.186558517+BQ56 -> 202922.19 | BR57: =BQ31+BR27*0.6 -> 232502.36 | BS57: =BR27*0.4+BS27*0.5 -> 116391.04 | BT57: =SUM(BH57:BS57) -> 1979779.6 | BV57: =BV31+BV56 -> 162757.87 | BW57: =BW31+BW56 -> 157566.83 | BX57: =BX31+BX56 -> 197961.54 | BY57: =BY31+BY56 -> 160769.23 | BZ57: =BZ31+BZ56 -> 153232.39 | CA57: =CA31+CA56 -> 143192.13 | CB57: =CB31+CB56 -> 178736.21 | CC57: =CC31+CC56 -> 202914.1 | ... CF57: =CF31+CF56 -> 173115.84 | CG57: =BS57 -> 116391.04 | CJ57: =CJ31+CJ56 -> 184850.74 | CK57: =CK31+CK56 -> 171882.51 | CL57: =CL31+CL56 -> 191983.4 | CM57: =CM31+CM56 -> 165270.48 | CN57: =CN31+CN56 -> 157242.75 | CO57: =CO31+CO56 -> 123621.68 | CP57: =CP31+CP56 -> 231213.55 | CQ57: =CQ31+CQ56 -> 211318.73 | ... CU57: =CU31+CU56 -> 107560.73 | CV57: =SUM(CJ57:CU57) -> 2217192.6 | CX57: 98000 | CY57: 147381.66 | CZ57: 188447.67 | DA57: 152352 | DB57: 128446 | DC57: 126790 | DD57: 173761 | DE57: 173510.6 | DF57: 202797.42 | DG57: 202922.19 | DH57: 232502.36 | DI57: 116391.04
A58: FATURAMENTO REAL | AF58: 133791 | AG58: 166459 | AH58: 149450 | AI58: 151073 | AJ58: 192944 | AK58: 166139 | AL58: 151874 | AM58: 157771 | AN58: 200312 | AO58: 202691 | AP58: 207768 | AQ58: 113286 | AR58: =SUM(AF58:AK58) -> 959856 | AT58: 89680 | AU58: 128308 | AV58: 144871 | AW58: 161772 | AX58: 144516 | AY58: 103667 | AZ58: 141023 | BA58: 172093 | BB58: =166606+10000 -> 176606 | BC58: 181091 | BD58: 169802 | BE58: 120406 | BF58: =SUM(AT58:BE58) -> 1733835 | BG58: =BG55/AR55 -> 0.099910256 | BH58: 78906 | BI58: 119296 | BJ58: 165286 | BK58: 144532 | BL58: 157691 | BM58: 129096 | BN58: 125800 | BO58: 176354 | BP58: 173554 | BQ58: 185766 | BT58: =SUM(BH58:BS58) -> 1456281
B59: Desvio Faturamento Real -Previsto | AF59: =AF58-AF26 -> 133789.57 | AG59: =AG58-AG26 -> 166455.03 | AH59: =AH58-AH26 -> 149445.55 | AI59: =AI58-AI26 -> 151069.82 | AJ59: =AJ58-AJ26 -> 192941.24 | AK59: =AK58-AK26 -> 166135.77 | AL59: =AL58-AL26 -> 151871.64 | AM59: =AM58-AM26 -> 157768.86 | ... AQ59: =AQ58-AQ26 -> 113282.52 | AR59: =SUM(AF59:AQ59) -> 1993520.8 | AT59: =AT58-AT57 -> -19510 | AU59: =AU58-AU57 -> -25359 | AV59: =AV58-AV57 -> -33907 | AW59: =AW58-AW57 -> 9802 | AX59: =AX58-AX57 -> 2100 | AY59: =AY58-AY57 -> -73668 | AZ59: =AZ58-AZ57 -> -11207 | BA59: =BA58-BA57 -> -73434 | ... BE59: =BE58-BE57 -> 86709.704 | BF59: =SUM(AT59:BE59) -> -139474.44 | BH59: =BH58-BH57 -> -77302 | BI59: =BI58-BI57 -> -28044 | BJ59: =BJ58-BJ57 -> -1473 | BK59: =BK58-BK57 -> -7820 | BL59: =BL58-BL57 -> 29245 | BM59: =BM58-BM57 -> 2306 | BN59: =BN58-BN57 -> -47961 | BO59: =BO58-BO57 -> 2843.4009 | ... BQ59: =BQ58-BQ57 -> -17156.187 | BT59: =SUM(BH59:BS59) -> -174605.21
A60: 5 | B60: Pendente de Faturamento | O60: 0 | P60: =SUM(D60:O60) -> 0 | AD60: =SUM(R60:AC60) -> 0 | AF60: 0 | AG60: 0 | AH60: 0 | AI60: 0 | AJ60: 0 | AK60: 0 | AL60: 0 | AM60: 0 | AN60: 0 | AO60: 0 | AQ60: 8938 | AR60: =SUM(AF60:AQ60) -> 8938 | AT60: 106642 | AU60: 90699 | AV60: 89681 | AW60: 58790 | AX60: 35520 | AY60: 61551 | AZ60: 71511 | BA60: 63617 | BB60: 66748 | BC60: 75532 | BD60: 37786 | BE60: 4503 | BF60: =SUM(AT60:BE60) -> 762580 | BH60: 69404 | BI60: 80412 | BJ60: 94386 | BK60: 78313 | BL60: 47034 | BM60: 50851 | BN60: 93202 | BO60: 100687 | BP60: 127995 | BQ60: 122686
A61: VENDA REAL | AF61: =AF62+AF64 -> 118364 | AG61: =AG62+AG64 -> 173742 | AH61: =AH62+AH64 -> 73470 | AI61: =AI62+AI64 -> 87377 | AJ61: =AJ62+AJ64 -> 119657 | AK61: =AK62+AK64 -> 154747 | AL61: =AL62+AL64 -> 138073 | AM61: =AM62+AM64 -> 180773 | ... AQ61: =AQ62+AQ64 -> 87384 | AR61: =SUM(AF61:AQ61) -> 1678462 | AT61: =AT62+AT64 -> 155346 | AU61: =AU62+AU64 -> 123370 | AV61: =AV62+AV64 -> 144065 | AW61: =AW62+AW64 -> 127865 | AX61: =AX62+AX64 -> 123461 | AY61: =AY62+AY64 -> 121196 | AZ61: =AZ62+AZ64 -> 168029 | BA61: =BA62+BA64 -> 164268 | ... BE61: =BE62+BE64 -> 90194 | BF61: =SUM(AT61:BE61) -> 1685749 | BG61: =BF61/AR61-1 -> 0.0043414745 | BH61: =BH62+BH64 -> 144332 | BI61: =BI62+BI64 -> 128781 | BJ61: =BJ62+BJ64 -> 193129 | BK61: =BK62+BK64 -> 106092 | BL61: =BL62+BL64 -> 132638 | BM61: =BM62+BM64 -> 139193 | BN61: =BN62+BN64 -> 173703 | BO61: =BO62+BO64 -> 186902 | ... BQ61: =BQ62+BQ64 -> 191324 | BT61: =SUM(BH61:BS61) -> 1596780 | CJ61: =CJ62+CJ64 -> 204853
B62: Varejo | AF62: 92193 | AG62: 152006 | AH62: 62734 | AI62: 71526 | AJ62: 89409 | AK62: 120675 | AL62: 100592 | AM62: 148128 | AN62: 164346 | AO62: 203437 | AP62: 64957 | AQ62: 31837 | AR62: =SUM(AF62:AQ62) -> 1301840 | AT62: 125048 | AU62: 96006 | AV62: 111470 | AW62: 99222 | AX62: 91253 | AY62: 90595 | AZ62: 129147 | BA62: 133525 | BB62: 159291 | BC62: 115573 | BD62: 98386 | BE62: 36527 | BF62: =SUM(AT62:BE62) -> 1286043 | BG62: =BF62/AR62-1 -> -0.012134364 | BH62: 110235 | BI62: 103047 | BJ62: 158855 | BK62: 77254 | BL62: 99853 | BM62: 100723 | BN62: 125338 | BO62: 153622 | BP62: 166483 | BQ62: 156140 | BR62: 111391 | BS62: 26768 | BT62: =SUM(BH62:BS62) -> 1389709 | BV62: 128446 | BW62: 119229 | BX62: 134860 | BY62: 111992 | BZ62: 102725 | CA62: 74472 | CB62: 164045 | CC62: 148167 | CD62: 189715 | CE62: 165488 | CF62: 103829 | CG62: 39967 | CH62: =SUM(BV62:CG62) -> 1482935 | CJ62: 167136 | CX62: 54245
B63: VENDA EM LINHA relizada fabrica | AF63: =AF62-AF31 -> 2047 | AG63: =AG62-AG31 -> -3571 | AH63: =AH62-AH31 -> -219 | AI63: =AI62-AI31 -> -1735 | AJ63: =AJ62-AJ31 -> -2447 | AK63: =AK62-AK31 -> 675 | AL63: =AL62-AL31 -> -9703 | AM63: =AM62-AM31 -> -52075 | ... AQ63: =AQ62-AQ31 -> -11563 | AR63: =SUM(AF63:AQ63) -> -176184.33 | AT63: =AT62-AT31 -> 8451.75 | AU63: =AU62-AU31 -> -37227.103 | AV63: =AV62-AV31 -> -6779.1379 | AW63: =AW62-AW31 -> -22342.138 | AX63: =AX62-AX31 -> 4719.0345 | AY63: =AY62-AY31 -> -14182.778 | AZ63: =AZ62-AZ31 -> -6630.7778 | BA63: =BA62-BA31 -> -77771.296 | ... BE63: =BE62-BE31 -> 5840.387 | BF63: =SUM(AT63:BE63) -> -291466.72 | BH63: =BH62-BH28 -> -6365 | BI63: =BI62-BI28 -> -8486.3333 | BJ63: =BJ62-BJ28 -> 23180.926 | BK63: =BK62-BK28 -> -44486.741 | BL63: =BL62-BL28 -> 5926.1481 | BM63: =BM62-BM28 -> 10043.741 | BN63: =BN62-BN28 -> -4917.5556 | BO63: =BO62-BO28 -> 3071.6219 | ... BQ63: =BQ62-BQ28 -> 29010 | BT63: =SUM(BH63:BS63) -> 11629.058 | BV63: 124435 | BW63: 117564 | BX63: 133262 | BY63: 110312 | BZ63: 101441 | CA63: 67535 | CB63: 155594 | CH63: =SUM(BV63:CG63) -> 810143 | CJ63: 159683 | CK63: 182683 | CL63: 137562
B64: Loja | AF64: 26171 | AG64: 21736 | AH64: 10736 | AI64: 15851 | AJ64: 30248 | AK64: 34072 | AL64: 37481 | AM64: 32645 | AN64: 30252 | AO64: 39494 | AP64: 42389 | AQ64: 55547 | AR64: =SUM(AF64:AQ64) -> 376622 | AT64: 30298 | AU64: 27364 | AV64: 32595 | AW64: 28643 | AX64: 32208 | AY64: 30601 | AZ64: 38882 | BA64: 30743 | BB64: =24621+1200 -> 25821 | BC64: 31662 | BD64: 37222 | BE64: 53667 | BF64: =SUM(AT64:BE64) -> 399706 | BG64: =BF64/AR64-1 -> 0.061292224 | BH64: 34097 | BI64: 25734 | BJ64: 34274 | BK64: 28838 | BL64: 32785 | BM64: 38470 | BN64: 48365 | BO64: 33280 | BP64: 34203 | BQ64: 35184 | BR64: 34873 | BS64: 48960 | BT64: =SUM(BH64:BS64) -> 429063 | BV64: 38900 | BW64: 31376 | BX64: 29886 | BY64: 30671 | BZ64: 34553 | CA64: 36515 | CB64: 38915 | CC64: 34615 | CD64: 29617 | CE64: 34538 | CF64: 45914 | CG64: 60875 | CH64: =SUM(BV64:CG64) -> 446375 | CJ64: 37717 | CX64: 22115
B65: META DE VENDA LOJA EM LINHA | AF65: =AF64-AF55 -> -12329 | AG65: =AG64-AG55 -> -664 | AH65: =AH64-AH55 -> 65 | AI65: =AI64-AI55 -> -246 | AJ65: =AJ64-AJ55 -> -30 | AK65: =AK64-AK55 -> 5512 | AL65: =AL64-AL55 -> -4219 | AM65: =AM64-AM55 -> -6055 | ... AQ65: =AQ64-AQ55 -> 1107 | AR65: =SUM(AF65:AQ65) -> -20064 | AT65: =AT64-AT55 -> -5855 | AU65: =AU64-AU55 -> -7925 | AV65: =AV64-AV55 -> -3277 | AW65: =AW64-AW55 -> -9388 | AX65: =AX64-AX55 -> -1358 | AY65: =AY64-AY55 -> -2965 | AZ65: =AZ64-AZ55 -> 7986 | BA65: =BA64-BA55 -> -403 | ... BE65: =BE64-BE55 -> 4404 | BF65: =SUM(AT65:BE65) -> -36613 | BH65: =BH64-BH55 -> -2056 | BI65: =BI64-BI55 -> -9555 | BJ65: =BJ64-BJ55 -> -1598 | BK65: =BK64-BK55 -> -9193 | BL65: =BL64-BL55 -> -5785 | BM65: =BM64-BM55 -> -757 | BN65: =BN64-BN55 -> 7237 | BO65: =BO64-BO55 -> -4911 | ... BQ65: =BQ64-BQ55 -> -5041 | BT65: =SUM(BH65:BS65) -> -35647 | BV65: 27740 | BW65: 23272 | BX65: 24576 | BY65: 26006 | BZ65: 30640 | CA65: 30640 | CB65: 29618 | CC65: 29686 | CD65: 29993 | CE65: 31540 | CF65: 38086 | CG65: 54003 | CH65: =SUM(BV65:CG65) -> 375800 | CJ65: =BV65*1.03 -> 28572.2 | CK65: =BW65*1.03 -> 23970.16 | CL65: =BX65*1.03 -> 25313.28 | CM65: =BY65*1.03 -> 26786.18 | CN65: =BZ65*1.03 -> 31559.2 | CO65: =CA65*1.03 -> 31559.2 | CP65: =CB65*1.03 -> 30506.54 | CQ65: =CC65*1.03 -> 30576.58 | ... CU65: =CG65*1.03 -> 55623.09 | CV65: =SUM(CJ65:CU65) -> 387074
A66: Desvio Venda Real-Previsto | B66: VENDA REALIZADA LOJA EM LINHA | AF66: =AF61-AF27 -> -10282 | AG66: =AG61-AG27 -> -4235 | AH66: =AH61-AH27 -> -154 | AI66: =AI61-AI27 -> -1981 | AJ66: =AJ61-AJ27 -> -2477 | AK66: =AK61-AK27 -> 6187 | AL66: =AL61-AL27 -> -13922 | AM66: =AM61-AM27 -> -58130 | ... AQ66: =AQ61-AQ27 -> -10456 | AR66: =SUM(AF66:AQ66) -> -196248.33 | AT66: =AT61-AT27 -> 2596.75 | AU66: =AU61-AU27 -> -45152.103 | AV66: =AV61-AV27 -> -10056.138 | AW66: =AW61-AW27 -> -31730.138 | AX66: =AX61-AX27 -> 3361.0345 | AY66: =AY61-AY27 -> -17147.778 | AZ66: =AZ61-AZ27 -> 1355.2222 | BA66: =BA61-BA27 -> -78174.296 | ... BE66: =BE61-BE27 -> 17507.387 | BF66: =SUM(AT66:BE66) -> -320816.72 | BH66: =BH61-BH27 -> -8421 | BI66: =BI61-BI27 -> -18041.333 | BJ66: =BJ61-BJ27 -> 21582.926 | BK66: =BK61-BK27 -> -53679.741 | BL66: =BL61-BL27 -> 141.14815 | BM66: =BM61-BM27 -> 9286.7407 | BN66: =BN61-BN27 -> 2319.4444 | BO66: =BO61-BO27 -> 7351.6219 | ... BQ66: =BQ61-BQ27 -> 27459 | BT66: =SUM(BH66:BS66) -> -13368.942 | CB66: =CB65+CB62 -> 193663 | CC66: =CC65+CC62 -> 177853 | CD66: =CD65+CD62 -> 219708 | CE66: =CE65+CE62 -> 197028 | CF66: =CF65+CF62 -> 141915 | CG66: =CG65+CG62 -> 93970 | CJ66: 27785 | CK66: 23447 | CL66: 26944
A67: Desvio Venda Real-Previsto % | AF67: =AF62-AF28 -> 92193 | AG67: =AG62-AG28 -> 152006 | AH67: =AH62-AH28 -> 62734 | AI67: =AI62-AI28 -> 71526 | AJ67: =AJ62-AJ28 -> 89409 | AK67: =AK62-AK28 -> 120675 | AL67: =AL62-AL28 -> 100592 | AM67: =AM62-AM28 -> 148128 | ... AQ67: =AQ62-AQ28 -> 31837 | AR67: =SUM(AF67:AQ67) -> 1301840 | AT67: =AT66/AT27 -> 0.017000083 | AU67: =AU66/AU27 -> -0.26792986 | AV67: =AV66/AV27 -> -0.065248272 | AW67: =AW66/AW27 -> -0.19881644 | AX67: =AX66/AX27 -> 0.027985308 | AY67: =AY66/AY27 -> -0.12395048 | AZ67: =AZ66/AZ27 -> 0.0081309864 | BA67: =BA66/BA27 -> -0.32244496 | ... BE67: =BE66/BE27 -> 0.24086123 | BF67: =AVERAGE(AT67:BE67) -> -0.11124824 | BH67: =BH66/BH27 -> -0.055128214 | BI67: =BI66/BI27 -> -0.12287867 | BJ67: =BJ66/BJ27 -> 0.12581416 | BK67: =BK66/BK27 -> -0.33597769 | BL67: =BL66/BL27 -> 0.0010652944 | BM67: =BM66/BM27 -> 0.071488016 | BN67: =BN66/BN27 -> 0.013533646 | BO67: =BO66/BO27 -> 0.040944619 | ... BQ67: =BQ66/BQ27 -> 0.16757087 | BT67: =BT66/BT27 -> -0.0071185037
A68: A Produzir no Mês corrente
B69: venda realizada em linha | BV69: 152642 | BW69: 141495 | BX69: 158268 | BY69: 135742 | BZ69: 130614 | CA69: 97296 | CB69: 180319 | CC69: 175137 | CD69: 216035 | CE69: 188049 | CF69: 139782 | CG69: 90604 | CH69: =SUM(BV69:CG69) -> 1805983 | CJ69: x | CK69: =BW69 -> 141495 | CL69: =BX69 -> 158268 | CM69: =BY69 -> 135742 | CN69: =BZ69 -> 130614 | CO69: =CA69 -> 97296 | CP69: =CB69 -> 180319 | CQ69: =CC69 -> 175137 | CR69: =CD69 -> 216035 | CS69: =CS70 -> 229416.92 | CT69: =CT70 -> 162785.09 | CU69: =CU70 -> 103183.82 | CV69: =CH69 -> 1805983
B70: venda prevista em linha | BV70: =BV27 -> 161157.87 | BW70: =BW27 -> 155966.83 | BX70: =BX27 -> 196111.54 | BY70: =BY27 -> 159169.23 | BZ70: =BZ27 -> 151482.39 | CA70: =CA27 -> 141442.13 | CB70: =CB27 -> 176986.21 | CC70: =CC27 -> 201301.09 | ... CG70: =CG27 -> 87483.817 | CH70: =SUM(BV70:CG70) -> 2030972.3 | CJ70: =CJ27 -> 181422.94 | CK70: =CK27 -> 165852.67 | CL70: =CL27 -> 185796.68 | CM70: =CM27 -> 160056.66 | CN70: =CN27 -> 153801.95 | CO70: =CO27 -> 120180.88 | CP70: =CP27 -> 225720.09 | CQ70: =CQ27 -> 206895.31 | ... CU70: =CU27 -> 103183.82 | CV70: =SUM(CJ70:CU70) -> 2151766.6 | CX70: =CX27 -> 190494.09 | CY70: =CY27 -> 174145.3 | CZ70: =CZ27 -> 195086.51 | DA70: =DA27 -> 168059.49 | DB70: =DB27 -> 161492.05 | DC70: =DC27 -> 126189.92 | DD70: =DD27 -> 237006.09 | DE70: =DE27 -> 217240.08 | ... DI70: =DI27 -> 108343.01 | DJ70: =SUM(CX70:DI70) -> 2259355
A71: 7 | B71: Total Produção Projetada | D71: 98048 | E71: 128688 | F71: 124704 | G71: 157500 | H71: 182600 | I71: 157700 | J71: 181700 | K71: 165900 | L71: 174300 | M71: 215800 | N71: 180000 | O71: 112500 | P71: =SUM(D71:O71) -> 1879440 | R71: 158400 | S71: 161000 | T71: 117800 | U71: 2000 | V71: 53800 | W71: 190600 | X71: 187900 | Y71: 196800 | Z71: 192300 | AA71: 182300 | AB71: 175000 | AC71: 134100 | AD71: =SUM(R71:AC71) -> 1752000 | AF71: =SUM(AF72,AF74) -> 161400 | AG71: =SUM(AG72,AG74) -> 166000 | AH71: =SUM(AH72,AH74) -> 150471 | AI71: =SUM(AI72,AI74) -> 149040 | AJ71: =SUM(AJ72,AJ74) -> 196360 | AK71: =SUM(AK72,AK74) -> 163300 | AL71: =SUM(AL72,AL74) -> 190000 | AM71: =SUM(AM72,AM74,AM75) -> 167000 | AN71: =SUM(AN72,AN74,AN75) -> 170500 | AO71: =SUM(AO72,AO74,AO75) -> 140000 | AP71: =SUM(AP72,AP74,AP75) -> 130000 | AQ71: =SUM(AQ72,AQ74,AQ75) -> 100000 | AR71: =SUM(AF71:AQ71) -> 1884071 | AT71: =SUM(AT72,AT74,AT75) -> 133000 | AU71: =SUM(AU72,AU74,AU75) -> 125180 | AV71: =SUM(AV72,AV74,AV75) -> 117228 | AW71: =SUM(AW72,AW74,AW75) -> 127500 | AX71: =SUM(AX72,AX74,AX75) -> 140000 | AY71: =SUM(AY72,AY74,AY75) -> 158343 | AZ71: =SUM(AZ72,AZ74,AZ75) -> 152409 | BA71: =SUM(BA72,BA74,BA75) -> 173520 | ... BC71: =SUM(BC72,BC74,BC75) -> 157500 | BD71: 129431 | BE71: 61700 | BF71: =SUM(AT71:BE71) -> 1640811 | BG71: =BF71-AR71 -> -243260 | BH71: =SUM(BH72,BH74,BH75) -> 139760 | BI71: =SUM(BI72,BI74,BI75) -> 116580 | BJ71: =SUM(BJ72,BJ74,BJ75) -> 148340 | BK71: =SUM(BK72,BK74,BK75) -> 112360 | BL71: =SUM(BL72,BL74,BL75) -> 108660 | BM71: =SUM(BM72,BM74,BM75) -> 153416 | BN71: =SUM(BN72,BN74,BN75) -> 137676 | BO71: =SUM(BO72,BO74,BO75) -> 160654 | BP71: =SUM(BP72,BP74,BP75) -> 157000 | BQ71: 156725 | BR71: 182069 | BS71: =BS72+BS75 -> 156420 | BT71: =SUM(BH71:BS71) -> 1729660 | BV71: =BV7*BV73 -> 133000 | BW71: =BW7*BW73 -> 133000 | BX71: =BX7*BX73 -> 147000 | BY71: =BY7*BY73 -> 172800 | BZ71: =BZ7*BZ73 -> 165600 | CA71: =CA7*CA73 -> 158400 | CB71: =CB7*CB73 -> 180000 | CC71: =CC7*CC73 -> 172800 | ... CG71: =CG7*CG73 -> 98800 | CH71: =SUM(BV71:CG71) -> 1874200 | CJ71: =CJ7*CJ73 -> 165000 | CK71: =CK7*CK73 -> 188600 | CL71: =CL7*CL73 -> 171000 | CM71: =CM7*CM73 -> 180000 | CN71: =CN7*CN73 -> 189000 | CO71: =CO7*CO73 -> 193500 | CP71: =CP7*CP73 -> 216000 | CQ71: =CQ7*CQ73 -> 207000 | ... CU71: =CU7*CU73 -> 119600 | CV71: =SUM(CJ71:CU71) -> 2218500 | CX71: =CX7*CX73 -> 184000 | CY71: =CY7*CY73 -> 138000 | CZ71: =CZ7*CZ73 -> 174800 | DA71: =DA7*DA73 -> 184000 | DB71: =DB7*DB73 -> 193200 | DC71: =DC7*DC73 -> 184000 | DD71: =DD7*DD73 -> 211600 | DE71: =DE7*DE73 -> 193200 | ... DI71: =DI7*DI73 -> 119600 | DJ71: =SUM(CX71:DI71) -> 2152800
B72: Meta Fábrica | D72: 98048 | E72: 128688 | F72: 124704 | G72: 157500 | H72: 182600 | I72: 157700 | J72: 181700 | K72: 165900 | L72: 174300 | M72: 215800 | N72: 180000 | O72: 112500 | P72: =SUM(D72:O72) -> 1879440 | R72: 158400 | S72: 146000 | T72: 102200 | U72: 0 | V72: 43800 | W72: 160600 | X72: 167900 | Y72: 153300 | Z72: 153300 | AA72: 153300 | AB72: 146000 | AC72: 124100 | AF72: 131400 | AG72: 146000 | AH72: 125511 | AI72: 135000 | AJ72: 177320 | AK72: 151300 | AL72: 176000 | AM72: =AM73*AM7 -> 154000 | AN72: =AN73*AN7 -> 157500 | AO72: =AO73*AO7 -> 140000 | AP72: =AP73*AP7 -> 130000 | AQ72: =AQ73*AQ7+16000 -> 100000 | AR72: =SUM(AF72:AQ72) -> 1724031 | AT72: =AT73*AT7 -> 133000 | AU72: =125180 -> 125180 | AV72: =AV73*AV7+7428 -> 117228 | AW72: =AW73*AW7 -> 123500 | AX72: =AX73*AX7 -> 132000 | AY72: =AY73*AY7 -> 153343 | AZ72: 142409 | BA72: 163520 | BB72: =BB73*BB7 -> 165000 | BC72: =BC73*BC7 -> 157500 | BD72: 129431 | BE72: 61700 | BF72: =SUM(AT72:BE72) -> 1603811 | BG72: =BF72+BF75-AR72-AR75 -> -113040 | BH72: 136760 | BI72: 116580 | BJ72: 148340 | BK72: 112360 | BL72: 108660 | BM72: 153416 | BN72: 137676 | BO72: 150654 | BP72: =7100*BP7 -> 142000 | BQ72: =BQ71-BQ75 -> 136725 | BR72: =BR71-BR75 -> 167069 | BS72: 124020 | BT72: =SUM(BH72:BS72) -> 1634260 | BV72: =BV73*BV74-24551 -> 108449 | BW72: =BW73*BW74 -> 133000 | BX72: =BX73*BX74 -> 147000 | BY72: =BY73*BY74 -> 172800 | BZ72: =BZ73*BZ74 -> 165600 | CA72: =CA73*CA74 -> 158400 | CB72: =CB73*CB74 -> 180000 | CC72: =CC73*CC74 -> 172800 | CD72: =CD73*CD74 -> 172800 | ... CG72: =CG73*CG74 -> 98800 | CH72: =SUM(BV72:CG72) -> 1849649 | CI72: =(CH72-BT78)/BT78 -> 0.29391869 | CJ72: =CJ71 -> 165000 | CK72: =CK71 -> 188600 | CL72: =CL71 -> 171000 | CM72: =CM71 -> 180000 | CN72: =CN71 -> 189000 | CO72: =CO71 -> 193500 | CP72: 168760 | CQ72: 194340 | CR72: 208000 | CS72: 201780 | CT72: 154060 | CU72: 96720 | CV72: 1949109 | CW72: =(CV72-CH78)/CH78 -> 0.11040222 | CX72: =CX71 -> 184000 | CY72: =CY71 -> 138000 | CZ72: =CZ71 -> 174800 | DA72: =DA71 -> 184000 | DB72: =DB71 -> 193200 | DC72: =DC71 -> 184000 | DD72: 168760 | DE72: 194340 | DF72: 208000 | DG72: 201780 | DH72: 154060 | DI72: 96720 | DJ72: 1949109
B73: Media Dia Fábrica | R73: =R72/R7 -> 7200 | S73: =S72/S7 -> 7300 | T73: =T72/T7 -> 7300 | U73: =U72/U7 -> 0 | V73: =V72/V7 -> 3650 | W73: =W72/W7 -> 7300 | X73: =X72/X7 -> 7300 | Y73: =Y72/Y7 -> 7300 | ... AC73: =AC72/AC7 -> 7300 | AF73: =AF72/AF7 -> 7300 | AG73: =AG72/AG7 -> 7300 | AH73: =AH72/AH7 -> 6275.55 | AI73: =AI72/AI7 -> 6750 | AJ73: =AJ72/AJ7 -> 8060 | AK73: =AK72/AK7 -> 7565 | AL73: =AL72/AL7 -> 8000 | AM73: 7000 | AN73: 7500 | AO73: 7000 | AP73: 6500 | AQ73: 7000 | AR73: =AVERAGE(AF73:AQ73) -> 7187.5458 | AT73: 7000 | AU73: =AU72/AU7 -> 6588.4211 | AV73: 6100 | AW73: 6500 | AX73: 6000 | AY73: 7302.0476 | AZ73: 7000 | BA73: =BA72/BA7 -> 7432.7273 | BB73: 7500 | BC73: 7500 | BD73: =BD72/BD7 -> 6471.55 | BE73: =BE72/BE7 -> 6170 | BF73: =AVERAGE(AT73:BE73) -> 6797.0622 | BH73: =BH72/BH7 -> 6838 | BI73: =BI72/BI7 -> 6857.6471 | BJ73: =BJ72/BJ7 -> 6449.5652 | BK73: =BK72/BK7 -> 6242.2222 | BL73: =BL72/BL7 -> 4939.0909 | BM73: =BM72/BM7 -> 6670.2609 | BN73: =BN72/BN7 -> 6556 | BO73: =BO72/BO7 -> 7174 | ... BS73: =BS72/BS7 -> 8858.5714 | BT73: =AVERAGE(BH73:BS73) -> 6879.1268 | BV73: 7000 | BW73: 7000 | BX73: 7000 | BY73: 7200 | BZ73: 7200 | CA73: 7200 | CB73: 7200 | CC73: =CB73 -> 7200 | CD73: 7200 | CE73: 7200 | CF73: 7600 | CG73: 7600 | CJ73: 7500 | CK73: 8200 | CL73: 9000 | CM73: 9000 | CN73: 9000 | CO73: 9000 | CP73: 9000 | CQ73: 9200 | CR73: =CQ73 -> 9200 | CS73: =CR73 -> 9200 | CT73: =CS73 -> 9200 | CU73: =CT73 -> 9200 | CX73: =CU73 -> 9200 | CY73: =CX73 -> 9200 | CZ73: =CY73 -> 9200 | DA73: =CZ73 -> 9200 | DB73: =DA73 -> 9200 | DC73: =DB73 -> 9200 | DD73: =DC73 -> 9200 | DE73: =DD73 -> 9200 | DF73: =DE73 -> 9200 | ... DI73: =DH73 -> 9200
B74: dias trabalhados | S74: 15000 | T74: 15600 | U74: 2000 | V74: 10000 | W74: 30000 | X74: 20000 | Y74: 30000 | Z74: 30000 | AA74: 20000 | AB74: 20000 | AC74: 10000 | AF74: 30000 | AG74: 20000 | AH74: 24960 | AI74: 14040 | AJ74: 19040 | AK74: 12000 | AL74: 14000 | AM74: 13000 | AN74: 13000 | AO74: 0 | AP74: 0 | AQ74: 0 | AR74: =SUM(AF74:AQ74) -> 160040 | AT74: 0 | AU74: 0 | BF74: =SUM(AT74:BE74) -> 0 | BG74: =BF74-AR74 -> -160040 | BT74: =SUM(BH74:BS74) -> 0 | BV74: =BV7 -> 19 | BW74: =BW7 -> 19 | BX74: =BX7 -> 21 | BY74: =BY7 -> 24 | BZ74: =BZ7 -> 23 | CA74: =CA7 -> 22 | CB74: =CB7 -> 25 | CC74: =CC7 -> 24 | ... CG74: =CG7 -> 13 | CH74: =SUM(BV74:CG74) -> 260 | CJ74: =CJ7 -> 22 | CK74: =CK7 -> 23 | CL74: =CL7 -> 19 | CM74: =CM7 -> 20 | CN74: =CN7 -> 21 | CO74: =CO7 -> 21.5 | CV74: 131 | CX74: =CX7 -> 20 | CY74: =CY7 -> 15 | CZ74: =CZ7 -> 19 | DA74: =DA7 -> 20 | DB74: =DB7 -> 21 | DC74: =DC7 -> 20 | DJ74: 131
B75: Total Produção 2024 | T75: 0 | U75: 0 | V75: 0 | W75: 0 | X75: 0 | Y75: 13500 | Z75: 9000 | AA75: 9000 | AB75: 9000 | AC75: 0 | AF75: 13500 | AG75: 13500 | AH75: 2820 | AI75: 0 | AJ75: 0 | AK75: 0 | AL75: 0 | AR75: =SUM(AF75:AQ75) -> 29820 | AW75: 4000 | AX75: 8000 | AY75: 5000 | AZ75: 10000 | BA75: 10000 | BB75: 0 | BC75: 0 | BD75: 0 | BF75: =SUM(AT75:BE75) -> 37000 | BH75: 3000 | BO75: 10000 | BP75: 15000 | BQ75: 20000 | BR75: 15000 | BS75: =7200*9/2 -> 32400 | BT75: =SUM(BH75:BS75) -> 95400 | BV75: =BV78-BV71 -> 21584 | BW75: =BW78-BW71 -> 18963 | BX75: =BX78-BX71 -> -2354 | BY75: =BY78-BY71 -> 5998 | BZ75: =BZ78-BZ71 -> -13737 | CA75: =CA78-CA71 -> -6090 | CB75: =CB78-CB71 -> -2176 | CC75: =CC78-CC71 -> -17344 | ... CG75: =CG78-CG71 -> -98800 | CH75: =SUM(CD75:CG75) -> -123726 | CJ75: =BV78 -> 154584 | CK75: =BW78 -> 151963 | CL75: =BX78 -> 144646 | CM75: =BY78 -> 178798 | CN75: =BZ78 -> 151863 | CO75: =CA78 -> 152310 | CV75: 127800 | CX75: =CJ78 -> 0 | CY75: =CK78 -> 0 | CZ75: =CL78 -> 175111 | DA75: =CM78 -> 0 | DB75: =CN78 -> 0 | DC75: =CO78 -> 0 | DJ75: 127800
B76: Minutos DIARO | AO76: =AO71*9.68 -> 1355200 | AP76: =AP71*9.68 -> 1258400 | AQ76: =AQ71*9.68 -> 968000 | AT76: =AT71*9.68 -> 1287440 | AU76: =AU71*9.68 -> 1211742.4 | AV76: =AV71*9.68 -> 1134767 | AW76: =AW71*9.68 -> 1234200 | AX76: =AX71*9.68 -> 1355200 | AY76: =AY71*9.68 -> 1532760.2 | AZ76: =AZ71*9.68 -> 1475319.1 | BA76: =BA71*9.68 -> 1679673.6 | ... BF76: =BF71*9.68 -> 15883050 | CF76: MOSTRUARIO | CM76: 61884.013 | CN76: =CM76 -> 61884.013 | CO76: =CN76 -> 61884.013 | CP76: =CO76 -> 61884.013 | CQ76: =CP76 -> 61884.013 | CR76: =CQ76 -> 61884.013 | CS76: =CR76 -> 61884.013 | CT76: =CS76 -> 61884.013 | CU76: =CT76 -> 61884.013
B77: MInutos Mensal | CM77: =CM76*CM7 -> 1237680.3 | CN77: =CN76*CN7 -> 1299564.3 | CO77: =CO76*CO7 -> 1330506.3 | CP77: =CP76*CP7 -> 1485216.3 | CQ77: =CQ76*CQ7 -> 1392390.3 | CR77: =CR76*CR7 -> 1330506.3 | CS77: =CS76*CS7 -> 1454274.3 | CT77: =CT76*CT7 -> 1175796.2 | CU77: =CU76*CU7 -> 804492.17
A78: PRODUÇÃO | B78: Realizada | D78: 95972 | E78: 130805 | F78: 121914 | G78: 165455 | H78: 192013 | I78: 167281 | J78: 181409 | K78: 163138 | L78: 169051 | M78: 183254 | P78: =SUM(D78:O78) -> 1570292 | R78: 149582 | S78: 152735 | T78: 107681 | U78: 2974 | V78: 32639 | W78: 153121 | X78: 198635 | Y78: 160489 | Z78: 160893 | AA78: 180999 | AB78: 167265 | AC78: 135424 | AD78: =SUM(R78:AC78) -> 1602437 | AF78: 145616 | AG78: 168450 | AH78: 153291 | AI78: 149378 | AJ78: 196360 | AK78: 170558 | AL78: 171758 | AM78: =SUM(AM79:AM80) -> 168974 | AN78: =SUM(AN79:AN80) -> 144792 | AO78: =SUM(AO79:AO80) -> 141375 | AP78: =SUM(AP79:AP80) -> 143221 | AQ78: =SUM(AQ79:AQ80) -> 85543 | AR78: =SUM(AF78:AQ78) -> 1839316 | AT78: =SUM(AT79:AT80) -> 120211 | AU78: =SUM(AU79:AU80) -> 120216 | AV78: =SUM(AV79:AV80) -> 101053 | AW78: =SUM(AW79:AW80) -> 137388 | AX78: =SUM(AX79:AX80) -> 137400 | AY78: =SUM(AY79:AY80) -> 135412 | AZ78: =SUM(AZ79:AZ80) -> 157032 | BA78: =SUM(BA79:BA80) -> 173287 | ... BE78: =SUM(BE79:BE80) -> 55950 | BF78: =SUM(AT78:BE78) -> 1596631 | BG78: =BF78/AR78-1 -> -0.13194307 | BH78: =SUM(BH79:BH80) -> 138562 | BI78: =SUM(BI79:BI80) -> 109391 | BJ78: =SUM(BJ79:BJ80) -> 160056 | BK78: =SUM(BK79:BK80) -> 124826 | BL78: =SUM(BL79:BL80) -> 151185 | BM78: =SUM(BM79:BM80) -> 134688 | BN78: =SUM(BN79:BN80) -> 157005 | BO78: =SUM(BO79:BO80) -> 151231 | ... BQ78: =SUM(BQ79:BQ80) -> 159215 | BT78: =SUM(BH78:BS78) -> 1429494 | BV78: 154584 | BW78: 151963 | BX78: 144646 | BY78: 178798 | BZ78: 151863 | CA78: 152310 | CB78: =CB79+CB80 -> 177824 | CC78: =CC79+CC80 -> 155456 | CD78: =CD79+CD80 -> 159431 | CE78: 173593 | CF78: 154850 | CG78: =CG79+CG80 -> 0 | CH78: =SUM(BV78:CG78) -> 1755318 | CL78: 175111
B79: Real Fábrica | AF79: 126362 | AG79: 153970 | AH79: 128331 | AI79: 135338 | AJ79: 177312 | AK79: 150818 | AL79: 158858 | AM79: 153933 | AN79: 134244 | AO79: 137435 | AP79: 143221 | AQ79: 85543 | AR79: =SUM(AF79:AQ79) -> 1685365 | AT79: 120211 | AU79: 120216 | AV79: 101053 | AW79: 137388 | AX79: 137400 | AY79: 135412 | AZ79: 157032 | BA79: 172227 | BB79: =157995+8500 -> 166495 | BC79: 153816 | BD79: 138051 | BE79: 55950 | BF79: =SUM(AT79:BE79) -> 1595251 | BH79: 138562 | BI79: 109391 | BJ79: 160056 | BK79: 124826 | BL79: 151185 | BM79: 134688 | BN79: 157005 | BO79: 151231 | BP79: 143335 | BQ79: 159215 | BT79: =SUM(BH79:BS79) -> 1429494 | BV79: 154584 | BW79: 151963 | BX79: 144646 | BY79: 178798 | BZ79: 151863 | CA79: 152310 | CB79: 177824 | CC79: 155456 | CD79: 159431
B80: Real Oficina | AF80: =AF78-AF79 -> 19254 | AG80: =AG78-AG79 -> 14480 | AH80: =AH78-AH79 -> 24960 | AI80: =AI78-AI79 -> 14040 | AJ80: =AJ78-AJ79 -> 19048 | AK80: =AK78-AK79 -> 19740 | AL80: =AL78-AL79 -> 12900 | AM80: 15041 | AN80: 10548 | AO80: 3940 | AP80: 0 | AQ80: 0 | AR80: =SUM(AF80:AQ80) -> 153951 | AT80: 0 | AU80: 0 | AV80: 0 | AW80: 0 | AX80: 0 | AY80: 0 | AZ80: 0 | BA80: 1060 | BB80: 320 | BC80: 0 | BD80: 0 | BF80: =SUM(AT80:BE80) -> 1380 | BT80: =SUM(BH80:BS80) -> 0
A81: Desvio Produção Real-Previsto | AF81: =AF78-AF71 -> -15784 | AG81: =AG78-AG71 -> 2450 | AH81: =AH78-AH71 -> 2820 | AI81: =AI78-AI71 -> 338 | AJ81: =AJ78-AJ71 -> 0 | AK81: =AK78-AK71 -> 7258 | AL81: =AL78-AL71 -> -18242 | AM81: =AM78-AM71 -> 1974 | ... AQ81: =AQ78-AQ71 -> -14457 | AR81: =SUM(AF81:AQ81) -> -44755 | AT81: =AT78-AT71 -> -12789 | AU81: =AU78-AU71 -> -4964 | AV81: =AV78-AV71 -> -16175 | AW81: =AW78-AW71 -> 9888 | AX81: =AX78-AX71 -> -2600 | AY81: =AY78-AY71 -> -22931 | AZ81: =AZ78-AZ71 -> 4623 | BA81: =BA78-BA71 -> -233 | ... BE81: =BE78-BE71 -> -5750 | BF81: =SUM(AT81:BE81) -> -44180 | BH81: =BH78-BH71 -> -1198 | BI81: =BI78-BI71 -> -7189 | BJ81: =BJ78-BJ71 -> 11716 | BK81: =BK78-BK71 -> 12466 | BL81: =BL78-BL71 -> 42525 | BM81: =BM78-BM71 -> -18728 | BN81: =BN78-BN71 -> 19329 | BO81: =BO78-BO71 -> -9423 | ... BQ81: =BQ78-BQ71 -> 2490 | BT81: =SUM(BH81:BS81) -> 38323 | BY81: =BY78-BY71 -> 5998 | BZ81: =BZ78-BZ71 -> -13737 | CA81: =CA78-CA71 -> -6090 | CB81: =CB78-CB71 -> -2176 | CC81: =CC78-CC71 -> -17344 | CD81: =CD78-CD71 -> -13369 | CE81: =CE78-CE71 -> 793 | CF81: =CF78-CF71 -> -12350 | ... CH81: =CH78-CH71 -> -118882 | CJ81: =CJ78-CJ71 -> -165000 | CK81: =CK78-CK71 -> -188600 | CL81: =CL78-CL71 -> 4111 | CM81: =CM78-CM71 -> -180000 | CN81: =CN78-CN71 -> -189000 | CO81: =CO78-CO71 -> -193500 | CP81: =CP78-CP71 -> -216000 | CQ81: =CQ78-CQ71 -> -207000 | ... CV81: =CV78-CV71 -> -2218500 | CX81: =CX78-CX71 -> -184000 | CY81: =CY78-CY71 -> -138000 | CZ81: =CZ78-CZ71 -> -174800 | DA81: =DA78-DA71 -> -184000 | DB81: =DB78-DB71 -> -193200 | DC81: =DC78-DC71 -> -184000 | DD81: =DD78-DD71 -> -211600 | DE81: =DE78-DE71 -> -193200 | ... DJ81: =DJ78-DJ71 -> -2152800
A82: Diferença Produção x Venda | D82: =#REF!-#REF! -> #REF! | E82: =#REF!-#REF! -> #REF! | F82: =#REF!-#REF! -> #REF! | G82: =G71-#REF! -> #REF! | H82: =H71-#REF! -> #REF! | I82: =I71-#REF! -> #REF! | J82: =#REF!-#REF! -> #REF! | K82: =#REF!-#REF! -> #REF! | L82: =L71-L27 -> -24911 | M82: =M71-M27 -> -13674 | N82: =N71-N27 -> 57632 | O82: =O71-O27 -> 74079 | P82: =SUM(D82:O82) -> #REF! | R82: =R71-R27 -> 22222.66 | S82: =S71-S27 -> 17159.674 | T82: =T71-T27 -> -24753.772 | U82: =U71-U27 -> -17814.9 | V82: =V71-V27 -> 1715 | W82: =W71-W27 -> 120430.62 | X82: =X71-X27 -> 43436.667 | Y82: =Y71-Y27 -> -29747.083 | ... AD82: =AD71-AD27 -> 333561.36 | AF82: =AF71-AF27 -> 32754 | AG82: =AG71-AG27 -> -11977 | AH82: =AH71-AH27 -> 76847 | AI82: =AI71-AI27 -> 59682 | AJ82: =AJ71-AJ27 -> 74226 | AK82: =AK71-AK27 -> 14740 | AL82: =AL71-AL27 -> 38005 | AM82: =AM71-AM27 -> -71903 | ... AQ82: =AQ71-AQ27 -> 2160 | AR82: =SUM(AF82:AQ82) -> 9360.6667 | AT82: =AT71-AT27 -> -19749.25 | AU82: =AU71-AU27 -> -43342.103 | AV82: =AV71-AV27 -> -36893.138 | AW82: =AW71-AW27 -> -32095.138 | AX82: =AX71-AX27 -> 19900.034 | AY82: =AY71-AY27 -> 19999.222 | AZ82: =AZ71-AZ27 -> -14264.778 | BA82: =BA71-BA27 -> -68922.296 | ... BE82: =BE71-BE27 -> -10986.613 | BF82: =SUM(AT82:BE82) -> -365754.72 | BH82: =BH71-BH27 -> -12993 | BI82: =BI71-BI27 -> -30242.333 | BJ82: =BJ71-BJ27 -> -23206.074 | BK82: =BK71-BK27 -> -47411.741 | BL82: =BL71-BL27 -> -23836.852 | BM82: =BM71-BM27 -> 23509.741 | BN82: =BN71-BN27 -> -33707.556 | BO82: =BO71-BO27 -> -18896.378 | ... BQ82: =BQ71-BQ27 -> -7140 | BT82: =SUM(BH82:BS82) -> -218977.94 | BY82: =BY71-BY27 -> 13630.769 | BZ82: =BZ71-BZ27 -> 14117.607 | CA82: =CA71-CA27 -> 16957.871 | CB82: =CB71-CB27 -> 3013.7856 | CC82: =CC71-CC27 -> -28501.089 | CD82: =CD71-CD27 -> -40033.04 | CE82: =CE71-CE27 -> -43122.304 | CF82: =CF71-CF27 -> -3915.8422 | CG82: =CG71-CG27 -> 11316.183 | CH82: =CH78-CH69 -> -50665 | CJ82: =CJ71-CJ27 -> -16422.94 | CK82: =CK71-CK27 -> 22747.33 | CL82: =CL71-CL27 -> -14796.68 | CM82: =CM71-CM27 -> 19943.34 | CN82: =CN71-CN27 -> 35198.05 | CO82: =CO71-CO27 -> 73319.12 | CP82: =CP71-CP27 -> -9720.09 | CQ82: =CQ71-CQ27 -> 104.69 | ... CV82: =CV71-CV27 -> 66733.35 | CX82: =CX71-CX27 -> -6494.087 | CY82: =CY71-CY27 -> -36145.303 | CZ82: =CZ71-CZ27 -> -20286.514 | DA82: =DA71-DA27 -> 15940.507 | DB82: =DB71-DB27 -> 31707.952 | DC82: =DC71-DC27 -> 57810.076 | DD82: =DD71-DD27 -> -25406.095 | DE82: =DE71-DE27 -> -24040.076 | ... DJ82: =DJ71-DJ27 -> 195702.83
CA83: =BZ83+CA82 -> 16957.871 | CB83: =CA83+CB82 -> 19971.656 | CC83: =CB83+CC82 -> -8529.433 | CD83: =CC83+CD82 -> -48562.473 | CE83: =CD83+CE82 -> -91684.777 | CF83: =CE83+CF82 -> -95600.619 | CG83: =CF83+CG82 -> -84284.436

Sheet Plano mestre 95 % 2025 5% - (3)
R1: PLANEJAMENTO FABRICA | AF1: PLANEJAMENTO FABRICA | AT1: PLANEJAMENTO FABRICA | BH1: PLANEJAMENTO FABRICA | BV1: PLANEJAMENTO FABRICA | CH1: Férias 18/12 - 29/12 | CJ1: PLANEJAMENTO FABRICA | CX1: PLANEJAMENTO FABRICA
D2: 2019 | R2: 2020 | AF2: 2021 | AT2: 2022 | BH2: 2023 | BV2: 2024 | CH2: COMPENSAÇÃO 30 ,31 ,02 e 03 | CJ2: /--------------------------------------------2025 | CX2: 2026
A3: Dias Uteis Produção | C3: =A3 -> Dias Uteis Produção | CH3: 12 dias de férias | CJ3: 23 | CK3: 20 | CL3: 21 | CM3: 22 | CN3: 22 | CO3: 21 | CP3: 23 | CQ3: 21 | CR3: 21 | CS3: 23 | CT3: 20 | CU3: 13 | CX3: 23 | CY3: 20 | CZ3: 21 | DA3: 22 | DB3: 22 | DC3: 21 | DD3: 23 | DE3: 21 | DF3: 21 | DG3: 23 | DH3: 20 | DI3: 13
A4: (-) FÉRIAS | C4: =A4 -> (-) FÉRIAS | CH4: 4 dias de compensação | CJ4: 3 | CL4: 1.5 | CX4: 3 | CY4: 5
A5: (+) SABADO | C5: =A5 -> (+) SABADO | CH5: dias de compensação 9/11 , 23/11 , 7/12 e 14/12 | CJ5: 2 | CK5: 3 | CL5: 1.5 | CM5: 0 | CN5: 0 | CO5: 1.5 | CP5: 1 | CQ5: 1.5 | CR5: 1.5 | CS5: 1.5 | CT5: 0 | DA5: 0 | DB5: 0 | DC5: 0 | DD5: 0 | DE5: 0 | DF5: 0 | DG5: 1 | DH5: 0
A6: (-)FERIADO | C6: =A6 -> (-)FERIADO | CG6: 2 grupos a partir de dezembro | CL6: 2 | CM6: 2 | CN6: 1 | CO6: 1 | CR6: 1 | CS6: 1 | CT6: 1 | CZ6: 2 | DA6: 2 | DB6: 1 | DC6: 1 | DF6: 1 | DG6: 1 | DH6: 1
A7: Dias Trabalhados | C7: =A7 -> Dias Trabalhados | D7: 16 | E7: 21 | F7: 18 | G7: 21 | H7: 22 | I7: 19 | J7: 23 | K7: 21 | L7: 21 | M7: 26 | N7: 24 | O7: 15 | R7: 22 | S7: 20 | T7: 14 | U7: 1 | V7: 12 | W7: 22 | X7: 23 | Y7: 21 | Z7: 21 | AA7: 21 | AB7: 20 | AC7: 17 | AF7: 18 | AG7: 20 | AH7: 20 | AI7: 20 | AJ7: 22 | AK7: 20 | AL7: 22 | AM7: 22 | AN7: 21 | AO7: 20 | AP7: 20 | AQ7: 12 | AT7: 19 | AU7: 19 | AV7: 18 | AW7: 19 | AX7: 22 | AY7: 21 | AZ7: 21 | BA7: 22 | BB7: 22 | BC7: 21 | BD7: 20 | BE7: 10 | BH7: 20 | BI7: 17 | BJ7: 23 | BK7: 18 | BL7: 22 | BM7: 23 | BN7: 21 | BO7: 21 | BP7: 20 | BQ7: 21 | BR7: 20 | BS7: 14 | BT7: 20 | BV7: 19 | BW7: 19 | BX7: 21 | BY7: =22+2 -> 24 | BZ7: =21+2 -> 23 | CA7: =20+2 -> 22 | CB7: =23+2 -> 25 | CC7: =21+3 -> 24 | CD7: =21+3 -> 24 | CE7: =23+1 -> 24 | CF7: =19+3 -> 22 | CG7: =12+1 -> 13 | CJ7: =CJ3+CJ5-CJ6-CJ4 -> 22 | CK7: =CK3+CK5-CK6-CK4 -> 23 | CL7: 19 | CM7: =CM3+CM5-CM6-CM4 -> 20 | CN7: =CN3+CN5-CN6-CN4 -> 21 | CO7: =CO3+CO5-CO6-CO4 -> 21.5 | CP7: =CP3+CP5-CP6 -> 24 | CQ7: =CQ3+CQ5-CQ6 -> 22.5 | CR7: =CR3+CR5-CR6 -> 21.5 | CS7: =CS3+CS5-CS6 -> 23.5 | CT7: =CT3+CT5-CT6 -> 19 | CU7: =CU3+CU5-CU6 -> 13 | CX7: =CX3+CX5-CX6-CX4 -> 20 | CY7: =CY3+CY5-CY6-CY4 -> 15 | CZ7: =CZ3+CZ5-CZ6-CZ4 -> 19 | DA7: =DA3+DA5-DA6-DA4 -> 20 | DB7: =DB3+DB5-DB6-DB4 -> 21 | DC7: =DC3+DC5-DC6-DC4 -> 20 | DD7: =DD3+DD5-DD6 -> 23 | DE7: =DE3+DE5-DE6 -> 21 | DF7: =DF3+DF5-DF6 -> 20 | DG7: =DG3+DG5-DG6 -> 23 | DH7: =DH3+DH5-DH6 -> 19 | DI7: =DI3+DI5-DI6 -> 13
D8: JAN | E8: FEV | F8: MAR | G8: ABR | H8: MAI | I8: JUN | J8: JUL | K8: AGO | L8: SET | M8: OUT | N8: NOV | O8: DEZ | P8: TOTAL | R8: JAN | S8: FEV | T8: MAR | U8: ABR | V8: MAI | W8: JUN | X8: JUL | Y8: AGO | Z8: SET | AA8: OUT | AB8: NOV | AC8: DEZ | AD8: TOTAL | AF8: JAN | AG8: FEV | AH8: MAR | AI8: ABR | AJ8: MAI | AK8: JUN | AL8: JUL | AM8: AGO | AN8: SET | AO8: OUT | AP8: NOV | AQ8: DEZ | AR8: TOTAL | AT8: JAN | AU8: FEV | AV8: MAR | AW8: ABR | AX8: MAI | AY8: JUN | AZ8: JUL | BA8: AGO | BB8: SET | BC8: OUT | BD8: NOV | BE8: DEZ | BF8: TOTAL | BH8: JAN | BI8: FEV | BJ8: MAR | BK8: ABR | BL8: MAI | BM8: JUN | BN8: JUL | BO8: AGO | BP8: SET | BQ8: OUT | BR8: NOV | BS8: DEZ | BT8: TOTAL | BV8: JAN | BW8: FEV | BX8: MAR | BY8: ABR | BZ8: MAI | CA8: JUN | CB8: JUL | CC8: AGO | CD8: SET | CE8: OUT | CF8: NOV | CG8: DEZ | CH8: TOTAL | CJ8: JAN | CK8: FEV | CL8: MAR | CM8: ABR | CN8: MAI | CO8: JUN | CP8: JUL | CQ8: AGO | CR8: SET | CS8: OUT | CT8: NOV | CU8: DEZ | CV8: TOTAL | CX8: JAN | CY8: FEV | CZ8: MAR | DA8: ABR | DB8: MAI | DC8: JUN | DD8: JUL | DE8: AGO | DF8: SET | DG8: OUT | DH8: NOV | DI8: DEZ | DJ8: TOTAL
CI9: redução de meta | CW9: redução de meta
A10: ESTOQUE FÍSICO | B10: Total (1+2) DISPONÍVEL TOTAL | D10: =SUM(D15:D17) -> 304786 | E10: =SUM(E15:E17) -> 311986 | F10: =SUM(F15:F17) -> 328231 | G10: =SUM(G15:G17) -> 317873 | H10: =SUM(H15:H17) -> 347196 | I10: =SUM(I15:I17) -> 402253 | J10: =SUM(J15:J17) -> 454488 | K10: =SUM(K15:K17) -> 447182 | ... O10: =SUM(O15:O17) -> 188264 | R10: =SUM(R15:R17) -> 283359 | S10: =SUM(S15:S17) -> 342718 | T10: =SUM(T15:T17) -> 313212 | U10: =SUM(U15:U17) -> 298093 | V10: =SUM(V15:V17) -> 206617 | W10: =SUM(W15:W17) -> 235875 | X10: =SUM(X15:X17) -> 360135 | Y10: =SUM(Y15:Y17) -> 361665 | ... AC10: =SUM(AC15:AC17) -> 197551 | AF10: =SUM(AF15:AF19) -> 255339 | AG10: =SUM(AG15:AG19) -> 292621 | AH10: =SUM(AH15:AH19) -> 397976 | AI10: =SUM(AI15:AI19) -> 388165 | AJ10: =SUM(AJ15:AJ19) -> 409301 | AK10: =SUM(AK15:AK19) -> 490913 | AL10: =SUM(AL15:AL19) -> 563229 | AM10: =SUM(AM15:AM19) -> 559169 | ... AQ10: =SUM(AQ15:AQ19) -> 531679 | AR10: =AQ10 -> 531679 | AT10: =SUM(AT15:AT19) -> 471378 | AU10: =SUM(AU15:AU19) -> 473307 | AV10: =SUM(AV15:AV19) -> 412518 | AW10: =SUM(AW15:AW19) -> 398039 | AX10: =SUM(AX15:AX19) -> 417827 | AY10: =SUM(AY15:AY19) -> 507968 | AZ10: =SUM(AZ15:AZ19) -> 477530 | BA10: =SUM(BA15:BA19) -> 520708 | ... BE10: =SUM(BE15:BE19) -> 356505 | BF10: =BE10 -> 356505 | BH10: =SUM(BH15:BH19) -> 357143 | BI10: =SUM(BI15:BI19) -> 355011 | BJ10: =SUM(BJ15:BJ19) -> 344281 | BK10: =SUM(BK15:BK19) -> 389628 | BL10: =SUM(BL15:BL19) -> 324889 | BM10: =SUM(BM15:BM19) -> 352666 | BN10: =SUM(BN15:BN19) -> 418721 | BO10: =SUM(BO15:BO19) -> 356602 | ... BR10: =SUM(BR15:BR19) -> 228035 | BS10: =BS15+BS16+BS19 -> 201165 | BT10: =BS10 -> 201165 | BV10: =BV11+BV16+BV19 -> 247713 | BW10: =BW11+BW16+BW19 -> 278707 | BX10: =BX11+BX16+BX19 -> 281829 | BY10: =BY11+BY16+BY19 -> 317753 | BZ10: =BZ11+BZ16+BZ19 -> 270339 | CA10: =CA11+CA16+CA19 -> 310383 | CB10: =CB11+CB16+CB19 -> 328365 | CC10: =CC11+CC16+CC19 -> 333476 | ... CG10: =CG11+CG16+CG19 -> 182266 | CH10: =CH15+CH16+CH19 -> 161447 | CJ10: =CH10+CJ71-CJ27 -> 145024.06 | CK10: =CJ10+CK71-CK27 -> 167771.39 | CL10: =CK10+CL71-CL27 -> 152974.71 | CM10: =CL10+CM71-CM27 -> 172918.05 | CN10: =CM10+CN71-CN27 -> 208116.1 | CO10: =CN10+CO71-CO27 -> 281435.22 | CP10: =CO10+CP71-CP27 -> 271715.13 | CQ10: =CP10+CQ71-CQ27 -> 271819.82 | CR10: =CQ10+CR71-CR27 -> 212966.18 | ... CU10: =CT10+CU71-CU27 -> 228180.35 | CV10: 116080.11 | CX10: =CV10+CX71-CX27 -> 109586.02 | CY10: =CX10+CY71-CY27 -> 73440.716 | CZ10: =CY10+CZ71-CZ27 -> 53154.202 | DA10: =CZ10+DA71-DA27 -> 69094.709 | DB10: =DA10+DB71-DB27 -> 100802.66 | DC10: =DB10+DC71-DC27 -> 158612.74 | DD10: =DC10+DD71-DD27 -> 133206.64 | DE10: =DD10+DE71-DE27 -> 109166.57 | DF10: =DE10+DF71-DF27 -> 23680.246 | ... DI10: =DH10+DI71-DI27 -> 9525.1244 | DJ10: 116080.11
A11: 0 | B11: ESTOQUE FISICO EM LINHA | BV11: 204006 | BW11: 241182 | BX11: 245950 | BY11: 281974 | BZ11: 202865 | CA11: 240895 | CB11: 273565 | CC11: 288981 | CD11: 273990 | CE11: 237556 | CF11: 168313 | CG11: 150819 | CH11: =CG11 -> 150819 | CJ11: 205037 | CK11: 230430 | CL11: 234343 | CM11: 262404
A12: 0 | B12: PEDIDOS EM CARTEIRA | BV12: 80956 | BW12: 110544 | BX12: 134506 | BY12: 127959 | BZ12: 66136 | CA12: 72582 | CB12: 94286 | CC12: 133081 | CD12: 148174 | CE12: 154201 | CF12: 97365 | CG12: 30184 | CJ12: 132209 | CK12: 180000 | CL12: 177643 | CM12: 148159
A13: 0 | B13: PROCESSO | CJ13: 150321 | CK13: 133602 | CL13: 135672 | CM13: 127653
A14: 0 | B14: ESTOQUE NEGATIVO | CJ14: 36757 | CK14: 55826 | CL14: 60438 | CM14: 50114
A15: 1 | B15: EM LINHA DISPONIVEL | D15: 197000 | E15: 223027 | F15: 230513 | G15: 231174 | H15: 255028 | I15: =316386+3241 -> 319627 | J15: 377712 | K15: 382411 | L15: 394107 | M15: 267954 | O15: 143875 | R15: 208084 | S15: 268431 | T15: 250616 | U15: 237088 | V15: 147777 | W15: 215818 | X15: 273510 | Y15: 299059 | Z15: 304980 | AA15: 231197 | AB15: 143086 | AC15: 172491 | AF15: 198695 | AG15: 234210 | AH15: 327560 | AI15: 332523 | AJ15: 356667 | AK15: 384165 | AL15: 317268 | AM15: 370708 | AN15: 354503 | AO15: 314605 | AP15: 90490 | AQ15: 58348 | AR15: =AQ15 -> 58348 | AT15: 158701 | AU15: 115369 | AV15: 142379 | AW15: 118765 | AX15: 113246 | AY15: 106776 | AZ15: 175234 | BA15: 151553 | BB15: 167082 | BC15: 150959 | BD15: 119787 | BE15: 65426 | BF15: =BE15 -> 65426 | BH15: 166918 | BI15: 167160 | BJ15: 204571 | BK15: 153197 | BL15: 196798 | BM15: 145596 | BN15: 166021 | BO15: 211305 | BP15: 201071 | BQ15: 177743 | BR15: 144020 | BS15: 154347 | BT15: =BS15 -> 154347 | BV15: 151471 | BW15: 155653 | BX15: 151611 | BY15: 177044 | BZ15: 170481 | CA15: 221665 | CB15: 218105 | CC15: 188153 | CD15: 147751 | CE15: 112996 | CF15: 135968 | CG15: 130000 | CH15: =CG15 -> 130000 | CI15: 114000 | CJ15: 109585 | CK15: 103815 | CL15: 117138 | CM15: =CL15+CM71-CM27 -> 137081.34 | CN15: =CM15+CN71-CN27 -> 172279.39 | CO15: =CN15+CO71-CO27 -> 245598.51 | CP15: =CO15+CP71-CP27 -> 235878.42 | CQ15: =CP15+CQ71-CQ27 -> 235983.11 | CR15: =CQ15+CR71-CR27 -> 177129.47 | CS15: =CR15+CS71-CS27 -> 163912.55 | CT15: =CS15+CT71-CT27 -> 175927.46 | CU15: =CT15+CU71-CU27 -> 192343.64 | CX15: =CU15+CX71-CX27 -> 185849.55 | CY15: =CX15+CY71-CY27 -> 149704.25 | CZ15: =CY15+CZ71-CZ27 -> 129417.74 | DA15: =CZ15+DA71-DA27 -> 145358.24 | DB15: =DA15+DB71-DB27 -> 177066.2 | DC15: =DB15+DC71-DC27 -> 234876.27 | DD15: =DC15+DD71-DD27 -> 209470.18 | DE15: =DD15+DE71-DE27 -> 185430.1 | DF15: =DE15+DF71-DF27 -> 99943.779 | ... DI15: =DH15+DI71-DI27 -> 85788.657 | DJ15: 0
A16: 2 | B16: EM LINHA NAO COMPRAR MP DISPONIVEL | D16: 73670 | E16: 59682 | F16: 54710 | G16: 56175 | H16: 58933 | I16: 42784 | J16: 35755 | K16: 33547 | L16: 22824 | M16: 26162 | O16: 44389 | R16: 39759 | S16: 38325 | T16: 26634 | U16: =14430+2754+7859 -> 25043 | V16: 23840 | W16: 20057 | X16: 80502 | Y16: 56483 | Z16: 44233 | AA16: 38155 | AB16: 27540 | AC16: 25060 | AF16: 21326 | AG16: 17804 | AH16: 27157 | AI16: 19677 | AJ16: 18817 | AK16: 25034 | AL16: 28090 | AM16: 25660 | AN16: 33752 | AO16: 24699 | AP16: 19340 | AQ16: 29842 | AR16: =AQ16 -> 29842 | AT16: 46493 | AU16: 37125 | AV16: 38574 | AW16: 43626 | AX16: 39641 | AY16: 55553 | AZ16: 48023 | BA16: 55043 | BB16: 50383 | BC16: 54355 | BD16: 82473 | BE16: 65398 | BF16: =BE16 -> 65398 | BH16: 68747 | BI16: 62843 | BJ16: 62154 | BK16: 49337 | BL16: 27730 | BM16: 42459 | BN16: 44049 | BO16: 29196 | BP16: 36882 | BQ16: 35965 | BR16: 31343 | BS16: 23087 | BT16: =BS16 -> 23087 | BV16: 15202 | BW16: 12471 | BX16: 11483 | BY16: 14071 | BZ16: 49617 | CA16: 36385 | CB16: 25473 | CC16: 16933 | CD16: 12684 | CE16: 21084 | CF16: 15172 | CG16: 11469 | CH16: =CG16 -> 11469 | CI16: =7500*5 -> 37500 | CJ16: 9465 | CK16: 13722 | CL16: 10771 | CM16: 8991 | CV16: 0 | DJ16: 0
A17: 3 | B17: EM LINHA PARADO (cob >3) DISPONIVEL | D17: 34116 | E17: 29277 | F17: 43008 | G17: 30524 | H17: 33235 | I17: 39842 | J17: 41021 | K17: 31224 | M17: 10286 | R17: 35516 | S17: 35962 | T17: 35962 | U17: 35962 | V17: 35000 | X17: 6123 | Y17: 6123 | Z17: 4187 | AA17: 2745 | AF17: 8366 | AG17: 11534 | AH17: 11507 | AI17: 9148 | AJ17: 8524 | AK17: 25290 | AL17: 91080 | AM17: 66830 | AN17: 36866 | AO17: 16173 | AP17: 178274 | AQ17: 210665 | AR17: =AQ17 -> 210665 | AT17: 121075 | AU17: 149376 | AV17: 104538 | AW17: 105262 | AX17: 121073 | AY17: 163931 | AZ17: 109964 | BA17: 148266 | BB17: 130697 | BC17: 113779 | BD17: 91119 | BE17: 103286 | BF17: =BE17 -> 103286 | BH17: 49631 | BI17: 52953 | BJ17: 28440 | BK17: 83601 | BL17: 25812 | BM17: 59545 | BN17: 83435 | BO17: 34041 | BP17: 22399 | BQ17: 24887 | BR17: 12183 | BS17: 12183 | BT17: =BS17 -> 12183 | BV17: 5216 | BX17: 65273 | BY17: 70182 | BZ17: 57659 | CA17: 71669 | CB17: 73078 | CC17: 85302 | CD17: 25343 | CE17: 19030 | CF17: 19422 | CG17: 25927 | CH17: =CG17 -> 25927 | CI17: 29000 | CJ17: 21580 | CK17: 18052 | CL17: 30722 | CM17: 55095 | CV17: 0 | DJ17: 0
A18: 4 | B18: EM LINHA PARADO (cob >6) DISPONIVEL | D18: 34116 | E18: 29277 | F18: 43008 | G18: 30524 | H18: 33235 | I18: 39842 | J18: 41021 | K18: 31224 | M18: 10286 | R18: 35516 | S18: 35962 | T18: 35962 | U18: 35962 | V18: 35000 | X18: 6123 | Y18: 6123 | Z18: 4187 | AA18: 2745 | AF18: 8366 | AG18: 11534 | AH18: 11507 | AI18: 9148 | AJ18: 8524 | AK18: 25290 | AL18: 91080 | AM18: 66830 | AN18: 36866 | AO18: 16173 | AP18: 178274 | AQ18: 210665 | AR18: =AQ18 -> 210665 | AT18: 121075 | AU18: 149376 | AV18: 104538 | AW18: 105262 | AX18: 121073 | AY18: 163931 | AZ18: 109964 | BA18: 148266 | BB18: 130697 | BC18: 113779 | BD18: 91119 | BE18: 103286 | BF18: =BE18 -> 103286 | BH18: 49631 | BI18: 52953 | BJ18: 28440 | BK18: 83601 | BL18: 25812 | BM18: 59545 | BN18: 83435 | BO18: 34041 | BP18: 22399 | BQ18: 24887 | BR18: 12183 | BS18: 12183 | BT18: =BS18 -> 12183 | CD18: 6361 | CE18: 7759 | CF18: 6573 | CG18: 9541 | CH18: =CG18 -> 9541 | CI18: =CI15+CI16-CI17 -> 122500 | CJ18: 9582 | CK18: 7266 | CL18: 11364 | CM18: 15500 | CV18: 0 | DJ18: 0
A19: 1 | B19: FL (OPORTUNIDADES) DISPONIVEL | D19: 6409 | E19: 6860 | F19: 4970 | G19: 31203 | H19: 31499 | I19: 25903 | J19: 18606 | K19: 16014 | L19: 13416 | M19: 40079 | O19: 0 | R19: 3376 | S19: 11736 | T19: 22454 | U19: 21384 | V19: 66870 | W19: 73769 | X19: 13944 | Y19: 32750 | Z19: 18536 | AA19: 40211 | AB19: 44457 | AC19: 24504 | AF19: 18586 | AG19: 17539 | AH19: 20245 | AI19: 17669 | AJ19: 16769 | AK19: 31134 | AL19: 35711 | AM19: 29141 | AN19: 25307 | AO19: 35964 | AP19: 37378 | AQ19: 22159 | AR19: =AQ19 -> 22159 | AT19: 24034 | AU19: 22061 | AV19: 22489 | AW19: 25124 | AX19: 22794 | AY19: 17777 | AZ19: 34345 | BA19: 17580 | BB19: 26992 | BC19: 21373 | BD19: 21202 | BE19: 19109 | BF19: =BE19 -> 19109 | BH19: 22216 | BI19: 19102 | BJ19: 20676 | BK19: 19892 | BL19: 48737 | BM19: 45521 | BN19: 41781 | BO19: 48019 | BP19: 43955 | BQ19: 41505 | BR19: 28306 | BS19: 23731 | BT19: =BS19 -> 23731 | BV19: 28505 | BW19: 25054 | BX19: 24396 | BY19: 21708 | BZ19: 17857 | CA19: 33103 | CB19: 29327 | CC19: 27562 | CD19: 19590 | CE19: 11730 | CF19: 10529 | CG19: 19978 | CH19: =CG19 -> 19978 | CJ19: 18456 | CK19: 15409 | CL19: 18755 | CM19: 15700 | CV19: 0 | DJ19: 0
A20: 0 | B20: EM LINHA NAO COMPRAR MP FISICO | CE20: 34501 | CF20: 18809 | CG20: 12618 | CJ20: 11940 | CK20: 19956 | CL20: 15650 | CM20: 11745
A21: 0 | B21: FL(OPORTUNIDADE) FISICO | CE21: 12837 | CF21: 11839 | CG21: 20519 | CJ21: 17816 | CK21: 17432 | CL21: 21670 | CM21: 19814
B22: SALDO UTIL DE ESTOQUE | D22: =D10-D17 -> 270670 | E22: =E10-E17 -> 282709 | F22: =F10-F17 -> 285223 | G22: =G10-G17 -> 287349 | H22: =H10-H17 -> 313961 | I22: =I10-I17 -> 362411 | J22: =J10-J17 -> 413467 | K22: =K10-K17 -> 415958 | ... O22: =O10-O17 -> 188264 | R22: =R10-R17 -> 247843 | S22: =S10-S17 -> 306756 | T22: =T10-T17 -> 277250 | U22: =U10-U17 -> 262131 | V22: =V10-V17 -> 171617 | W22: =W10-W17 -> 235875 | X22: =X10-X17 -> 354012 | Y22: =Y10-Y17 -> 355542 | ... AB22: =AB10-AB17 -> 170626 | AF22: =AF10-AF17 -> 246973 | AG22: =AG10-AG17 -> 281087 | AH22: =AH10-AH17 -> 386469 | AI22: =AI10-AI17 -> 379017 | AJ22: =AJ10-AJ17 -> 400777 | AK22: =AK10-AK17 -> 465623 | AL22: =AL10-AL17 -> 472149 | AM22: =AM10-AM17 -> 492339 | ... AQ22: =AQ10-AQ17 -> 321014 | AR22: =AQ22 -> 321014 | AT22: =AT10-AT17 -> 350303 | AU22: =AU10-AU17 -> 323931 | AV22: =AV10-AV17 -> 307980 | AW22: =AW10-AW17 -> 292777 | AX22: =AX10-AX17 -> 296754 | AY22: =AY10-AY17 -> 344037 | AZ22: =AZ10-AZ17 -> 367566 | BA22: =BA10-BA17 -> 372442 | ... BE22: =BE10-BE17 -> 253219 | BF22: =BE22 -> 253219 | BH22: =BH10-BH17 -> 307512 | BI22: =BI10-BI17 -> 302058 | BJ22: =BJ10-BJ17 -> 315841 | BK22: =BK10-BK17 -> 306027 | BL22: =BL10-BL17 -> 299077 | BM22: =BM10-BM17 -> 293121 | BN22: =BN10-BN17 -> 335286 | BO22: =BO10-BO17 -> 322561 | ... BS22: =BS10-BS17 -> 188982 | BT22: =BS22 -> 188982 | BV22: =BV15-BV17-BV18 -> 146255 | BW22: =BW15-BW17-BW18 -> 155653 | BX22: =BX15-BX17-BX18 -> 86338 | BY22: =BY15-BY17-BY18 -> 106862 | BZ22: =BZ15-BZ17-BZ18 -> 112822 | CA22: =CA15-CA17-CA18 -> 149996 | CB22: =CB15-CB17-CB18 -> 145027 | CC22: =CC15-CC17-CC18 -> 102851 | ... CH22: =CH15-CH17-CH18 -> 94532 | CJ22: =CJ15-CJ17-CJ18 -> 78423 | CK22: =CK15-CK17-CK18 -> 78497 | CL22: =CL15-CL17-CL18 -> 75052 | CM22: =CM15-CM17-CM18 -> 66486.34 | CN22: =CN15-CN17-CN18 -> 172279.39 | CO22: =CO15-CO17-CO18 -> 245598.51 | CP22: =CP15-CP17-CP18 -> 235878.42 | CQ22: =CQ15-CQ17-CQ18 -> 235983.11 | ... CU22: =CU15-CU17-CU18 -> 192343.64 | CV22: 116080.11 | CX22: 242497 | CY22: 234422.08 | CZ22: 194348.71 | DA22: 223062.99 | DB22: 228884.87 | DC22: 240669.79 | DD22: 234679.66 | DE22: 197008.01 | DF22: 148007.96 | DG22: 111276.3 | DH22: 93072.106 | DI22: 116080.11 | DJ22: 116080.11
A23: ESTOQUE EM LINHA | C23: (1-3-5) | D23: =D15-D17 -> 162884 | E23: =E15+E19-E17-E60 -> 200610 | F23: =F15+F19-F17-F60 -> 192475 | G23: =G15+G19-G17-G60 -> 231853 | H23: =H15+H19-H17-H60 -> 253292 | I23: =I15+I19-I17-I60 -> 305688 | J23: =J15+J19-J17-J60 -> 355297 | K23: =K15+K19-K17-K60 -> 367201 | L23: =L15+L19-L17-L60 -> 407523 | ... O23: =O15+O19-O17-O60 -> 143875 | P23: =J23 -> 355297 | R23: =R15-R17 -> 172568 | S23: =S15+S19-S17-S60 -> 244205 | T23: =T15+T19-T17-T60 -> 237108 | U23: =U15+U19-U17-U60 -> 222510 | V23: =V15+V19-V17-V60 -> 179647 | W23: =W15+W19-W17-W60 -> 289587 | X23: =X15+X19-X17-X60 -> 281331 | Y23: =Y15+Y19-Y17-Y60 -> 325686 | Z23: =Z15+Z19-Z17-Z60 -> 319329 | ... AC23: =AC15+AC19-AC17-AC60 -> 196995 | AD23: =X23 -> 281331 | AF23: =AF15+AF17+AF16 -> 228387 | AG23: =AG15+AG17+AG16 -> 263548 | AH23: =AH15+AH17+AH16 -> 366224 | AI23: =AI15+AI17+AI16 -> 361348 | AJ23: =AJ15+AJ17+AJ16 -> 384008 | AK23: =AK15+AK17+AK16 -> 434489 | AL23: =AL15+AL17+AL16 -> 436438 | AM23: =AM15+AM17+AM16 -> 463198 | ... AQ23: =AQ15+AQ17+AQ16 -> 298855 | AR23: =AQ23 -> 298855 | AT23: =AT15+AT17+AT16 -> 326269 | AU23: =AU15+AU17+AU16 -> 301870 | AV23: =AV15+AV17+AV16 -> 285491 | AW23: =AW15+AW17+AW16 -> 267653 | AX23: =AX15+AX17+AX16 -> 273960 | AY23: =AY15+AY17+AY16 -> 326260 | AZ23: =AZ15+AZ17+AZ16 -> 333221 | BA23: =BA15+BA17+BA16 -> 354862 | ... BE23: =BE15+BE17+BE16 -> 234110 | BF23: =SUM(AT23:BE23) -> 3664330 | BH23: =BH15+BH17+BH16 -> 285296 | BI23: =BI15+BI17+BI16 -> 282956 | BJ23: =BJ15+BJ17+BJ16 -> 295165 | BK23: =BK15+BK17+BK16 -> 286135 | BL23: =BL15+BL17+BL16 -> 250340 | BM23: =BM15+BM17+BM16 -> 247600 | BN23: =BN15+BN17+BN16 -> 293505 | BO23: =BO15+BO17+BO16 -> 274542 | ... BS23: =BS15+BS17+BS16 -> 189617 | BT23: =BS23 -> 189617 | BV23: =BV15+BV17+BV16 -> 171889 | BW23: =BW15+BW19+BW16 -> 193178 | BX23: =BX15+BX17+BX16 -> 228367 | BY23: =BY15+BY17+BY16 -> 261297 | BZ23: =BZ15+BZ17+BZ16 -> 277757 | CA23: =CA15+CA17+CA16 -> 329719 | CB23: =CB15+CB17+CB16 -> 316656 | CC23: =CC15+CC17+CC16 -> 290388 | CD23: =CD15+CD17+CD16 -> 185778 | CE23: =CE15+CE17+CE16 -> 153110 | ... CG23: =CG15+CG17+CG16 -> 167396 | CH23: =CG23 -> 167396 | CJ23: 224424 | CK23: 0 | CL23: 0 | CM23: 0 | CN23: 0 | CO23: 0 | CP23: 0 | CQ23: 0 | CR23: 0 | CS23: 0 | CT23: 0 | CU23: 0 | CV23: 0 | CX23: 224424 | CY23: 0 | CZ23: 0 | DA23: 0 | DB23: 0 | DC23: 0 | DD23: 0 | DE23: 0 | DF23: 0 | DG23: 0 | DH23: 0 | DI23: 0 | DJ23: 0
A24: ESTOQUE EM LINHA SEM SALDO PARADO | C24: (1-3-5-6+7) | D24: =D10-D19-D17 -> 264261 | E24: =E10-E19-E17 -> 275849 | F24: =F10-F19-F17 -> 280253 | G24: =G10-G19-G17 -> 256146 | H24: =H10-H19-H17 -> 282462 | I24: =I10-I19-I17 -> 336508 | J24: =J10-J19-J17 -> 394861 | K24: =K10-K19-K17 -> 399944 | ... O24: =O10-O19-O17 -> 188264 | P24: =O24 -> 188264 | R24: =R10-R19-R17 -> 244467 | S24: =S10-S19-S17 -> 295020 | T24: =T10-T19-T17 -> 254796 | U24: =U10-U19-U17 -> 240747 | V24: =V10-V19-V17 -> 104747 | W24: =W10-W19-W17 -> 162106 | X24: =X10-X19-X17 -> 340068 | Y24: =Y10-Y19-Y17 -> 322792 | ... AC24: =AC10-AC19-AC17 -> 173047 | AD24: =AC24 -> 173047 | AF24: =AF23-AF17 -> 220021 | AG24: =AG23-AG17 -> 252014 | AH24: =AH23-AH17 -> 354717 | AI24: =AI23-AI17 -> 352200 | AJ24: =AJ23-AJ17 -> 375484 | AK24: =AK23-AK17 -> 409199 | AL24: =AL23-AL17 -> 345358 | AM24: =AM23-AM17 -> 396368 | ... AQ24: =AQ23-AQ17 -> 88190 | AR24: =AQ24 -> 88190 | AT24: =AT23-AT17 -> 205194 | AU24: =AU23-AU17 -> 152494 | AV24: =AV23-AV17 -> 180953 | AW24: =AW23-AW17 -> 162391 | AX24: =AX23-AX17 -> 152887 | AY24: =AY23-AY17 -> 162329 | AZ24: =AZ23-AZ17 -> 223257 | BA24: =BA23-BA17 -> 206596 | ... BE24: =BE23-BE17 -> 130824 | BF24: =SUM(AT24:BE24) -> 2201964 | BG24: =SUM(AT27:AY27)/SUM(AF61:AK61)-1 -> 0.22832581 | BH24: =BH23-BH17 -> 235665 | BI24: =BI23-BI17 -> 230003 | BJ24: =BJ23-BJ17 -> 266725 | BK24: =BK23-BK17 -> 202534 | BL24: =BL23-BL17 -> 224528 | BM24: =BM23-BM17 -> 188055 | BN24: =BN23-BN17 -> 210070 | BO24: =BO23-BO17 -> 240501 | ... BS24: =BS23-BS17 -> 177434 | BT24: =BS24 -> 177434 | BV24: =BV23-BV17 -> 166673 | BW24: =BW23-BW17 -> 193178 | BX24: =BX23-BX17 -> 163094 | BY24: =BY23-BY17 -> 191115 | BZ24: =BZ23-BZ17 -> 220098 | CA24: =CA23-CA17 -> 258050 | CB24: =CB23-CB17 -> 243578 | CC24: =CC23-CC17 -> 205086 | ... CG24: =CG23-CG17 -> 141469 | CH24: =CG24 -> 141469 | CJ24: 219208 | CK24: 0 | CL24: 0 | CM24: 0 | CN24: 0 | CO24: 0 | CP24: 0 | CQ24: 0 | CR24: 0 | CS24: 0 | CT24: 0 | CU24: 0 | CV24: 0 | CX24: 219208 | CY24: 0 | CZ24: 0 | DA24: 0 | DB24: 0 | DC24: 0 | DD24: 0 | DE24: 0 | DF24: 0 | DG24: 0 | DH24: 0 | DI24: 0 | DJ24: 0
A25: PROJEÇÃO DOS ESTOQUES DISPONIVEL | C25: (1-5-6+7) | D25: =D10 -> 304786 | E25: =E10 -> 311986 | F25: =F10 -> 328231 | G25: =G10 -> 317873 | H25: =H10 -> 347196 | I25: =I10 -> 402253 | J25: =J10 -> 454488 | K25: =K10 -> 447182 | ... O25: =O10 -> 188264 | P25: =O25 -> 188264 | R25: =R10 -> 283359 | S25: =S10 -> 342718 | T25: =T10 -> 313212 | U25: =U10 -> 298093 | V25: =V10 -> 206617 | W25: =W10 -> 235875 | X25: =X10 -> 360135 | Y25: =Y10 -> 361665 | ... AC25: =AC10 -> 197551 | AD25: =AC25 -> 197551 | AF25: =AF10-AF60 -> 255339 | AG25: =AG10-AG60 -> 292621 | AH25: =AH10-AH60 -> 397976 | AI25: =AI10-AI60 -> 388165 | AJ25: =AJ10-AJ60 -> 409301 | AK25: =AK10-AK60 -> 490913 | AL25: =AL10-AL60 -> 563229 | AM25: =AM10-AM60 -> 559169 | ... AQ25: =AQ10-AQ60 -> 522741 | AR25: =AQ25 -> 522741 | AT25: =AT10-AT60 -> 364736 | AU25: =AU10-AU60 -> 382608 | AV25: =AV10-AV60 -> 322837 | AW25: =AW10-AW60 -> 339249 | AX25: =AX10-AX60 -> 382307 | AY25: =AY10-AY60 -> 446417 | AZ25: =AZ10-AZ60 -> 406019 | BA25: =BA10-BA60 -> 457091 | BB25: =BB10-BB60 -> 439103 | BC25: =BB25-BC27+BC71-BC60 -> 267702.71 | BD25: =BC25-BD27+BD71-BD60 -> 224792.12 | BE25: =BD25-BE27+BE71-BE60 -> 209302.51 | BF25: =BE25 -> 209302.51 | BG25: =BG27/AR27 -> 0.070333736 | BH25: =BH10-BH60 -> 287739 | BI25: =BI10-BI60 -> 274599 | BJ25: =BJ10-BJ60 -> 249895 | BK25: =BK10-BK60 -> 311315 | BL25: =BL10-BL60 -> 277855 | BM25: =BM10-BM60 -> 301815 | BN25: =BN10-BN60 -> 325519 | BO25: =BO10-BO60 -> 255915 | ... BS25: =BS10-BS60 -> 201165 | BT25: =BS25 -> 201165 | BV25: =BV10-BV60 -> 247713 | BW25: =BW10-BW60 -> 278707 | BX25: =BX10-BX60 -> 281829 | BY25: =BY10-BY60 -> 317753 | BZ25: =BZ10-BZ60 -> 270339 | CA25: =CA10-CA60 -> 310383 | CB25: =CB10-CB60 -> 328365 | CC25: =CC10-CC60 -> 333476 | ... CG25: =CG10-CG60 -> 182266 | CH25: =CG25 -> 182266 | CJ25: 247713 | CK25: 234422.08 | CL25: 194348.71 | CM25: 223062.99 | CN25: 228884.87 | CO25: 240669.79 | CP25: 234679.66 | CQ25: 197008.01 | CR25: 148007.96 | CS25: 111276.3 | CT25: 93072.106 | CU25: 116080.11 | CV25: 116080.11 | CW25: =CV27-459000 -> 1692766.6 | CX25: 247713 | CY25: 234422.08 | CZ25: 194348.71 | DA25: 223062.99 | DB25: 228884.87 | DC25: 240669.79 | DD25: 234679.66 | DE25: 197008.01 | DF25: 148007.96 | DG25: 111276.3 | DH25: 93072.106 | DI25: 116080.11 | DJ25: 116080.11
B26: Cobertura de Estoque | AF26: =AF10/AG27 -> 1.4346741 | AG26: =AG10/AH27 -> 3.9745328 | AH26: =AH10/AI27 -> 4.4537255 | AI26: =AI10/AJ27 -> 3.1781895 | AJ26: =AJ10/AK27 -> 2.7551225 | AK26: =AK10/AL27 -> 3.229797 | AL26: =AL10/AM27 -> 2.3575635 | AM26: =AM10/AN27 -> 2.1413161 | ... AP26: =AP10/AQ27 -> 5.1487735 | AQ26: =AQ10/AT27 -> 3.4807307 | AR26: =AQ26 -> 3.4807307 | AT26: =AT10/AU27 -> 2.7971286 | AU26: =AU10/AV27 -> 3.0710064 | AV26: =AV10/AW27 -> 2.584778 | AW26: =AW10/AX27 -> 3.3142308 | AX26: =AX10/AY27 -> 3.0202081 | AY26: =AY10/(AZ57+AZ56) -> 3.0375411 | AZ26: =AZ10/(BA57+BA56) -> 1.7862994 | BA26: =BA10/(BB57+BB56) -> 2.3917338 | BB26: =BB10/(BC57+BC56) -> 2.0297187 | BC26: =BC10/(BD57+BD56) -> 2.9418602 | BD26: =BD10/(BE57+BE56) -> 5.3595753 | BE26: =BE10/BH27 -> 2.3338658 | BH26: =BH10/BI27 -> 2.4324842 | BI26: =BI10/BJ27 -> 2.069479 | BJ26: =BJ10/BK27 -> 2.1548304 | BK26: =BK10/BL27 -> 2.9406585 | BL26: =BL10/BM27 -> 2.5009495 | BM26: =BM10/BN27 -> 2.0577587 | BN26: =BN10/BO27 -> 2.332053 | BV26: 0 | BW26: 0 | BX26: 0 | BY26: 0 | BZ26: 0 | CA26: 0 | CB26: 0 | CC26: 0 | CD26: 0 | CE26: 0 | CF26: 0 | CJ26: 0 | CK26: 0 | CL26: 0 | CM26: 0 | CN26: 0 | CO26: 0 | CP26: 0 | CQ26: 0 | CR26: 0 | CS26: 0 | CT26: 0 | CX26: 0 | CY26: 0 | CZ26: 0 | DA26: 0 | DB26: 0 | DC26: 0 | DD26: 0 | DE26: 0 | DF26: 0 | DG26: 0 | DH26: 0
A27: 6 | B27: Estimativa Vendas Comercial | D27: =SUM(D31:D54) -> 82250 | E27: =SUM(E31:E54) -> 117000 | F27: =SUM(F31:F54) -> 121750 | G27: =SUM(G31:G54) -> 150000 | H27: =SUM(H31:H54) -> 99500 | I27: =SUM(I31:I54) -> 102000 | J27: =SUM(J31:J54) -> 177632 | K27: =SUM(K31:K54) -> 178158 | ... P27: =SUM(P31:P54) -> 1617764 | R27: =R31+R55 -> 136177.34 | S27: =S31+S55 -> 143840.33 | T27: =T31+T55 -> 142553.77 | U27: =U31+U55 -> 19814.9 | V27: =V31+V55 -> 52085 | W27: =W31+W55 -> 70169.382 | X27: =X31+X55 -> 144463.33 | Y27: =Y31+Y55 -> 226547.08 | ... AC27: =AC31+AC55 -> 0 | AD27: =SUM(R27:AC27) -> 1418438.6 | AF27: =AF31+AF55 -> 128646 | AG27: =AG31+AG55 -> 177977 | AH27: =AH31+AH55 -> 73624 | AI27: =AI31+AI55 -> 89358 | AJ27: =AJ31+AJ55 -> 122134 | AK27: =AK31+AK55 -> 148560 | AL27: =AL31+AL55 -> 151995 | AM27: =AM31+AM55 -> 238903 | ... AQ27: =AQ31+AQ55 -> 97840 | AR27: =SUM(AF27:AQ27) -> 1874710.3 | AT27: =AT31+AT55 -> 152749.25 | AU27: =AU31+AU55 -> 168522.1 | AV27: =AV31+AV55 -> 154121.14 | AW27: =AW31+AW55 -> 159595.14 | AX27: =AX31+AX55 -> 120099.97 | AY27: =AY31+AY55 -> 138343.78 | AZ27: =AZ31+AZ55 -> 166673.78 | BA27: =BA31+BA55 -> 242442.3 | ... BD27: =BD31+BD55 -> 134555.59 | BE27: =BE31+BE56 -> 72686.613 | BF27: =SUM(AT27:BE27) -> 2006565.7 | BG27: =BF27-AR27 -> 131855.38 | BH27: =BH28+BH55 -> 152753 | BI27: =BI28+BI55 -> 146822.33 | BJ27: =BJ28+BJ55 -> 171546.07 | BK27: =BK28+BK55 -> 159771.74 | BL27: =BL28+BL55 -> 132496.85 | BM27: =BM28+BM55 -> 129906.26 | BN27: =BN28+BN55 -> 171383.56 | BO27: =BO28+BO56 -> 179550.38 | BP27: =BP28+BP56 -> 202053.75 | BQ27: =BQ28+BQ56 -> 163865 | BR27: =BR28+BR56 -> 175620.6 | BS27: 92285.6 | BT27: =SUM(BH27:BS27) -> 1878055.1 | BV27: =BV31+(BV56)*$CI$27 -> 161157.87 | BW27: =BW31+(BW56)*$CI$27 -> 155966.83 | BX27: =BX31+(BX56)*$CI$27 -> 196111.54 | BY27: =BY31+(BY56)*$CI$27 -> 159169.23 | BZ27: =BZ31+(BZ56)*$CI$27 -> 151482.39 | CA27: =CA31+(CA56)*$CI$27 -> 141442.13 | CB27: =CB31+(CB56)*$CI$27 -> 176986.21 | CC27: =CC31+(CC56)*$CI$27 -> 201301.09 | ... CG27: =CG31+(CG56)*$CI$27 -> 87483.817 | CH27: =SUM(BV27:CG27) -> 2030972.3 | CI27: 0.95 | CJ27: =CJ31+CJ65 -> 181422.94 | CK27: =CK31+CK65 -> 165852.67 | CL27: =CL31+CL65 -> 185796.68 | CM27: =CM31+CM65 -> 160056.66 | CN27: =CN31+CN65 -> 153801.95 | CO27: =CO31+CO65 -> 120180.88 | CP27: =CP31+CP65 -> 225720.09 | CQ27: =CQ31+CQ65 -> 206895.31 | ... CU27: =CU31+CU65 -> 103183.82 | CV27: =SUM(CJ27:CU27) -> 2151766.6 | CW27: 10% DE CRESCIMENTO | CX27: =CJ27*1.05 -> 190494.09 | CY27: =CK27*1.05 -> 174145.3 | CZ27: =CL27*1.05 -> 195086.51 | DA27: =CM27*1.05 -> 168059.49 | DB27: =CN27*1.05 -> 161492.05 | DC27: =CO27*1.05 -> 126189.92 | DD27: =CP27*1.05 -> 237006.09 | DE27: =CQ27*1.05 -> 217240.08 | ... DI27: =CU27*1.05 -> 108343.01 | DJ27: 1957097.2
B28: Estimativa de Venda para plano de produção | AY28: =AY31+AY56 -> 119777.78 | AZ28: =AZ31+AZ56 -> 150777.78 | BA28: =BA31+BA56 -> 233098.5 | BB28: =BB29/BB30 -> 210777.78 | BC28: =BC31+BC56 -> 249806.29 | BD28: =BD31+BD56*0.85 -> 122960.59 | BE28: =BE31+BE56*0.85 -> 66386.613 | BF28: =SUM(AT28:BE28) -> 1153585.3 | BH28: =BH29/BH30-0.1*BH29/BH30 -> 116600 | BI28: =BI29/BI30-0.1*BI29/BI30 -> 111533.33 | BJ28: =BJ29/BJ30-0.05*BJ29/BJ30 -> 135674.07 | BK28: =BK29/BK30-0.05*BK29/BK30 -> 121740.74 | BL28: =BL29/BL30-0.05*BL29/BL30 -> 93926.852 | BM28: =BM29/BM30-0.05*BM29/BM30 -> 90679.259 | BN28: =BN29/BN30-0.05*BN29/BN30 -> 130255.56 | BO28: =BO29/BO30-0.05*BO29/BO30 -> 150550.38 | BP28: =BP29/BP30-0.05*BP29/BP30 -> 161830.75 | BQ28: 127130 | BR28: 138687.6 | BS28: 43639.2 | BT28: =SUM(BH28:BS28) -> 1422247.7 | BV28: =BV31+BV55 -> 166555.78 | BW28: =BW31+BW55 -> 152835.37 | BX28: =BX31+BX55 -> 195319.21 | BY28: =BY31+BY55 -> 158396.19 | BZ28: =BZ31+BZ55 -> 152371.51 | CA28: =CA31+CA55 -> 147696.01 | CB28: =CB31+CB55 -> 189465.05 | CC28: =CC31+CC55 -> 202914.1 | ... CG28: =CG31+CG55 -> 88389.319 | CH28: =SUM(BV28:CG28) -> 2065409.9 | CI28: =(CH28-BT62)/BT62 -> 0.48621753 | CW28: =(CV28-CH62)/CH62 -> -1 | CX28: 166555.78 | CY28: 152835.37 | CZ28: 195319.21 | DA28: 158396.19 | DB28: 152371.51 | DC28: 147696.01 | DD28: 189465.05 | DE28: 202914.1 | DF28: 214499.62 | DG28: 217683 | DH28: 179284.72 | DI28: 88389.319 | DJ28: 2065409.9
B29: Estimativa Varejo em R$ | AN29: 6715000 | AO29: 6555000 | AP29: 2640000 | AQ29: 1302000 | AT29: 3264695 | AU29: 3863760 | AV29: 3429225 | AW29: 3525360 | AX29: 2509485 | AY29: 2829000 | AZ29: 3666000 | BA29: 5705000 | BB29: 5691000 | BC29: 5600000 | BD29: 2430000 | BE29: 800000 | BF29: =SUM(AT29:BE29) -> 43313525 | BH29: 3498000 | BI29: 3346000 | BJ29: 3856000 | BK29: 3460000 | BL29: 2669500 | BM29: 2577200 | BN29: 3702000 | BO29: 4278800.2 | BP29: 4599400.2 | BQ29: =BQ28*BQ30 -> 3432510 | BR29: 2954493.2 | BS29: 984831.07 | BT29: =SUM(BH29:BS29) -> 39358735 | BV29: =BV30*BV31 -> 3399704.6 | BW29: =BW30*BW31 -> 3264737.6 | BX29: =BX30*BX31 -> 4185000 | BY29: =BY30*BY31 -> 3348000 | BZ29: =BZ30*BZ31 -> 3074042.2 | CA29: =CA30*CA31 -> 2812995.4 | CB29: =CB30*CB31 -> 3737141.6 | CC29: =CC30*CC31 -> 4437000.7 | ... CG29: =CG30*CG31 -> 792579.23 | CH29: =SUM(BV29:CG29) -> 41966781 | CJ29: =CJ30*CJ31 -> 4023031.5 | CK29: =CK30*CK31 -> 3734347.7 | CL29: =CL30*CL31 -> 4223923.1 | CM29: =CM30*CM31 -> 3507679 | CN29: =CN30*CN31 -> 3217429.2 | CO29: =CO30*CO31 -> 2332522.6 | CP29: =CP30*CP31 -> 5138020.6 | CQ29: =CQ30*CQ31 -> 4640709 | ... CV29: =CV30*CV31 -> 46446711 | CX29: 3399704.6 | CY29: 3264737.6 | CZ29: 4185000 | DA29: 3348000 | DB29: 3074042.2 | DC29: 2812995.4 | DD29: 3737141.6 | DE29: 4437000.7 | DF29: 4710370.4 | DG29: 4744197 | DH29: 3461011.9 | DI29: 792579.23 | DJ29: 41966781
B30: Ticket Médio R$ | AN30: =30 -> 30 | AO30: =30 -> 30 | AP30: =30 -> 30 | AQ30: =30 -> 30 | AT30: 28 | AU30: 29 | AV30: 29 | AW30: 29 | AX30: 29 | AY30: 27 | AZ30: 27 | BA30: 27 | BB30: 27 | BC30: 26.07 | BD30: 26.07 | BE30: 26.07 | BH30: 27 | BI30: 27 | BJ30: 27 | BK30: 27 | BL30: 27 | BM30: 27 | BN30: 27 | BO30: 27 | BP30: 27 | BQ30: 27 | BR30: 27 | BS30: 27 | BV30: 26 | BW30: 26 | BX30: 26 | BY30: 26 | BZ30: 26 | CA30: 26 | CB30: 26 | CC30: 26 | CD30: 26 | CE30: 26 | CF30: 26 | CG30: 26 | CJ30: 26.32 | CK30: =CJ30 -> 26.32 | CL30: =CK30 -> 26.32 | CM30: =CL30 -> 26.32 | CN30: =CM30 -> 26.32 | CO30: =CN30 -> 26.32 | CP30: =CO30 -> 26.32 | CQ30: =CP30 -> 26.32 | CR30: =CQ30 -> 26.32 | ... CV30: =CU30 -> 26.32 | CX30: 26 | CY30: 26 | CZ30: 26 | DA30: 26 | DB30: 26 | DC30: 26 | DD30: 26 | DE30: 26 | DF30: 26 | DG30: 26 | DH30: 26 | DI30: 26
B31: Estimativa Varejo Multimarcas | D31: 82250 | E31: 117000 | F31: 121750 | G31: 150000 | H31: 99500 | I31: 102000 | J31: 177632 | K31: 178158 | L31: 199211 | M31: 229474 | N31: 122368 | O31: 38421 | P31: =SUM(D31:O31) -> 1617764 | R31: 115619.8 | S31: 123327.78 | T31: 128854 | U31: =126016*0.15 -> 18902.4 | V31: 35234 | W31: 56469.382 | X31: 118413.33 | Y31: 198797.08 | Z31: 242087.5 | AA31: 140000 | AB31: 0 | AC31: -45300 | AD31: =SUM(R31:AC31) -> 1132405.3 | AF31: 90146 | AG31: 155577 | AH31: 62953 | AI31: 73261 | AJ31: 91856 | AK31: 120000 | AL31: 110295 | AM31: 200203 | AN31: =AN29/AN30 -> 223833.33 | AO31: =AO29/AO30 -> 218500 | AP31: =AP29/AP30 -> 88000 | AQ31: =AQ29/AQ30 -> 43400 | AR31: =SUM(AF31:AQ31) -> 1478024.3 | AT31: =AT29/AT30 -> 116596.25 | AU31: =AU29/AU30 -> 133233.1 | AV31: =AV29/AV30 -> 118249.14 | AW31: =AW29/AW30 -> 121564.14 | AX31: =AX29/AX30 -> 86533.966 | AY31: =AY29/AY30 -> 104777.78 | AZ31: =AZ29/AZ30 -> 135777.78 | BA31: =BA29/BA30 -> 211296.3 | ... BE31: =BE29/BE30 -> 30686.613 | BF31: =SUM(AT31:BE31) -> 1577509.7 | BG31: =BF31-AR31 -> 99485.382 | BH31: =BH28 -> 116600 | BI31: =BI28 -> 111533.33 | BJ31: =BJ28 -> 135674.07 | BK31: =BK28 -> 121740.74 | BL31: =BL28 -> 93926.852 | BM31: =BM28 -> 90679.259 | BN31: =BN28 -> 130255.56 | BO31: =BO28 -> 150550.38 | ... BT31: =BT28 -> 1422247.7 | BV31: ='META EM PEÇAS'!S73 -> 130757.87 | BW31: ='META EM PEÇAS'!T73 -> 125566.83 | BX31: ='META EM PEÇAS'!U73 -> 160961.54 | BY31: ='META EM PEÇAS'!V73 -> 128769.23 | BZ31: ='META EM PEÇAS'!W73 -> 118232.39 | CA31: ='META EM PEÇAS'!X73 -> 108192.13 | CB31: ='META EM PEÇAS'!Y73 -> 143736.21 | CC31: ='META EM PEÇAS'!Z73 -> 170653.87 | ... CG31: ='META EM PEÇAS'!AD73 -> 30483.817 | CH31: 45 | CI31: =CH31*26 -> 1170 | CJ31: =BV62*1.19 -> 152850.74 | CK31: =BW62*1.19 -> 141882.51 | CL31: =BX62*1.19 -> 160483.4 | CM31: =BY62*1.19 -> 133270.48 | CN31: =BZ62*1.19 -> 122242.75 | CO31: =CA62*1.19 -> 88621.68 | CP31: =CB62*1.19 -> 195213.55 | CQ31: =CC62*1.19 -> 176318.73 | ... CU31: =CG62*1.19 -> 47560.73 | CV31: =SUM(CJ31:CU31) -> 1764692.6 | CW31: =CV31*26 -> 45882009 | CX31: 130757.87 | CY31: 125566.83 | CZ31: 160961.54 | DA31: 128769.23 | DB31: 118232.39 | DC31: 108192.13 | DD31: 143736.21 | DE31: 170653.87 | DF31: 181168.09 | DG31: 182469.12 | DH31: 133115.84 | DI31: 30483.817 | DJ31: 1614106.9
CJ32: =BV62 -> 128446 | CK32: =BW62 -> 119229 | CL32: =BX62 -> 134860 | CM32: =BY62 -> 111992 | CN32: =BZ62 -> 102725 | CO32: =CA62 -> 74472 | CP32: =CB62 -> 164045 | CQ32: =CC62 -> 148167 | ... CU32: =CG62 -> 39967 | CV32: =SUM(CJ32:CU32) -> 1482935
CJ33: =(CJ31-CJ32)/CJ32 -> 0.19 | CK33: =(CK31-CK32)/CK32 -> 0.19 | CL33: =(CL31-CL32)/CL32 -> 0.19 | CM33: =(CM31-CM32)/CM32 -> 0.19 | CN33: =(CN31-CN32)/CN32 -> 0.19 | CO33: =(CO31-CO32)/CO32 -> 0.19 | CP33: =(CP31-CP32)/CP32 -> 0.19 | CQ33: =(CQ31-CQ32)/CQ32 -> 0.19 | ... CU33: =(CU31-CU32)/CU32 -> 0.19
A34: 1 | B34: Loja Maraponga | P34: =SUM(D34:O34) -> 0 | R34: 7017.5439 | S34: 7017.5439 | T34: =7017.54385964912/2 -> 3508.7719 | U34: =96*U7 -> 96 | V34: 3000 | W34: 7200 | X34: 8500 | Y34: 8500 | Z34: 8500 | AA34: 9000 | AB34: 9500 | AC34: 8500 | AD34: =SUM(R34:AC34) -> 80339.86 | AF34: 8000 | AG34: 4000 | AH34: 5673 | AI34: 4500 | AJ34: 7892 | AK34: 6400 | AL34: 8000 | AM34: 8000 | AN34: 8000 | AO34: 8000 | AP34: 8800 | AQ34: 6400 | AR34: =SUM(AF34:AQ34) -> 83665 | AT34: 4861 | AU34: 5809 | AV34: 5072 | AW34: 4725 | AX34: 5832 | AY34: 5832 | AZ34: 5567 | BA34: 5567 | BB34: 5832 | BC34: 6892 | BD34: 7422 | BE34: 4241 | BF34: =SUM(AT34:BE34) -> 67652 | BG34: =BF34/AR34-1 -> -0.19139425 | BT34: 36051 | BV34: 4782.99 | BW34: 2945.31 | BX34: ='META EM PEÇAS'!U26-('META EM PEÇAS'!U26*0.05) -> 7080.369 | BY34: ='META EM PEÇAS'!V26-('META EM PEÇAS'!V26*0.05) -> 4355.655 | BZ34: ='META EM PEÇAS'!W26-('META EM PEÇAS'!W26*0.05) -> 5839.935 | CA34: ='META EM PEÇAS'!X26-('META EM PEÇAS'!X26*0.05) -> 5900.8965 | CB34: ='META EM PEÇAS'!Y26-('META EM PEÇAS'!Y26*0.05) -> 5279.796 | CC34: ='META EM PEÇAS'!Z26-('META EM PEÇAS'!Z26*0.05) -> 4897.2405 | CD34: ='META EM PEÇAS'!AA26-('META EM PEÇAS'!AA26*0.05) -> 5018.28 | CE34: ='META EM PEÇAS'!AB26-('META EM PEÇAS'!AB26*0.05) -> 4641.0255 | ... CG34: ='META EM PEÇAS'!AD26-('META EM PEÇAS'!AD26*0.05) -> 3929.808 | CH34: 4136.64 | CJ34: 4782.99 | CK34: 2945.31 | CL34: 7080.369 | CM34: 4355.655 | CN34: 5839.935 | CO34: 5900.8965 | CP34: 5279.796 | CQ34: 4897.2405 | CR34: 5018.28 | CS34: 4641.0255 | CT34: 6521.1135 | CU34: 3929.808 | CV34: 4136.64 | CX34: 4782.99 | CY34: 2945.31 | CZ34: 7080.369 | DA34: 4355.655 | DB34: 5839.935 | DC34: 5900.8965 | DD34: 5279.796 | DE34: 4897.2405 | DF34: 5018.28 | DG34: 4641.0255 | DH34: 6521.1135 | DI34: 3929.808 | DJ34: 4136.64
A35: 2 | B35: Loja Iguatemi | P35: =SUM(D35:O35) -> 0 | R35: 2909 | S35: 2545 | T35: =2727/1.2 -> 2272.5 | U35: =2*U7 -> 2 | V35: 500 | W35: 1300 | X35: 3200 | Y35: 3200 | Z35: 3600 | AA35: 3600 | AB35: 3600 | AC35: 4500 | AD35: =SUM(R35:AC35) -> 31228.5 | AF35: 4000 | AG35: 1500 | AH35: 189 | AI35: 1842 | AJ35: 3764 | AK35: 3200 | AL35: 6000 | AM35: 5000 | AN35: 5000 | AO35: 5000 | AP35: 5000 | AQ35: 9000 | AR35: =SUM(AF35:AQ35) -> 49495 | AT35: 5468 | AU35: 5468 | AV35: 6249 | AW35: 6249 | AX35: 3923 | AY35: 3923 | AZ35: 3745 | BA35: 3745 | BB35: 3923 | BC35: 4636 | BD35: 4993 | BE35: 7133 | BF35: =SUM(AT35:BE35) -> 59455 | BG35: =BF35/AR35-1 -> 0.20123245 | BT35: 40562 | BV35: 4442.61 | BW35: 3433.56 | BX35: ='META EM PEÇAS'!U27-('META EM PEÇAS'!U27*0.05) -> 3860.0115 | BY35: ='META EM PEÇAS'!V27-('META EM PEÇAS'!V27*0.05) -> 3578.175 | BZ35: ='META EM PEÇAS'!W27-('META EM PEÇAS'!W27*0.05) -> 4015.5075 | CA35: ='META EM PEÇAS'!X27-('META EM PEÇAS'!X27*0.05) -> 4835.3955 | CB35: ='META EM PEÇAS'!Y27-('META EM PEÇAS'!Y27*0.05) -> 5815.197 | CC35: ='META EM PEÇAS'!Z27-('META EM PEÇAS'!Z27*0.05) -> 3888.2835 | CD35: ='META EM PEÇAS'!AA27-('META EM PEÇAS'!AA27*0.05) -> 4032.294 | CE35: ='META EM PEÇAS'!AB27-('META EM PEÇAS'!AB27*0.05) -> 4375.092 | ... CG35: ='META EM PEÇAS'!AD27-('META EM PEÇAS'!AD27*0.05) -> 7897.6065 | CH35: =SUM(BV35:CG35) -> 55778.656 | CJ35: 4442.61 | CK35: 3433.56 | CL35: 3860.0115 | CM35: 3578.175 | CN35: 4015.5075 | CO35: 4835.3955 | CP35: 5815.197 | CQ35: 3888.2835 | CR35: 4032.294 | CS35: 4375.092 | CT35: 5604.924 | CU35: 7897.6065 | CV35: 55778.656 | CX35: 4442.61 | CY35: 3433.56 | CZ35: 3860.0115 | DA35: 3578.175 | DB35: 4015.5075 | DC35: 4835.3955 | DD35: 5815.197 | DE35: 3888.2835 | DF35: 4032.294 | DG35: 4375.092 | DH35: 5604.924 | DI35: 7897.6065 | DJ35: 55778.656
A36: 3 | B36: Loja Monsenhor Tabosa | P36: =SUM(D36:O36) -> 0 | R36: 746 | S36: 653 | T36: 700 | U36: 0 | V36: 200 | W36: 400 | X36: 900 | Y36: 900 | Z36: 900 | AA36: 900 | AB36: 900 | AC36: 1200 | AD36: =SUM(R36:AC36) -> 8399 | AF36: 1800 | AG36: 1200 | AH36: 230 | AI36: 472 | AJ36: 1495 | AK36: 1200 | AL36: 1500 | AM36: 1500 | AN36: 1500 | AO36: 1500 | AP36: 1650 | AQ36: 2400 | AR36: =SUM(AF36:AQ36) -> 16447 | AT36: 2438 | AU36: 1501 | AV36: 1566 | AW36: 2127 | AX36: 1928 | AY36: 1928 | AZ36: 1840 | BA36: 1840 | BB36: 1928 | BC36: 2278 | BD36: 2454 | BE36: 3505 | BF36: =SUM(AT36:BE36) -> 25333 | BG36: =BF36/AR36-1 -> 0.5402809 | BT36: 7784 | BV36: 451 | BW36: 348.6 | BX36: ='META EM PEÇAS'!U28-('META EM PEÇAS'!U28*0.05) -> 391.97 | BY36: ='META EM PEÇAS'!V28-('META EM PEÇAS'!V28*0.05) -> 363.28 | BZ36: ='META EM PEÇAS'!W28-('META EM PEÇAS'!W28*0.05) -> 407.55 | CA36: ='META EM PEÇAS'!X28-('META EM PEÇAS'!X28*0.05) -> 490.77 | CB36: ='META EM PEÇAS'!Y28-('META EM PEÇAS'!Y28*0.05) -> 590.33 | CC36: ='META EM PEÇAS'!Z28-('META EM PEÇAS'!Z28*0.05) -> 394.63 | CD36: ='META EM PEÇAS'!AA28-('META EM PEÇAS'!AA28*0.05) -> 409.26 | CE36: ='META EM PEÇAS'!AB28-('META EM PEÇAS'!AB28*0.05) -> 444.22 | ... CG36: ='META EM PEÇAS'!AD28-('META EM PEÇAS'!AD28*0.05) -> 801.8 | CH36: =SUM(BV36:CG36) -> 5662.46 | CJ36: 451 | CK36: 348.6 | CL36: 391.97 | CM36: 363.28 | CN36: 407.55 | CO36: 490.77 | CP36: 590.33 | CQ36: 394.63 | CR36: 409.26 | CS36: 444.22 | CT36: 569.05 | CU36: 801.8 | CV36: 5662.46 | CX36: 451 | CY36: 348.6 | CZ36: 391.97 | DA36: 363.28 | DB36: 407.55 | DC36: 490.77 | DD36: 590.33 | DE36: 394.63 | DF36: 409.26 | DG36: 444.22 | DH36: 569.05 | DI36: 801.8 | DJ36: 5662.46
A37: 4 | B37: Loja North Shopping | P37: =SUM(D37:O37) -> 0 | R37: 1455 | S37: =2036 -> 2036 | T37: =2182/2 -> 1091 | U37: 0 | V37: 200 | W37: 900 | X37: 1600 | Y37: 1600 | Z37: 1600 | AA37: 1600 | AB37: 2200 | AC37: 2500 | AD37: =SUM(R37:AC37) -> 16782 | AF37: 2200 | AG37: 1500 | AH37: 121 | AI37: 565 | AJ37: 1514 | AK37: 1760 | AL37: 1800 | AM37: 2200 | AN37: 2200 | AO37: 2200 | AP37: 2420 | AQ37: 3520 | AR37: =SUM(AF37:AQ37) -> 22000 | AT37: 1529 | AU37: 1516 | AV37: 1586 | AW37: 1979 | AX37: 1283 | AY37: 1283 | AZ37: 1224 | BA37: 1224 | BB37: 1283 | BC37: 1516 | BD37: 1632 | BE37: 2332 | BF37: =SUM(AT37:BE37) -> 18387 | BG37: =BF37/AR37-1 -> -0.16422727 | BT37: 9018 | BV37: 1143.9 | BW37: 884.43 | BX37: ='META EM PEÇAS'!U29-('META EM PEÇAS'!U29*0.05) -> 993.9375 | BY37: ='META EM PEÇAS'!V29-('META EM PEÇAS'!V29*0.05) -> 921.4905 | BZ37: ='META EM PEÇAS'!W29-('META EM PEÇAS'!W29*0.05) -> 1033.695 | CA37: ='META EM PEÇAS'!X29-('META EM PEÇAS'!X29*0.05) -> 1244.8515 | CB37: ='META EM PEÇAS'!Y29-('META EM PEÇAS'!Y29*0.05) -> 1497.5325 | CC37: ='META EM PEÇAS'!Z29-('META EM PEÇAS'!Z29*0.05) -> 1001.0055 | CD37: ='META EM PEÇAS'!AA29-('META EM PEÇAS'!AA29*0.05) -> 1038.1125 | CE37: ='META EM PEÇAS'!AB29-('META EM PEÇAS'!AB29*0.05) -> 1126.4625 | ... CG37: ='META EM PEÇAS'!AD29-('META EM PEÇAS'!AD29*0.05) -> 2033.817 | CH37: =SUM(BV37:CG37) -> 14362.873 | CJ37: 1143.9 | CK37: 884.43 | CL37: 993.9375 | CM37: 921.4905 | CN37: 1033.695 | CO37: 1244.8515 | CP37: 1497.5325 | CQ37: 1001.0055 | CR37: 1038.1125 | CS37: 1126.4625 | CT37: 1443.639 | CU37: 2033.817 | CV37: 14362.873 | CX37: 1143.9 | CY37: 884.43 | CZ37: 993.9375 | DA37: 921.4905 | DB37: 1033.695 | DC37: 1244.8515 | DD37: 1497.5325 | DE37: 1001.0055 | DF37: 1038.1125 | DG37: 1126.4625 | DH37: 1443.639 | DI37: 2033.817 | DJ37: 14362.873
A38: 5 | B38: Loja Dom Luis | P38: =SUM(D38:O38) -> 0 | R38: 1353 | S38: 1184 | T38: 1268 | U38: =10*U7 -> 10 | V38: =10*V7 -> 120 | W38: 600 | X38: 1600 | Y38: 1600 | Z38: 1600 | AA38: 1600 | AB38: 1600 | AC38: 2200 | AD38: =SUM(R38:AC38) -> 14735 | AF38: 1800 | AG38: 1200 | AH38: 181 | AI38: 628 | AJ38: 1169 | AK38: 960 | AL38: 1500 | AM38: 1200 | AN38: 1200 | AO38: 1200 | AP38: 1320 | AQ38: 1920 | AR38: =SUM(AF38:AQ38) -> 14278 | AT38: 1496 | AU38: 1200 | AV38: 1227 | AW38: 1655 | AX38: 1141 | AY38: 1141 | AZ38: 1089 | BA38: 1089 | BB38: 1141 | BC38: 1349 | BD38: 1453 | BE38: 2075 | BF38: =SUM(AT38:BE38) -> 16056 | BG38: =BF38/AR38-1 -> 0.12452724 | BT38: 10591 | BV38: 1474.98 | BW38: 1140.18 | BX38: ='META EM PEÇAS'!U30-('META EM PEÇAS'!U30*0.05) -> 1281.9585 | BY38: ='META EM PEÇAS'!V30-('META EM PEÇAS'!V30*0.05) -> 1188.3075 | BZ38: ='META EM PEÇAS'!W30-('META EM PEÇAS'!W30*0.05) -> 1333.2015 | CA38: ='META EM PEÇAS'!X30-('META EM PEÇAS'!X30*0.05) -> 1606.203 | CB38: ='META EM PEÇAS'!Y30-('META EM PEÇAS'!Y30*0.05) -> 1931.331 | CC38: ='META EM PEÇAS'!Z30-('META EM PEÇAS'!Z30*0.05) -> 1291.677 | CD38: ='META EM PEÇAS'!AA30-('META EM PEÇAS'!AA30*0.05) -> 1339.386 | CE38: ='META EM PEÇAS'!AB30-('META EM PEÇAS'!AB30*0.05) -> 1453.3575 | ... CG38: ='META EM PEÇAS'!AD30-('META EM PEÇAS'!AD30*0.05) -> 2623.1115 | CH38: =SUM(BV38:CG38) -> 18525.228 | CJ38: 1474.98 | CK38: 1140.18 | CL38: 1281.9585 | CM38: 1188.3075 | CN38: 1333.2015 | CO38: 1606.203 | CP38: 1931.331 | CQ38: 1291.677 | CR38: 1339.386 | CS38: 1453.3575 | CT38: 1861.5345 | CU38: 2623.1115 | CV38: 18525.228 | CX38: 1474.98 | CY38: 1140.18 | CZ38: 1281.9585 | DA38: 1188.3075 | DB38: 1333.2015 | DC38: 1606.203 | DD38: 1931.331 | DE38: 1291.677 | DF38: 1339.386 | DG38: 1453.3575 | DH38: 1861.5345 | DI38: 2623.1115 | DJ38: 18525.228
A39: 6 | B39: Loja Parangaba | P39: =SUM(D39:O39) -> 0 | R39: 1455 | S39: 1273 | T39: 1364 | U39: 0 | V39: 200 | W39: 800 | X39: 1600 | Y39: 1600 | Z39: 1600 | AA39: 1600 | AB39: 1800 | AC39: 2400 | AD39: =SUM(R39:AC39) -> 15692 | AF39: 1500 | AG39: 1200 | AH39: 127 | AI39: 426 | AJ39: 1063 | AK39: 960 | AL39: 1500 | AM39: 1200 | AN39: 1200 | AO39: 1200 | AP39: 1320 | AQ39: 1920 | AR39: =SUM(AF39:AQ39) -> 13616 | AT39: 1222 | AU39: 1200 | AV39: 1117 | AW39: 1463 | AX39: 1087 | AY39: 1087 | AZ39: 1038 | BA39: 1038 | BB39: 1087 | BC39: 1285 | BD39: 1384 | BE39: 1977 | BF39: =SUM(AT39:BE39) -> 14985 | BG39: =BF39/AR39-1 -> 0.10054348 | BT39: 10087 | BV39: 1214.58 | BW39: 939.3 | BX39: ='META EM PEÇAS'!U31-('META EM PEÇAS'!U31*0.05) -> 1055.7825 | BY39: ='META EM PEÇAS'!V31-('META EM PEÇAS'!V31*0.05) -> 978.0345 | BZ39: ='META EM PEÇAS'!W31-('META EM PEÇAS'!W31*0.05) -> 1098.1905 | CA39: ='META EM PEÇAS'!X31-('META EM PEÇAS'!X31*0.05) -> 1322.5995 | CB39: ='META EM PEÇAS'!Y31-('META EM PEÇAS'!Y31*0.05) -> 1590.3 | CC39: ='META EM PEÇAS'!Z31-('META EM PEÇAS'!Z31*0.05) -> 1062.8505 | CD39: ='META EM PEÇAS'!AA31-('META EM PEÇAS'!AA31*0.05) -> 1102.608 | CE39: ='META EM PEÇAS'!AB31-('META EM PEÇAS'!AB31*0.05) -> 1196.259 | ... CG39: ='META EM PEÇAS'!AD31-('META EM PEÇAS'!AD31*0.05) -> 2160.1575 | CH39: =SUM(BV39:CG39) -> 15253.534 | CJ39: 1214.58 | CK39: 939.3 | CL39: 1055.7825 | CM39: 978.0345 | CN39: 1098.1905 | CO39: 1322.5995 | CP39: 1590.3 | CQ39: 1062.8505 | CR39: 1102.608 | CS39: 1196.259 | CT39: 1532.8725 | CU39: 2160.1575 | CV39: 15253.534 | CX39: 1214.58 | CY39: 939.3 | CZ39: 1055.7825 | DA39: 978.0345 | DB39: 1098.1905 | DC39: 1322.5995 | DD39: 1590.3 | DE39: 1062.8505 | DF39: 1102.608 | DG39: 1196.259 | DH39: 1532.8725 | DI39: 2160.1575 | DJ39: 15253.534
A40: 7 | B40: Loja Rio Mar | P40: =SUM(D40:O40) -> 0 | R40: 2000 | S40: =2182 -> 2182 | T40: =2455/2 -> 1227.5 | U40: =4*U7 -> 4 | V40: 200 | W40: 700 | X40: 1600 | Y40: 1600 | Z40: 1600 | AA40: 1600 | AB40: 2500 | AC40: 3200 | AD40: =SUM(R40:AC40) -> 18413.5 | AF40: 2600 | AG40: 1000 | AH40: 195 | AI40: 844 | AJ40: 1973 | AK40: 1840 | AL40: 2000 | AM40: 2300 | AN40: 2300 | AO40: 2300 | AP40: 2530 | AQ40: 3680 | AR40: =SUM(AF40:AQ40) -> 23562 | AT40: 1888 | AU40: 1414 | AV40: 2073 | AW40: 2338 | AX40: 1857 | AY40: 1857 | AZ40: 1772 | BA40: 1772 | BB40: 1857 | BC40: 2194 | BD40: 2363 | BE40: 3376 | BF40: =SUM(AT40:BE40) -> 24761 | BG40: =BF40/AR40-1 -> 0.050887021 | BT40: 22941 | BV40: 3211.29 | BW40: 2482.17 | BX40: ='META EM PEÇAS'!U32-('META EM PEÇAS'!U32*0.05) -> 2790.093 | BY40: ='META EM PEÇAS'!V32-('META EM PEÇAS'!V32*0.05) -> 2586.0045 | BZ40: ='META EM PEÇAS'!W32-('META EM PEÇAS'!W32*0.05) -> 2902.2975 | CA40: ='META EM PEÇAS'!X32-('META EM PEÇAS'!X32*0.05) -> 3495.126 | CB40: ='META EM PEÇAS'!Y32-('META EM PEÇAS'!Y32*0.05) -> 4203.693 | CC40: ='META EM PEÇAS'!Z32-('META EM PEÇAS'!Z32*0.05) -> 2810.4135 | CD40: ='META EM PEÇAS'!AA32-('META EM PEÇAS'!AA32*0.05) -> 2914.6665 | CE40: ='META EM PEÇAS'!AB32-('META EM PEÇAS'!AB32*0.05) -> 3162.93 | ... CG40: ='META EM PEÇAS'!AD32-('META EM PEÇAS'!AD32*0.05) -> 5709.177 | CH40: =SUM(BV40:CG40) -> 40319.592 | CJ40: 3211.29 | CK40: 2482.17 | CL40: 2790.093 | CM40: 2586.0045 | CN40: 2902.2975 | CO40: 3495.126 | CP40: 4203.693 | CQ40: 2810.4135 | CR40: 2914.6665 | CS40: 3162.93 | CT40: 4051.731 | CU40: 5709.177 | CV40: 40319.592 | CX40: 3211.29 | CY40: 2482.17 | CZ40: 2790.093 | DA40: 2586.0045 | DB40: 2902.2975 | DC40: 3495.126 | DD40: 4203.693 | DE40: 2810.4135 | DF40: 2914.6665 | DG40: 3162.93 | DH40: 4051.731 | DI40: 5709.177 | DJ40: 40319.592
A41: 9 | B41: Loja Joquei | P41: =SUM(D41:O41) -> 0 | R41: 1636 | S41: 1636 | T41: =1818/2 -> 909 | U41: 0 | V41: 200 | W41: 300 | X41: 1000 | Y41: 1200 | Z41: 1600 | AA41: 1600 | AB41: 1800 | AC41: 2300 | AD41: =SUM(R41:AC41) -> 14181 | AF41: 1500 | AG41: 1000 | AH41: 126 | AI41: 387 | AJ41: 895 | AK41: 800 | AL41: 1500 | AM41: 1000 | AN41: 1000 | AO41: 1000 | AP41: 1100 | AQ41: 1600 | AR41: =SUM(AF41:AQ41) -> 11908 | AT41: 1182 | AU41: 1200 | AV41: 932 | AW41: 1020 | AX41: 0 | AY41: 0 | AZ41: 0 | BA41: 0 | BB41: 0 | BC41: 0 | BD41: 0 | BE41: 0 | BF41: =SUM(AT41:BE41) -> 4334 | BG41: =BF41/AR41-1 -> -0.636043 | BT41: 7070 | BV41: 928.14 | BW41: 717.96 | BX41: ='META EM PEÇAS'!U37-('META EM PEÇAS'!U37*0.05) -> 806.6355 | BY41: ='META EM PEÇAS'!V37-('META EM PEÇAS'!V37*0.05) -> 747.441 | BZ41: ='META EM PEÇAS'!W37-('META EM PEÇAS'!W37*0.05) -> 839.325 | CA41: ='META EM PEÇAS'!X37-('META EM PEÇAS'!X37*0.05) -> 1010.724 | CB41: ='META EM PEÇAS'!Y37-('META EM PEÇAS'!Y37*0.05) -> 1214.8125 | CC41: ='META EM PEÇAS'!Z37-('META EM PEÇAS'!Z37*0.05) -> 812.82 | CD41: ='META EM PEÇAS'!AA37-('META EM PEÇAS'!AA37*0.05) -> 842.859 | CE41: ='META EM PEÇAS'!AB37-('META EM PEÇAS'!AB37*0.05) -> 914.4225 | ... CG41: ='META EM PEÇAS'!AD37-('META EM PEÇAS'!AD37*0.05) -> 1650.378 | CH41: =SUM(BV41:CG41) -> 11657.038 | CJ41: 928.14 | CK41: 717.96 | CL41: 806.6355 | CM41: 747.441 | CN41: 839.325 | CO41: 1010.724 | CP41: 1214.8125 | CQ41: 812.82 | CR41: 842.859 | CS41: 914.4225 | CT41: 1171.521 | CU41: 1650.378 | CV41: 11657.038 | CX41: 928.14 | CY41: 717.96 | CZ41: 806.6355 | DA41: 747.441 | DB41: 839.325 | DC41: 1010.724 | DD41: 1214.8125 | DE41: 812.82 | DF41: 842.859 | DG41: 914.4225 | DH41: 1171.521 | DI41: 1650.378 | DJ41: 11657.038
A42: 10 | B42: Loja Barra da Tijuca | P42: =SUM(D42:O42) -> 0 | R42: 1636 | S42: 1636 | T42: =1818/2 -> 909 | U42: =0.5*U7 -> 0.5 | V42: 200 | W42: 300 | X42: 1000 | Y42: 1200 | Z42: 1600 | AA42: 1600 | AB42: 1800 | AC42: 2300 | AD42: =SUM(R42:AC42) -> 14181.5 | AF42: 1500 | AG42: 1000 | AH42: 764 | AI42: 561 | AJ42: 1353 | AK42: 960 | AL42: 1500 | AM42: 1200 | AN42: 1200 | AO42: 1200 | AP42: 1320 | AQ42: 1920 | AR42: =SUM(AF42:AQ42) -> 14478 | AT42: 1285 | AU42: 957 | AV42: 1426 | AW42: 1595 | AX42: 1767 | AY42: 1767 | AZ42: 1686 | BA42: 1686 | BB42: 1767 | BC42: 2088 | BD42: 2248 | BE42: 3212 | BF42: =SUM(AT42:BE42) -> 21484 | BG42: =BF42/AR42-1 -> 0.48390662 | BT42: 16952 | BV42: 2631.9 | BW42: 2034.84 | BX42: ='META EM PEÇAS'!U33-('META EM PEÇAS'!U33*0.05) -> 2287.3815 | BY42: ='META EM PEÇAS'!V33-('META EM PEÇAS'!V33*0.05) -> 2119.5165 | BZ42: ='META EM PEÇAS'!W33-('META EM PEÇAS'!W33*0.05) -> 2379.2655 | CA42: ='META EM PEÇAS'!X33-('META EM PEÇAS'!X33*0.05) -> 2865.1905 | CB42: ='META EM PEÇAS'!Y33-('META EM PEÇAS'!Y33*0.05) -> 3445.65 | CC42: ='META EM PEÇAS'!Z33-('META EM PEÇAS'!Z33*0.05) -> 2303.2845 | CD42: ='META EM PEÇAS'!AA33-('META EM PEÇAS'!AA33*0.05) -> 2388.984 | CE42: ='META EM PEÇAS'!AB33-('META EM PEÇAS'!AB33*0.05) -> 2592.189 | ... CG42: ='META EM PEÇAS'!AD33-('META EM PEÇAS'!AD33*0.05) -> 4679.8995 | CH42: =SUM(BV42:CG42) -> 33049.177 | CJ42: 2631.9 | CK42: 2034.84 | CL42: 2287.3815 | CM42: 2119.5165 | CN42: 2379.2655 | CO42: 2865.1905 | CP42: 3445.65 | CQ42: 2303.2845 | CR42: 2388.984 | CS42: 2592.189 | CT42: 3321.0765 | CU42: 4679.8995 | CV42: 33049.177 | CX42: 2631.9 | CY42: 2034.84 | CZ42: 2287.3815 | DA42: 2119.5165 | DB42: 2379.2655 | DC42: 2865.1905 | DD42: 3445.65 | DE42: 2303.2845 | DF42: 2388.984 | DG42: 2592.189 | DH42: 3321.0765 | DI42: 4679.8995 | DJ42: 33049.177
A43: 10 | B43: Loja Kennedy | P43: =SUM(D43:O43) -> 0 | R43: 0 | S43: 0 | T43: 0 | U43: 0 | V43: 3500 | W43: 350 | X43: 800 | Y43: 1000 | Z43: 1600 | AA43: 2000 | AB43: 2400 | AC43: 3000 | AD43: =SUM(R43:AC43) -> 14650 | AF43: 2500 | AG43: 1000 | AH43: =2500*0.15 -> 375 | AI43: 787 | AJ43: 1569 | AK43: 2000 | AL43: 2500 | AM43: 2500 | AN43: 2500 | AO43: 2500 | AP43: 2750 | AQ43: 4000 | AR43: =SUM(AF43:AQ43) -> 24981 | AT43: 1806 | AU43: 2046 | AV43: 1646 | AW43: 1902 | AX43: 1545 | AY43: 1545 | AZ43: 1475 | BA43: 1475 | BB43: 1545 | BC43: 1826 | BD43: 0 | BE43: 0 | BF43: =SUM(AT43:BE43) -> 16811 | BG43: =BF43/AR43-1 -> -0.32704856 | BT43: 10230 | BV43: 1335.48 | BW43: 1032.3 | BX43: ='META EM PEÇAS'!U39-('META EM PEÇAS'!U39*0.05) -> 1160.0355 | BY43: ='META EM PEÇAS'!V39-('META EM PEÇAS'!V39*0.05) -> 1075.2195 | BZ43: ='META EM PEÇAS'!W39-('META EM PEÇAS'!W39*0.05) -> 1206.861 | CA43: ='META EM PEÇAS'!X39-('META EM PEÇAS'!X39*0.05) -> 1453.3575 | CB43: ='META EM PEÇAS'!Y39-('META EM PEÇAS'!Y39*0.05) -> 1747.563 | CC43: ='META EM PEÇAS'!Z39-('META EM PEÇAS'!Z39*0.05) -> 1168.8705 | CD43: ='META EM PEÇAS'!AA39-('META EM PEÇAS'!AA39*0.05) -> 1212.162 | CE43: ='META EM PEÇAS'!AB39-('META EM PEÇAS'!AB39*0.05) -> 1314.648 | ... CG43: ='META EM PEÇAS'!AD39-('META EM PEÇAS'!AD39*0.05) -> 2373.9645 | CH43: =SUM(BV43:CG43) -> 16765.296 | CJ43: 1335.48 | CK43: 1032.3 | CL43: 1160.0355 | CM43: 1075.2195 | CN43: 1206.861 | CO43: 1453.3575 | CP43: 1747.563 | CQ43: 1168.8705 | CR43: 1212.162 | CS43: 1314.648 | CT43: 1684.8345 | CU43: 2373.9645 | CV43: 16765.296 | CX43: 1335.48 | CY43: 1032.3 | CZ43: 1160.0355 | DA43: 1075.2195 | DB43: 1206.861 | DC43: 1453.3575 | DD43: 1747.563 | DE43: 1168.8705 | DF43: 1212.162 | DG43: 1314.648 | DH43: 1684.8345 | DI43: 2373.9645 | DJ43: 16765.296
A44: 11 | B44: Loja Iguatemi Intimate | P44: =SUM(D44:O44) -> 0 | R44: 0 | S44: 0 | T44: 0 | U44: 0 | V44: 4000 | W44: 100 | X44: 800 | Y44: 800 | Z44: 1200 | AA44: 1200 | AB44: 1800 | AC44: 2300 | AD44: =SUM(R44:AC44) -> 12200 | AF44: 1500 | AG44: 1000 | AH44: =1500*0.15 -> 225 | AI44: 324 | AJ44: 869 | AK44: 800 | AL44: 1500 | AM44: 1000 | AN44: 1000 | AO44: 1000 | AP44: 1100 | AQ44: 1600 | AR44: =SUM(AF44:AQ44) -> 11918 | AT44: 1191 | AU44: 1191 | AV44: 1191 | AW44: 1191 | AX44: 876 | AY44: 876 | AZ44: 836 | BA44: 836 | BB44: 876 | BC44: 1035 | BD44: 0 | BE44: 0 | BF44: =SUM(AT44:BE44) -> 10099 | BG44: =BF44/AR44-1 -> -0.15262628 | BT44: 7342 | BV44: 1643.31 | BW44: 1270.38 | BX44: ='META EM PEÇAS'!U40-('META EM PEÇAS'!U40*0.05) -> 1427.736 | BY44: ='META EM PEÇAS'!V40-('META EM PEÇAS'!V40*0.05) -> 1323.483 | BZ44: ='META EM PEÇAS'!W40-('META EM PEÇAS'!W40*0.05) -> 1485.1635 | CA44: ='META EM PEÇAS'!X40-('META EM PEÇAS'!X40*0.05) -> 1788.204 | CB44: ='META EM PEÇAS'!Y40-('META EM PEÇAS'!Y40*0.05) -> 2151.3225 | CC44: ='META EM PEÇAS'!Z40-('META EM PEÇAS'!Z40*0.05) -> 1438.338 | CD44: ='META EM PEÇAS'!AA40-('META EM PEÇAS'!AA40*0.05) -> 1491.348 | CE44: ='META EM PEÇAS'!AB40-('META EM PEÇAS'!AB40*0.05) -> 1618.572 | ... CG44: ='META EM PEÇAS'!AD40-('META EM PEÇAS'!AD40*0.05) -> 2921.7345 | CH44: =SUM(BV44:CG44) -> 20633.166 | CJ44: 1643.31 | CK44: 1270.38 | CL44: 1427.736 | CM44: 1323.483 | CN44: 1485.1635 | CO44: 1788.204 | CP44: 2151.3225 | CQ44: 1438.338 | CR44: 1491.348 | CS44: 1618.572 | CT44: 2073.5745 | CU44: 2921.7345 | CV44: 20633.166 | CX44: 1643.31 | CY44: 1270.38 | CZ44: 1427.736 | DA44: 1323.483 | DB44: 1485.1635 | DC44: 1788.204 | DD44: 2151.3225 | DE44: 1438.338 | DF44: 1491.348 | DG44: 1618.572 | DH44: 2073.5745 | DI44: 2921.7345 | DJ44: 20633.166
A45: 12 | B45: Loja Salvador Shopping | P45: =SUM(D45:O45) -> 0 | R45: 0 | S45: 0 | T45: 0 | U45: 0 | V45: 4000 | W45: 0 | X45: 800 | Y45: 1000 | Z45: 1200 | AA45: 1200 | AB45: 1800 | AC45: 2300 | AD45: =SUM(R45:AC45) -> 12300 | AF45: 1500 | AG45: 1200 | AH45: =1500*0.15 -> 225 | AI45: 332 | AJ45: 945 | AK45: 960 | AL45: 1500 | AM45: 1200 | AN45: 1200 | AO45: 1200 | AP45: 1320 | AQ45: 1920 | AR45: =SUM(AF45:AQ45) -> 13502 | AT45: 1254 | AU45: 1254 | AV45: 1254 | AW45: 1254 | AX45: 1236 | AY45: 1236 | AZ45: 0 | BA45: 0 | BB45: 0 | BC45: 0 | BD45: 0 | BE45: 0 | BF45: =SUM(AT45:BE45) -> 7488 | BG45: =BF45/AR45-1 -> -0.44541549 | BT45: 16899 | BV45: 2552.85 | BW45: 1973.46 | BX45: ='META EM PEÇAS'!U34-('META EM PEÇAS'!U34*0.05) -> 2218.4685 | BY45: ='META EM PEÇAS'!V34-('META EM PEÇAS'!V34*0.05) -> 2056.788 | BZ45: ='META EM PEÇAS'!W34-('META EM PEÇAS'!W34*0.05) -> 2307.702 | CA45: ='META EM PEÇAS'!X34-('META EM PEÇAS'!X34*0.05) -> 2778.6075 | CB45: ='META EM PEÇAS'!Y34-('META EM PEÇAS'!Y34*0.05) -> 3342.2805 | CC45: ='META EM PEÇAS'!Z34-('META EM PEÇAS'!Z34*0.05) -> 2234.3715 | CD45: ='META EM PEÇAS'!AA34-('META EM PEÇAS'!AA34*0.05) -> 2317.4205 | CE45: ='META EM PEÇAS'!AB34-('META EM PEÇAS'!AB34*0.05) -> 2514.441 | ... CG45: ='META EM PEÇAS'!AD34-('META EM PEÇAS'!AD34*0.05) -> 4539.423 | CH45: =SUM(BV45:CG45) -> 32057.053 | CJ45: 2552.85 | CK45: 1973.46 | CL45: 2218.4685 | CM45: 2056.788 | CN45: 2307.702 | CO45: 2778.6075 | CP45: 3342.2805 | CQ45: 2234.3715 | CR45: 2317.4205 | CS45: 2514.441 | CT45: 3221.241 | CU45: 4539.423 | CV45: 32057.053 | CX45: 2552.85 | CY45: 1973.46 | CZ45: 2218.4685 | DA45: 2056.788 | DB45: 2307.702 | DC45: 2778.6075 | DD45: 3342.2805 | DE45: 2234.3715 | DF45: 2317.4205 | DG45: 2514.441 | DH45: 3221.241 | DI45: 4539.423 | DJ45: 32057.053
A46: 13 | B46: Loja Shopping Morumbi | P46: =SUM(D46:O46) -> 0 | R46: 0 | S46: 0 | T46: 0 | U46: 0 | V46: 0 | W46: 0 | X46: 2000 | Y46: 800 | Z46: 800 | AA46: 1200 | AB46: 1800 | AC46: 2300 | AD46: =SUM(R46:AC46) -> 8900 | AF46: 1800 | AG46: 1200 | AH46: =1800*0.15 -> 270 | AI46: 896 | AJ46: 1339 | AK46: 1600 | AL46: 1800 | AM46: 2000 | AN46: 2000 | AO46: 2000 | AP46: 2200 | AQ46: 3200 | AR46: =SUM(AF46:AQ46) -> 20305 | AT46: 1980 | AU46: 1980 | AV46: 1980 | AW46: 1980 | AX46: 1409 | AY46: 1409 | AZ46: 1345 | BA46: 1345 | BB46: 1409 | BC46: 1665 | BD46: 1793 | BE46: 2562 | BF46: =SUM(AT46:BE46) -> 20857 | BG46: =BF46/AR46-1 -> 0.027185422 | BT46: 11555 | BV46: 1903.71 | BW46: 1471.26 | BX46: ='META EM PEÇAS'!U35-('META EM PEÇAS'!U35*0.05) -> 1654.7955 | BY46: ='META EM PEÇAS'!V35-('META EM PEÇAS'!V35*0.05) -> 1533.756 | BZ46: ='META EM PEÇAS'!W35-('META EM PEÇAS'!W35*0.05) -> 1721.058 | CA46: ='META EM PEÇAS'!X35-('META EM PEÇAS'!X35*0.05) -> 2071.8075 | CB46: ='META EM PEÇAS'!Y35-('META EM PEÇAS'!Y35*0.05) -> 2492.3535 | CC46: ='META EM PEÇAS'!Z35-('META EM PEÇAS'!Z35*0.05) -> 1666.281 | CD46: ='META EM PEÇAS'!AA35-('META EM PEÇAS'!AA35*0.05) -> 1728.126 | CE46: ='META EM PEÇAS'!AB35-('META EM PEÇAS'!AB35*0.05) -> 1874.787 | ... CG46: ='META EM PEÇAS'!AD35-('META EM PEÇAS'!AD35*0.05) -> 3384.6885 | CH46: =SUM(BV46:CG46) -> 23904.859 | CJ46: 1903.71 | CK46: 1471.26 | CL46: 1654.7955 | CM46: 1533.756 | CN46: 1721.058 | CO46: 2071.8075 | CP46: 2492.3535 | CQ46: 1666.281 | CR46: 1728.126 | CS46: 1874.787 | CT46: 2402.2365 | CU46: 3384.6885 | CV46: 23904.859 | CX46: 1903.71 | CY46: 1471.26 | CZ46: 1654.7955 | DA46: 1533.756 | DB46: 1721.058 | DC46: 2071.8075 | DD46: 2492.3535 | DE46: 1666.281 | DF46: 1728.126 | DG46: 1874.787 | DH46: 2402.2365 | DI46: 3384.6885 | DJ46: 23904.859
A47: 14 | B47: Loja Recife | R47: 0 | S47: 0 | T47: 0 | U47: 0 | V47: 0 | W47: 0 | X47: 0 | Y47: 2000 | Z47: 800 | AA47: 800 | AB47: 1200 | AC47: 1800 | AD47: =SUM(R47:AC47) -> 6600 | AF47: 1500 | AG47: 1200 | AH47: =1500*0.15 -> 225 | AI47: 374 | AJ47: 990 | AK47: 960 | AL47: 1800 | AM47: 1200 | AN47: 1200 | AO47: 1200 | AP47: 1320 | AQ47: 1920 | AR47: =SUM(AF47:AQ47) -> 13889 | AT47: 1518 | AU47: 1518 | AV47: 1518 | AW47: 1518 | AX47: 1276 | AY47: 1276 | AZ47: 1218 | BA47: 1218 | BB47: 1276 | BC47: 1508 | BD47: 1624 | BE47: 2320 | BF47: =SUM(AT47:BE47) -> 17788 | BG47: =BF47/AR47-1 -> 0.28072575 | BT47: 19018 | BV47: 2737.92 | BW47: 2116.68 | BX47: ='META EM PEÇAS'!U36-('META EM PEÇAS'!U36*0.05) -> 2379.2655 | BY47: ='META EM PEÇAS'!V36-('META EM PEÇAS'!V36*0.05) -> 2205.216 | BZ47: ='META EM PEÇAS'!W36-('META EM PEÇAS'!W36*0.05) -> 2474.6835 | CA47: ='META EM PEÇAS'!X36-('META EM PEÇAS'!X36*0.05) -> 2980.0455 | CB47: ='META EM PEÇAS'!Y36-('META EM PEÇAS'!Y36*0.05) -> 3584.3595 | CC47: ='META EM PEÇAS'!Z36-('META EM PEÇAS'!Z36*0.05) -> 2396.052 | CD47: ='META EM PEÇAS'!AA36-('META EM PEÇAS'!AA36*0.05) -> 2485.2855 | CE47: ='META EM PEÇAS'!AB36-('META EM PEÇAS'!AB36*0.05) -> 2696.442 | ... CG47: ='META EM PEÇAS'!AD36-('META EM PEÇAS'!AD36*0.05) -> 4868.085 | CH47: =SUM(BV47:CG47) -> 34378.519 | CJ47: 2737.92 | CK47: 2116.68 | CL47: 2379.2655 | CM47: 2205.216 | CN47: 2474.6835 | CO47: 2980.0455 | CP47: 3584.3595 | CQ47: 2396.052 | CR47: 2485.2855 | CS47: 2696.442 | CT47: 3454.485 | CU47: 4868.085 | CV47: 34378.519 | CX47: 2737.92 | CY47: 2116.68 | CZ47: 2379.2655 | DA47: 2205.216 | DB47: 2474.6835 | DC47: 2980.0455 | DD47: 3584.3595 | DE47: 2396.052 | DF47: 2485.2855 | DG47: 2696.442 | DH47: 3454.485 | DI47: 4868.085 | DJ47: 34378.519
A48: 15 | B48: Porto Alegre - RS | R48: 0 | S48: 0 | T48: 0 | U48: 0 | V48: 0 | W48: 0 | X48: 0 | Y48: 0 | Z48: 2000 | AA48: 800 | AB48: 800 | AC48: 1500 | AD48: =SUM(R48:AC48) -> 5100 | AF48: 1800 | AG48: 1200 | AH48: =1800*0.4 -> 720 | AI48: 1147 | AJ48: 1155 | AK48: 1600 | AL48: 1800 | AM48: 2000 | AN48: 2000 | AO48: 2000 | AP48: 2200 | AQ48: 3200 | AR48: =SUM(AF48:AQ48) -> 20822 | AT48: 1544 | AU48: 1544 | AV48: 1544 | AW48: 1544 | AX48: 862 | AY48: 862 | AZ48: 823 | BA48: 823 | BB48: 862 | BC48: 1019 | BD48: 1098 | BE48: 1568 | BF48: =SUM(AT48:BE48) -> 14093 | BG48: =BF48/AR48-1 -> -0.3231678 | BT48: 21133 | BV48: 3593.52 | BW48: 2776.98 | BX48: ='META EM PEÇAS'!U38-('META EM PEÇAS'!U38*0.05) -> 3122.289 | BY48: ='META EM PEÇAS'!V38-('META EM PEÇAS'!V38*0.05) -> 2893.4625 | BZ48: ='META EM PEÇAS'!W38-('META EM PEÇAS'!W38*0.05) -> 3247.746 | CA48: ='META EM PEÇAS'!X38-('META EM PEÇAS'!X38*0.05) -> 3910.371 | CB48: ='META EM PEÇAS'!Y38-('META EM PEÇAS'!Y38*0.05) -> 4703.754 | CC48: ='META EM PEÇAS'!Z38-('META EM PEÇAS'!Z38*0.05) -> 3144.3765 | CD48: ='META EM PEÇAS'!AA38-('META EM PEÇAS'!AA38*0.05) -> 3260.9985 | CE48: ='META EM PEÇAS'!AB38-('META EM PEÇAS'!AB38*0.05) -> 3539.301 | ... CG48: ='META EM PEÇAS'!AD38-('META EM PEÇAS'!AD38*0.05) -> 6387.705 | CH48: =SUM(BV48:CG48) -> 45113.742 | CJ48: 3593.52 | CK48: 2776.98 | CL48: 3122.289 | CM48: 2893.4625 | CN48: 3247.746 | CO48: 3910.371 | CP48: 4703.754 | CQ48: 3144.3765 | CR48: 3260.9985 | CS48: 3539.301 | CT48: 4533.2385 | CU48: 6387.705 | CV48: 45113.742 | CX48: 3593.52 | CY48: 2776.98 | CZ48: 3122.289 | DA48: 2893.4625 | DB48: 3247.746 | DC48: 3910.371 | DD48: 4703.754 | DE48: 3144.3765 | DF48: 3260.9985 | DG48: 3539.301 | DH48: 4533.2385 | DI48: 6387.705 | DJ48: 45113.742
A49: 16 | B49: E-Commerce | AA49: 800 | AB49: 800 | AC49: 1500 | AF49: 1500 | AG49: 1200 | AH49: =1500*0.15 -> 225 | AI49: 192 | AJ49: 663 | AK49: 800 | AL49: 1500 | AM49: 1000 | AN49: 1000 | AO49: 1000 | AP49: 1100 | AQ49: 1600 | AR49: =SUM(AF49:AQ49) -> 11780 | AT49: 960 | AU49: 960 | AV49: 960 | AW49: 960 | AX49: 1414 | AY49: 1414 | AZ49: 1350 | BA49: 1350 | BB49: 1414 | BC49: 1671 | BD49: 1800 | BE49: 2571 | BF49: =SUM(AT49:BE49) -> 16824 | BG49: =BF49/AR49-1 -> 0.42818336 | BH49: 900 | BI49: 643 | BJ49: 891 | BK49: 679 | BL49: 940 | BM49: 948 | BN49: 1124 | BO49: 913 | BP49: 911 | BQ49: 898 | BR49: 1465 | BS49: 1278 | BT49: =SUM(BH49:BS49) -> 11590 | BV49: ='META EM PEÇAS'!T47 -> 1749.7325 | BW49: ='META EM PEÇAS'!T48 -> 1701.1288 | BX49: ='META EM PEÇAS'!T49 -> 1846.9398 | BY49: ='META EM PEÇAS'!T50 -> 1701.1288 | BZ49: ='META EM PEÇAS'!T51 -> 1846.9398 | CA49: ='META EM PEÇAS'!T52 -> 1749.7325 | CB49: ='META EM PEÇAS'!T53 -> 2138.5619 | CC49: ='META EM PEÇAS'!T54 -> 1749.7325 | CD49: ='META EM PEÇAS'!T55 -> 1749.7325 | CE49: ='META EM PEÇAS'!T56 -> 1749.7325 | CF49: ='META EM PEÇAS'!T57 -> 2721.8061 | CG49: ='META EM PEÇAS'!T58 -> 1944.1472 | CH49: =SUM(BV49:CG49) -> 22649.315 | CJ49: 1749.7325 | CK49: 1701.1288 | CL49: 1846.9398 | CM49: 1701.1288 | CN49: 1846.9398 | CO49: 1749.7325 | CP49: 2138.5619 | CQ49: 1749.7325 | CR49: 1749.7325 | CS49: 1749.7325 | CT49: 2721.8061 | CU49: 1944.1472 | CV49: 22649.315 | CX49: 1749.7325 | CY49: 1701.1288 | CZ49: 1846.9398 | DA49: 1701.1288 | DB49: 1846.9398 | DC49: 1749.7325 | DD49: 2138.5619 | DE49: 1749.7325 | DF49: 1749.7325 | DG49: 1749.7325 | DH49: 2721.8061 | DI49: 1944.1472 | DJ49: 22649.315
AF50: 0 | AG50: 0 | AH50: 0 | AI50: 0 | AJ50: 0 | AK50: 400 | AL50: 500 | AM50: 500 | AN50: 600 | AO50: 600 | AP50: 660 | AQ50: 960 | AR50: =SUM(AF50:AQ50) -> 4220 | AT50: 960 | AU50: 960 | AV50: 960 | AW50: 960 | AX50: 580 | AY50: 580 | AZ50: 554 | BA50: 554 | BB50: 580 | BC50: 686 | BD50: 739 | BE50: 1055 | BF50: =SUM(AT50:BE50) -> 9168 | BG50: =BF50/AR50-1 -> 1.1725118
AF51: 0 | AG51: 0 | AH51: 0 | AI51: 0 | AJ51: 0 | AK51: 0 | AL51: 2500 | AM51: 2000 | AN51: 500 | AO51: 600 | AP51: 660 | AQ51: 960 | AR51: =SUM(AF51:AQ51) -> 7220 | AT51: 1518 | AU51: 1518 | AV51: 1518 | AW51: 1518 | AX51: 1943 | AY51: 1943 | AZ51: 1854 | BA51: 1854 | BB51: 1943 | BC51: 2296 | BD51: 2472 | BE51: 3532 | BF51: =SUM(AT51:BE51) -> 23909 | BG51: =BF51/AR51-1 -> 2.3114958
AF52: 0 | AG52: 0 | AH52: 0 | AI52: 0 | AJ52: 0 | AK52: 0 | AL52: 0 | AM52: 0 | AN52: 0 | AO52: 0 | AP52: 0 | AQ52: 0 | AR52: =SUM(AF52:AQ52) -> 0 | AT52: 0 | AU52: 0 | AV52: 0 | AW52: 0 | AX52: 800 | AY52: 800 | AZ52: 800 | BA52: 1050 | BB52: 1100 | BC52: 1300 | BD52: 1400 | BE52: 2000 | BF52: =SUM(AT52:BE52) -> 9250 | BG52: =BF52/AR52-1 -> #DIV/0!
BD53: 600 | BE53: 700 | BF53: =SUM(AT53:BE53) -> 1300 | CB53: 60 | CJ53: =(CJ55-CJ54)/CJ54 -> 0.03 | CK53: =(CK55-CK54)/CK54 -> 0.03 | CL53: =(CL55-CL54)/CL54 -> 0.03 | CM53: =(CM55-CM54)/CM54 -> 0.03 | CN53: =(CN55-CN54)/CN54 -> 0.03 | CO53: =(CO55-CO54)/CO54 -> 0.03 | CP53: =(CP55-CP54)/CP54 -> 0.03 | CQ53: =(CQ55-CQ54)/CQ54 -> 0.03 | ... CU53: =(CU55-CU54)/CU54 -> 0.03
B54: E-Commerce | P54: =SUM(D54:O54) -> 0 | R54: 350 | S54: 350 | T54: 450 | U54: 800 | V54: 531 | W54: 750 | X54: 650 | Y54: 750 | Z54: 900 | AA54: 1000 | AB54: 1200 | AC54: 1500 | AD54: =SUM(R54:AC54) -> 9231 | AF54: 1500 | AG54: 800 | AH54: 800 | AI54: 1820 | AJ54: 1630 | AK54: 1360 | AL54: 1000 | AM54: 1700 | AN54: 1700 | AO54: 1700 | AP54: 1870 | AQ54: 2720 | AR54: =SUM(AF54:AQ54) -> 18600 | AT54: 2053 | AU54: 2053 | AV54: 2053 | AW54: 2053 | AX54: 2807 | AY54: 2807 | AZ54: 2680 | BA54: 2680 | BB54: 2807 | BC54: 3318 | BD54: 5870 | BE54: 5104 | BF54: =SUM(AT54:BE54) -> 36285 | BG54: =BF54/AR54-1 -> 0.95080645 | BT54: =SUM(BH54:BS54) -> 0 | CJ54: =BV64 -> 38900 | CK54: =BW64 -> 31376 | CL54: =BX64 -> 29886 | CM54: =BY64 -> 30671 | CN54: =BZ64 -> 34553 | CO54: =CA64 -> 36515 | CP54: =CB64 -> 38915 | CQ54: =CC64 -> 34615 | ... CU54: =CG64 -> 60875
B55: Estimativa Lojas | D55: =SUM(D34:D54) -> 0 | E55: =SUM(E34:E54) -> 0 | F55: =SUM(F34:F54) -> 0 | G55: =SUM(G34:G54) -> 0 | H55: =SUM(H34:H54) -> 0 | I55: =SUM(I34:I54) -> 0 | J55: =SUM(J34:J54) -> 0 | K55: =SUM(K34:K54) -> 0 | ... O55: =SUM(O34:O54) -> 0 | P55: =SUM(D55:O55) -> 0 | R55: =SUM(R34:R54) -> 20557.544 | S55: =SUM(S34:S54) -> 20512.544 | T55: =SUM(T34:T54) -> 13699.772 | U55: =SUM(U34:U54) -> 912.5 | V55: =SUM(V34:V54) -> 16851 | W55: =SUM(W34:W54) -> 13700 | X55: =SUM(X34:X54) -> 26050 | Y55: =SUM(Y34:Y54) -> 27750 | ... AC55: =SUM(AC34:AC54) -> 45300 | AD55: =SUM(R55:AC55) -> 286033.36 | AF55: =SUM(AF34:AF54) -> 38500 | AG55: =SUM(AG34:AG54) -> 22400 | AH55: =SUM(AH34:AH54) -> 10671 | AI55: =SUM(AI34:AI54) -> 16097 | AJ55: =SUM(AJ34:AJ54) -> 30278 | AK55: =SUM(AK34:AK54) -> 28560 | AL55: =SUM(AL34:AL54) -> 41700 | AM55: =SUM(AM34:AM54) -> 38700 | ... AQ55: =SUM(AQ34:AQ54) -> 54440 | AR55: =SUM(AF55:AQ55) -> 396686 | AT55: =SUM(AT34:AT54) -> 36153 | AU55: =SUM(AU34:AU54) -> 35289 | AV55: =SUM(AV34:AV54) -> 35872 | AW55: =SUM(AW34:AW54) -> 38031 | AX55: =SUM(AX34:AX54) -> 33566 | AY55: =SUM(AY34:AY54) -> 33566 | AZ55: =SUM(AZ34:AZ54) -> 30896 | BA55: =SUM(BA34:BA54) -> 31146 | ... BE55: =SUM(BE34:BE54) -> 49263 | BF55: =SUM(AT55:BE55) -> 436319 | BG55: =BF55-AR55 -> 39633 | BH55: 36153 | BI55: 35289 | BJ55: 35872 | BK55: 38031 | BL55: 38570 | BM55: 39227 | BN55: 41128 | BO55: 38191 | BP55: 38191 | BQ55: 40225 | BR55: 43272 | BS55: 60327 | BT55: =SUM(BH55:BS55) -> 484476 | BV55: =SUM(BV34:BV51) -> 35797.912 | BW55: =SUM(BW34:BW51) -> 27268.539 | BX55: =SUM(BX34:BX51) -> 34357.669 | BY55: =SUM(BY34:BY51) -> 29626.958 | BZ55: =SUM(BZ34:BZ51) -> 34139.121 | CA55: =SUM(CA34:CA51) -> 39503.882 | CB55: =SUM(CB34:CB51) -> 45728.837 | CC55: =SUM(CC34:CC51) -> 32260.227 | ... CG55: =SUM(CG34:CG51) -> 57905.503 | CH55: =SUM(BV55:CG55) -> 451302.93 | CI55: =(CH55-BT64)/BT64 -> 0.051833719 | CJ55: =BV64*1.03 -> 40067 | CK55: =BW64*1.03 -> 32317.28 | CL55: =BX64*1.03 -> 30782.58 | CM55: =BY64*1.03 -> 31591.13 | CN55: =BZ64*1.03 -> 35589.59 | CO55: =CA64*1.03 -> 37610.45 | CP55: =CB64*1.03 -> 40082.45 | CQ55: =CC64*1.03 -> 35653.45 | ... CU55: =CG64*1.03 -> 62701.25 | CV55: =SUM(CJ55:CU55) -> 459766.25 | CW55: =(CV55-CH64)/CH64 -> 0.03 | CX55: 35797.912 | CY55: 27268.539 | CZ55: 34357.669 | DA55: 29626.958 | DB55: 34139.121 | DC55: 39503.882 | DD55: 45728.837 | DE55: 32260.227 | DF55: 33331.523 | DG55: 35213.881 | DH55: 46168.878 | DI55: 57905.503 | DJ55: 451302.93
B56: Estimativa lojas - Transferência - expectativa de 80% a menos que a venda | AY56: 15000 | AZ56: 15000 | BA56: =BA55*70% -> 21802.2 | BB56: =BB55*70% -> 22841 | BC56: 35000 | BD56: 35000 | BE56: 42000 | BF56: =SUM(AT56:BE56) -> 186643.2 | BH56: =BH55*0.8 -> 28922.4 | BI56: =BI55*0.8 -> 28231.2 | BJ56: =BJ55*0.8 -> 28697.6 | BK56: =BK55*0.8 -> 30424.8 | BL56: =BL55*0.8 -> 30856 | BM56: =BM55*0.8 -> 31381.6 | BN56: =BN55*0.85 -> 34958.8 | BO56: 29000 | BP56: 40223 | BQ56: 36735 | BR56: 36933 | BS56: 52283 | BT56: =SUM(BH56:BS56) -> 408646.4 | BV56: 32000 | BW56: 32000 | BX56: 37000 | BY56: 32000 | BZ56: 35000 | CA56: 35000 | CB56: 35000 | CC56: =CC55*1 -> 32260.227 | CD56: =CD55*1 -> 33331.523 | CE56: =CE55 -> 35213.881 | CF56: 40000 | CG56: 60000 | CJ56: 32000 | CK56: 30000 | CL56: 31500 | CM56: 32000 | CN56: 35000 | CO56: 35000 | CP56: 36000 | CQ56: 35000 | CR56: 35000 | CS56: 40000 | CT56: 51000 | CU56: 60000 | CV56: =SUM(CJ56:CU56) -> 452500 | CX56: 28638.33 | CY56: 21814.831 | CZ56: 27486.135 | DA56: 23701.567 | DB56: 27311.297 | DC56: 31603.106 | DD56: 36583.07 | DE56: 25808.182 | DF56: 26665.218 | DG56: 28171.105 | DH56: 36935.102 | DI56: 46324.402
A57: FATURAMENTO EXPEDIÇÃO META | AL57: =AL55/AVERAGE($AF$55:$AQ$55) -> 1.2614511 | AP57: =AP55/AVERAGE($AF$55:$AQ$55) -> 1.2293855 | AQ57: =AQ55/AVERAGE($AF$55:$AQ$55) -> 1.6468441 | AT57: 109190 | AU57: 153667 | AV57: 178778 | AW57: 151970 | AX57: 142416 | AY57: 177335 | AZ57: 152230 | BA57: 245527 | BB57: =5261504/27 -> 194870.52 | BC57: =5784000/27 -> 214222.22 | BD57: =3224000/27 -> 119407.41 | BE57: =909800/27 -> 33696.296 | BF57: =SUM(AT57:BE57) -> 1873309.4 | BH57: 156208 | BI57: 147340 | BJ57: 166759 | BK57: 152352 | BL57: 128446 | BM57: 126790 | BN57: 173761 | BO57: =144510.599073001+BO56 -> 173510.6 | BP57: =162574.422556972+BP56 -> 202797.42 | BQ57: =166187.186558517+BQ56 -> 202922.19 | BR57: =BQ31+BR27*0.6 -> 232502.36 | BS57: =BR27*0.4+BS27*0.5 -> 116391.04 | BT57: =SUM(BH57:BS57) -> 1979779.6 | BV57: =BV31+BV56 -> 162757.87 | BW57: =BW31+BW56 -> 157566.83 | BX57: =BX31+BX56 -> 197961.54 | BY57: =BY31+BY56 -> 160769.23 | BZ57: =BZ31+BZ56 -> 153232.39 | CA57: =CA31+CA56 -> 143192.13 | CB57: =CB31+CB56 -> 178736.21 | CC57: =CC31+CC56 -> 202914.1 | ... CF57: =CF31+CF56 -> 173115.84 | CG57: =BS57 -> 116391.04 | CJ57: =CJ31+CJ56 -> 184850.74 | CK57: =CK31+CK56 -> 171882.51 | CL57: =CL31+CL56 -> 191983.4 | CM57: =CM31+CM56 -> 165270.48 | CN57: =CN31+CN56 -> 157242.75 | CO57: =CO31+CO56 -> 123621.68 | CP57: =CP31+CP56 -> 231213.55 | CQ57: =CQ31+CQ56 -> 211318.73 | ... CU57: =CU31+CU56 -> 107560.73 | CV57: =SUM(CJ57:CU57) -> 2217192.6 | CX57: 98000 | CY57: 147381.66 | CZ57: 188447.67 | DA57: 152352 | DB57: 128446 | DC57: 126790 | DD57: 173761 | DE57: 173510.6 | DF57: 202797.42 | DG57: 202922.19 | DH57: 232502.36 | DI57: 116391.04
A58: FATURAMENTO REAL | AF58: 133791 | AG58: 166459 | AH58: 149450 | AI58: 151073 | AJ58: 192944 | AK58: 166139 | AL58: 151874 | AM58: 157771 | AN58: 200312 | AO58: 202691 | AP58: 207768 | AQ58: 113286 | AR58: =SUM(AF58:AK58) -> 959856 | AT58: 89680 | AU58: 128308 | AV58: 144871 | AW58: 161772 | AX58: 144516 | AY58: 103667 | AZ58: 141023 | BA58: 172093 | BB58: =166606+10000 -> 176606 | BC58: 181091 | BD58: 169802 | BE58: 120406 | BF58: =SUM(AT58:BE58) -> 1733835 | BG58: =BG55/AR55 -> 0.099910256 | BH58: 78906 | BI58: 119296 | BJ58: 165286 | BK58: 144532 | BL58: 157691 | BM58: 129096 | BN58: 125800 | BO58: 176354 | BP58: 173554 | BQ58: 185766 | BT58: =SUM(BH58:BS58) -> 1456281
B59: Desvio Faturamento Real -Previsto | AF59: =AF58-AF26 -> 133789.57 | AG59: =AG58-AG26 -> 166455.03 | AH59: =AH58-AH26 -> 149445.55 | AI59: =AI58-AI26 -> 151069.82 | AJ59: =AJ58-AJ26 -> 192941.24 | AK59: =AK58-AK26 -> 166135.77 | AL59: =AL58-AL26 -> 151871.64 | AM59: =AM58-AM26 -> 157768.86 | ... AQ59: =AQ58-AQ26 -> 113282.52 | AR59: =SUM(AF59:AQ59) -> 1993520.8 | AT59: =AT58-AT57 -> -19510 | AU59: =AU58-AU57 -> -25359 | AV59: =AV58-AV57 -> -33907 | AW59: =AW58-AW57 -> 9802 | AX59: =AX58-AX57 -> 2100 | AY59: =AY58-AY57 -> -73668 | AZ59: =AZ58-AZ57 -> -11207 | BA59: =BA58-BA57 -> -73434 | ... BE59: =BE58-BE57 -> 86709.704 | BF59: =SUM(AT59:BE59) -> -139474.44 | BH59: =BH58-BH57 -> -77302 | BI59: =BI58-BI57 -> -28044 | BJ59: =BJ58-BJ57 -> -1473 | BK59: =BK58-BK57 -> -7820 | BL59: =BL58-BL57 -> 29245 | BM59: =BM58-BM57 -> 2306 | BN59: =BN58-BN57 -> -47961 | BO59: =BO58-BO57 -> 2843.4009 | ... BQ59: =BQ58-BQ57 -> -17156.187 | BT59: =SUM(BH59:BS59) -> -174605.21
A60: 5 | B60: Pendente de Faturamento | O60: 0 | P60: =SUM(D60:O60) -> 0 | AD60: =SUM(R60:AC60) -> 0 | AF60: 0 | AG60: 0 | AH60: 0 | AI60: 0 | AJ60: 0 | AK60: 0 | AL60: 0 | AM60: 0 | AN60: 0 | AO60: 0 | AQ60: 8938 | AR60: =SUM(AF60:AQ60) -> 8938 | AT60: 106642 | AU60: 90699 | AV60: 89681 | AW60: 58790 | AX60: 35520 | AY60: 61551 | AZ60: 71511 | BA60: 63617 | BB60: 66748 | BC60: 75532 | BD60: 37786 | BE60: 4503 | BF60: =SUM(AT60:BE60) -> 762580 | BH60: 69404 | BI60: 80412 | BJ60: 94386 | BK60: 78313 | BL60: 47034 | BM60: 50851 | BN60: 93202 | BO60: 100687 | BP60: 127995 | BQ60: 122686
A61: VENDA REAL | AF61: =AF62+AF64 -> 118364 | AG61: =AG62+AG64 -> 173742 | AH61: =AH62+AH64 -> 73470 | AI61: =AI62+AI64 -> 87377 | AJ61: =AJ62+AJ64 -> 119657 | AK61: =AK62+AK64 -> 154747 | AL61: =AL62+AL64 -> 138073 | AM61: =AM62+AM64 -> 180773 | ... AQ61: =AQ62+AQ64 -> 87384 | AR61: =SUM(AF61:AQ61) -> 1678462 | AT61: =AT62+AT64 -> 155346 | AU61: =AU62+AU64 -> 123370 | AV61: =AV62+AV64 -> 144065 | AW61: =AW62+AW64 -> 127865 | AX61: =AX62+AX64 -> 123461 | AY61: =AY62+AY64 -> 121196 | AZ61: =AZ62+AZ64 -> 168029 | BA61: =BA62+BA64 -> 164268 | ... BE61: =BE62+BE64 -> 90194 | BF61: =SUM(AT61:BE61) -> 1685749 | BG61: =BF61/AR61-1 -> 0.0043414745 | BH61: =BH62+BH64 -> 144332 | BI61: =BI62+BI64 -> 128781 | BJ61: =BJ62+BJ64 -> 193129 | BK61: =BK62+BK64 -> 106092 | BL61: =BL62+BL64 -> 132638 | BM61: =BM62+BM64 -> 139193 | BN61: =BN62+BN64 -> 173703 | BO61: =BO62+BO64 -> 186902 | ... BQ61: =BQ62+BQ64 -> 191324 | BT61: =SUM(BH61:BS61) -> 1596780 | CJ61: =CJ62+CJ64 -> 204853
B62: Varejo | AF62: 92193 | AG62: 152006 | AH62: 62734 | AI62: 71526 | AJ62: 89409 | AK62: 120675 | AL62: 100592 | AM62: 148128 | AN62: 164346 | AO62: 203437 | AP62: 64957 | AQ62: 31837 | AR62: =SUM(AF62:AQ62) -> 1301840 | AT62: 125048 | AU62: 96006 | AV62: 111470 | AW62: 99222 | AX62: 91253 | AY62: 90595 | AZ62: 129147 | BA62: 133525 | BB62: 159291 | BC62: 115573 | BD62: 98386 | BE62: 36527 | BF62: =SUM(AT62:BE62) -> 1286043 | BG62: =BF62/AR62-1 -> -0.012134364 | BH62: 110235 | BI62: 103047 | BJ62: 158855 | BK62: 77254 | BL62: 99853 | BM62: 100723 | BN62: 125338 | BO62: 153622 | BP62: 166483 | BQ62: 156140 | BR62: 111391 | BS62: 26768 | BT62: =SUM(BH62:BS62) -> 1389709 | BV62: 128446 | BW62: 119229 | BX62: 134860 | BY62: 111992 | BZ62: 102725 | CA62: 74472 | CB62: 164045 | CC62: 148167 | CD62: 189715 | CE62: 165488 | CF62: 103829 | CG62: 39967 | CH62: =SUM(BV62:CG62) -> 1482935 | CJ62: 167136 | CX62: 54245
B63: VENDA EM LINHA relizada fabrica | AF63: =AF62-AF31 -> 2047 | AG63: =AG62-AG31 -> -3571 | AH63: =AH62-AH31 -> -219 | AI63: =AI62-AI31 -> -1735 | AJ63: =AJ62-AJ31 -> -2447 | AK63: =AK62-AK31 -> 675 | AL63: =AL62-AL31 -> -9703 | AM63: =AM62-AM31 -> -52075 | ... AQ63: =AQ62-AQ31 -> -11563 | AR63: =SUM(AF63:AQ63) -> -176184.33 | AT63: =AT62-AT31 -> 8451.75 | AU63: =AU62-AU31 -> -37227.103 | AV63: =AV62-AV31 -> -6779.1379 | AW63: =AW62-AW31 -> -22342.138 | AX63: =AX62-AX31 -> 4719.0345 | AY63: =AY62-AY31 -> -14182.778 | AZ63: =AZ62-AZ31 -> -6630.7778 | BA63: =BA62-BA31 -> -77771.296 | ... BE63: =BE62-BE31 -> 5840.387 | BF63: =SUM(AT63:BE63) -> -291466.72 | BH63: =BH62-BH28 -> -6365 | BI63: =BI62-BI28 -> -8486.3333 | BJ63: =BJ62-BJ28 -> 23180.926 | BK63: =BK62-BK28 -> -44486.741 | BL63: =BL62-BL28 -> 5926.1481 | BM63: =BM62-BM28 -> 10043.741 | BN63: =BN62-BN28 -> -4917.5556 | BO63: =BO62-BO28 -> 3071.6219 | ... BQ63: =BQ62-BQ28 -> 29010 | BT63: =SUM(BH63:BS63) -> 11629.058 | BV63: 124435 | BW63: 117564 | BX63: 133262 | BY63: 110312 | BZ63: 101441 | CA63: 67535 | CB63: 155594 | CH63: =SUM(BV63:CG63) -> 810143 | CJ63: 159683 | CK63: 182683 | CL63: 137562
B64: Loja | AF64: 26171 | AG64: 21736 | AH64: 10736 | AI64: 15851 | AJ64: 30248 | AK64: 34072 | AL64: 37481 | AM64: 32645 | AN64: 30252 | AO64: 39494 | AP64: 42389 | AQ64: 55547 | AR64: =SUM(AF64:AQ64) -> 376622 | AT64: 30298 | AU64: 27364 | AV64: 32595 | AW64: 28643 | AX64: 32208 | AY64: 30601 | AZ64: 38882 | BA64: 30743 | BB64: =24621+1200 -> 25821 | BC64: 31662 | BD64: 37222 | BE64: 53667 | BF64: =SUM(AT64:BE64) -> 399706 | BG64: =BF64/AR64-1 -> 0.061292224 | BH64: 34097 | BI64: 25734 | BJ64: 34274 | BK64: 28838 | BL64: 32785 | BM64: 38470 | BN64: 48365 | BO64: 33280 | BP64: 34203 | BQ64: 35184 | BR64: 34873 | BS64: 48960 | BT64: =SUM(BH64:BS64) -> 429063 | BV64: 38900 | BW64: 31376 | BX64: 29886 | BY64: 30671 | BZ64: 34553 | CA64: 36515 | CB64: 38915 | CC64: 34615 | CD64: 29617 | CE64: 34538 | CF64: 45914 | CG64: 60875 | CH64: =SUM(BV64:CG64) -> 446375 | CJ64: 37717 | CX64: 22115
B65: META DE VENDA LOJA EM LINHA | AF65: =AF64-AF55 -> -12329 | AG65: =AG64-AG55 -> -664 | AH65: =AH64-AH55 -> 65 | AI65: =AI64-AI55 -> -246 | AJ65: =AJ64-AJ55 -> -30 | AK65: =AK64-AK55 -> 5512 | AL65: =AL64-AL55 -> -4219 | AM65: =AM64-AM55 -> -6055 | ... AQ65: =AQ64-AQ55 -> 1107 | AR65: =SUM(AF65:AQ65) -> -20064 | AT65: =AT64-AT55 -> -5855 | AU65: =AU64-AU55 -> -7925 | AV65: =AV64-AV55 -> -3277 | AW65: =AW64-AW55 -> -9388 | AX65: =AX64-AX55 -> -1358 | AY65: =AY64-AY55 -> -2965 | AZ65: =AZ64-AZ55 -> 7986 | BA65: =BA64-BA55 -> -403 | ... BE65: =BE64-BE55 -> 4404 | BF65: =SUM(AT65:BE65) -> -36613 | BH65: =BH64-BH55 -> -2056 | BI65: =BI64-BI55 -> -9555 | BJ65: =BJ64-BJ55 -> -1598 | BK65: =BK64-BK55 -> -9193 | BL65: =BL64-BL55 -> -5785 | BM65: =BM64-BM55 -> -757 | BN65: =BN64-BN55 -> 7237 | BO65: =BO64-BO55 -> -4911 | ... BQ65: =BQ64-BQ55 -> -5041 | BT65: =SUM(BH65:BS65) -> -35647 | BV65: 27740 | BW65: 23272 | BX65: 24576 | BY65: 26006 | BZ65: 30640 | CA65: 30640 | CB65: 29618 | CC65: 29686 | CD65: 29993 | CE65: 31540 | CF65: 38086 | CG65: 54003 | CH65: =SUM(BV65:CG65) -> 375800 | CJ65: =BV65*1.03 -> 28572.2 | CK65: =BW65*1.03 -> 23970.16 | CL65: =BX65*1.03 -> 25313.28 | CM65: =BY65*1.03 -> 26786.18 | CN65: =BZ65*1.03 -> 31559.2 | CO65: =CA65*1.03 -> 31559.2 | CP65: =CB65*1.03 -> 30506.54 | CQ65: =CC65*1.03 -> 30576.58 | ... CU65: =CG65*1.03 -> 55623.09 | CV65: =SUM(CJ65:CU65) -> 387074
A66: Desvio Venda Real-Previsto | B66: VENDA REALIZADA LOJA EM LINHA | AF66: =AF61-AF27 -> -10282 | AG66: =AG61-AG27 -> -4235 | AH66: =AH61-AH27 -> -154 | AI66: =AI61-AI27 -> -1981 | AJ66: =AJ61-AJ27 -> -2477 | AK66: =AK61-AK27 -> 6187 | AL66: =AL61-AL27 -> -13922 | AM66: =AM61-AM27 -> -58130 | ... AQ66: =AQ61-AQ27 -> -10456 | AR66: =SUM(AF66:AQ66) -> -196248.33 | AT66: =AT61-AT27 -> 2596.75 | AU66: =AU61-AU27 -> -45152.103 | AV66: =AV61-AV27 -> -10056.138 | AW66: =AW61-AW27 -> -31730.138 | AX66: =AX61-AX27 -> 3361.0345 | AY66: =AY61-AY27 -> -17147.778 | AZ66: =AZ61-AZ27 -> 1355.2222 | BA66: =BA61-BA27 -> -78174.296 | ... BE66: =BE61-BE27 -> 17507.387 | BF66: =SUM(AT66:BE66) -> -320816.72 | BH66: =BH61-BH27 -> -8421 | BI66: =BI61-BI27 -> -18041.333 | BJ66: =BJ61-BJ27 -> 21582.926 | BK66: =BK61-BK27 -> -53679.741 | BL66: =BL61-BL27 -> 141.14815 | BM66: =BM61-BM27 -> 9286.7407 | BN66: =BN61-BN27 -> 2319.4444 | BO66: =BO61-BO27 -> 7351.6219 | ... BQ66: =BQ61-BQ27 -> 27459 | BT66: =SUM(BH66:BS66) -> -13368.942 | CB66: =CB65+CB62 -> 193663 | CC66: =CC65+CC62 -> 177853 | CD66: =CD65+CD62 -> 219708 | CE66: =CE65+CE62 -> 197028 | CF66: =CF65+CF62 -> 141915 | CG66: =CG65+CG62 -> 93970 | CJ66: 27785 | CK66: 23447 | CL66: 26944
A67: Desvio Venda Real-Previsto % | AF67: =AF62-AF28 -> 92193 | AG67: =AG62-AG28 -> 152006 | AH67: =AH62-AH28 -> 62734 | AI67: =AI62-AI28 -> 71526 | AJ67: =AJ62-AJ28 -> 89409 | AK67: =AK62-AK28 -> 120675 | AL67: =AL62-AL28 -> 100592 | AM67: =AM62-AM28 -> 148128 | ... AQ67: =AQ62-AQ28 -> 31837 | AR67: =SUM(AF67:AQ67) -> 1301840 | AT67: =AT66/AT27 -> 0.017000083 | AU67: =AU66/AU27 -> -0.26792986 | AV67: =AV66/AV27 -> -0.065248272 | AW67: =AW66/AW27 -> -0.19881644 | AX67: =AX66/AX27 -> 0.027985308 | AY67: =AY66/AY27 -> -0.12395048 | AZ67: =AZ66/AZ27 -> 0.0081309864 | BA67: =BA66/BA27 -> -0.32244496 | ... BE67: =BE66/BE27 -> 0.24086123 | BF67: =AVERAGE(AT67:BE67) -> -0.11124824 | BH67: =BH66/BH27 -> -0.055128214 | BI67: =BI66/BI27 -> -0.12287867 | BJ67: =BJ66/BJ27 -> 0.12581416 | BK67: =BK66/BK27 -> -0.33597769 | BL67: =BL66/BL27 -> 0.0010652944 | BM67: =BM66/BM27 -> 0.071488016 | BN67: =BN66/BN27 -> 0.013533646 | BO67: =BO66/BO27 -> 0.040944619 | ... BQ67: =BQ66/BQ27 -> 0.16757087 | BT67: =BT66/BT27 -> -0.0071185037
A68: A Produzir no Mês corrente
B69: venda realizada em linha | BV69: 152642 | BW69: 141495 | BX69: 158268 | BY69: 135742 | BZ69: 130614 | CA69: 97296 | CB69: 180319 | CC69: 175137 | CD69: 216035 | CE69: 188049 | CF69: 139782 | CG69: 90604 | CH69: =SUM(BV69:CG69) -> 1805983 | CJ69: x | CK69: =BW69 -> 141495 | CL69: =BX69 -> 158268 | CM69: =BY69 -> 135742 | CN69: =BZ69 -> 130614 | CO69: =CA69 -> 97296 | CP69: =CB69 -> 180319 | CQ69: =CC69 -> 175137 | CR69: =CD69 -> 216035 | CS69: =CS70 -> 229416.92 | CT69: =CT70 -> 162785.09 | CU69: =CU70 -> 103183.82 | CV69: =CH69 -> 1805983
B70: venda prevista em linha | BV70: =BV27 -> 161157.87 | BW70: =BW27 -> 155966.83 | BX70: =BX27 -> 196111.54 | BY70: =BY27 -> 159169.23 | BZ70: =BZ27 -> 151482.39 | CA70: =CA27 -> 141442.13 | CB70: =CB27 -> 176986.21 | CC70: =CC27 -> 201301.09 | ... CG70: =CG27 -> 87483.817 | CH70: =SUM(BV70:CG70) -> 2030972.3 | CJ70: =CJ27 -> 181422.94 | CK70: =CK27 -> 165852.67 | CL70: =CL27 -> 185796.68 | CM70: =CM27 -> 160056.66 | CN70: =CN27 -> 153801.95 | CO70: =CO27 -> 120180.88 | CP70: =CP27 -> 225720.09 | CQ70: =CQ27 -> 206895.31 | ... CU70: =CU27 -> 103183.82 | CV70: =SUM(CJ70:CU70) -> 2151766.6 | CX70: =CX27 -> 190494.09 | CY70: =CY27 -> 174145.3 | CZ70: =CZ27 -> 195086.51 | DA70: =DA27 -> 168059.49 | DB70: =DB27 -> 161492.05 | DC70: =DC27 -> 126189.92 | DD70: =DD27 -> 237006.09 | DE70: =DE27 -> 217240.08 | ... DI70: =DI27 -> 108343.01 | DJ70: =SUM(CX70:DI70) -> 2259355
A71: 7 | B71: Total Produção Projetada | D71: 98048 | E71: 128688 | F71: 124704 | G71: 157500 | H71: 182600 | I71: 157700 | J71: 181700 | K71: 165900 | L71: 174300 | M71: 215800 | N71: 180000 | O71: 112500 | P71: =SUM(D71:O71) -> 1879440 | R71: 158400 | S71: 161000 | T71: 117800 | U71: 2000 | V71: 53800 | W71: 190600 | X71: 187900 | Y71: 196800 | Z71: 192300 | AA71: 182300 | AB71: 175000 | AC71: 134100 | AD71: =SUM(R71:AC71) -> 1752000 | AF71: =SUM(AF72,AF74) -> 161400 | AG71: =SUM(AG72,AG74) -> 166000 | AH71: =SUM(AH72,AH74) -> 150471 | AI71: =SUM(AI72,AI74) -> 149040 | AJ71: =SUM(AJ72,AJ74) -> 196360 | AK71: =SUM(AK72,AK74) -> 163300 | AL71: =SUM(AL72,AL74) -> 190000 | AM71: =SUM(AM72,AM74,AM75) -> 167000 | AN71: =SUM(AN72,AN74,AN75) -> 170500 | AO71: =SUM(AO72,AO74,AO75) -> 140000 | AP71: =SUM(AP72,AP74,AP75) -> 130000 | AQ71: =SUM(AQ72,AQ74,AQ75) -> 100000 | AR71: =SUM(AF71:AQ71) -> 1884071 | AT71: =SUM(AT72,AT74,AT75) -> 133000 | AU71: =SUM(AU72,AU74,AU75) -> 125180 | AV71: =SUM(AV72,AV74,AV75) -> 117228 | AW71: =SUM(AW72,AW74,AW75) -> 127500 | AX71: =SUM(AX72,AX74,AX75) -> 140000 | AY71: =SUM(AY72,AY74,AY75) -> 158343 | AZ71: =SUM(AZ72,AZ74,AZ75) -> 152409 | BA71: =SUM(BA72,BA74,BA75) -> 173520 | ... BC71: =SUM(BC72,BC74,BC75) -> 157500 | BD71: 129431 | BE71: 61700 | BF71: =SUM(AT71:BE71) -> 1640811 | BG71: =BF71-AR71 -> -243260 | BH71: =SUM(BH72,BH74,BH75) -> 139760 | BI71: =SUM(BI72,BI74,BI75) -> 116580 | BJ71: =SUM(BJ72,BJ74,BJ75) -> 148340 | BK71: =SUM(BK72,BK74,BK75) -> 112360 | BL71: =SUM(BL72,BL74,BL75) -> 108660 | BM71: =SUM(BM72,BM74,BM75) -> 153416 | BN71: =SUM(BN72,BN74,BN75) -> 137676 | BO71: =SUM(BO72,BO74,BO75) -> 160654 | BP71: =SUM(BP72,BP74,BP75) -> 157000 | BQ71: 156725 | BR71: 182069 | BS71: =BS72+BS75 -> 156420 | BT71: =SUM(BH71:BS71) -> 1729660 | BV71: =BV7*BV73 -> 133000 | BW71: =BW7*BW73 -> 133000 | BX71: =BX7*BX73 -> 147000 | BY71: =BY7*BY73 -> 172800 | BZ71: =BZ7*BZ73 -> 165600 | CA71: =CA7*CA73 -> 158400 | CB71: =CB7*CB73 -> 180000 | CC71: =CC7*CC73 -> 172800 | ... CG71: =CG7*CG73 -> 98800 | CH71: =SUM(BV71:CG71) -> 1874200 | CJ71: =CJ7*CJ73 -> 165000 | CK71: =CK7*CK73 -> 188600 | CL71: =CL7*CL73 -> 171000 | CM71: =CM7*CM73 -> 180000 | CN71: =CN7*CN73 -> 189000 | CO71: =CO7*CO73 -> 193500 | CP71: =CP7*CP73 -> 216000 | CQ71: =CQ7*CQ73 -> 207000 | ... CU71: =CU7*CU73 -> 119600 | CV71: =SUM(CJ71:CU71) -> 2218500 | CX71: =CX7*CX73 -> 184000 | CY71: =CY7*CY73 -> 138000 | CZ71: =CZ7*CZ73 -> 174800 | DA71: =DA7*DA73 -> 184000 | DB71: =DB7*DB73 -> 193200 | DC71: =DC7*DC73 -> 184000 | DD71: =DD7*DD73 -> 211600 | DE71: =DE7*DE73 -> 193200 | ... DI71: =DI7*DI73 -> 119600 | DJ71: =SUM(CX71:DI71) -> 2152800
B72: Meta Fábrica | D72: 98048 | E72: 128688 | F72: 124704 | G72: 157500 | H72: 182600 | I72: 157700 | J72: 181700 | K72: 165900 | L72: 174300 | M72: 215800 | N72: 180000 | O72: 112500 | P72: =SUM(D72:O72) -> 1879440 | R72: 158400 | S72: 146000 | T72: 102200 | U72: 0 | V72: 43800 | W72: 160600 | X72: 167900 | Y72: 153300 | Z72: 153300 | AA72: 153300 | AB72: 146000 | AC72: 124100 | AF72: 131400 | AG72: 146000 | AH72: 125511 | AI72: 135000 | AJ72: 177320 | AK72: 151300 | AL72: 176000 | AM72: =AM73*AM7 -> 154000 | AN72: =AN73*AN7 -> 157500 | AO72: =AO73*AO7 -> 140000 | AP72: =AP73*AP7 -> 130000 | AQ72: =AQ73*AQ7+16000 -> 100000 | AR72: =SUM(AF72:AQ72) -> 1724031 | AT72: =AT73*AT7 -> 133000 | AU72: =125180 -> 125180 | AV72: =AV73*AV7+7428 -> 117228 | AW72: =AW73*AW7 -> 123500 | AX72: =AX73*AX7 -> 132000 | AY72: =AY73*AY7 -> 153343 | AZ72: 142409 | BA72: 163520 | BB72: =BB73*BB7 -> 165000 | BC72: =BC73*BC7 -> 157500 | BD72: 129431 | BE72: 61700 | BF72: =SUM(AT72:BE72) -> 1603811 | BG72: =BF72+BF75-AR72-AR75 -> -113040 | BH72: 136760 | BI72: 116580 | BJ72: 148340 | BK72: 112360 | BL72: 108660 | BM72: 153416 | BN72: 137676 | BO72: 150654 | BP72: =7100*BP7 -> 142000 | BQ72: =BQ71-BQ75 -> 136725 | BR72: =BR71-BR75 -> 167069 | BS72: 124020 | BT72: =SUM(BH72:BS72) -> 1634260 | BV72: =BV73*BV74-24551 -> 108449 | BW72: =BW73*BW74 -> 133000 | BX72: =BX73*BX74 -> 147000 | BY72: =BY73*BY74 -> 172800 | BZ72: =BZ73*BZ74 -> 165600 | CA72: =CA73*CA74 -> 158400 | CB72: =CB73*CB74 -> 180000 | CC72: =CC73*CC74 -> 172800 | CD72: =CD73*CD74 -> 172800 | ... CG72: =CG73*CG74 -> 98800 | CH72: =SUM(BV72:CG72) -> 1849649 | CI72: =(CH72-BT78)/BT78 -> 0.29391869 | CJ72: =CJ71 -> 165000 | CK72: =CK71 -> 188600 | CL72: =CL71 -> 171000 | CM72: =CM71 -> 180000 | CN72: =CN71 -> 189000 | CO72: =CO71 -> 193500 | CP72: 168760 | CQ72: 194340 | CR72: 208000 | CS72: 201780 | CT72: 154060 | CU72: 96720 | CV72: 1949109 | CW72: =(CV72-CH78)/CH78 -> 0.11040222 | CX72: =CX71 -> 184000 | CY72: =CY71 -> 138000 | CZ72: =CZ71 -> 174800 | DA72: =DA71 -> 184000 | DB72: =DB71 -> 193200 | DC72: =DC71 -> 184000 | DD72: 168760 | DE72: 194340 | DF72: 208000 | DG72: 201780 | DH72: 154060 | DI72: 96720 | DJ72: 1949109
B73: Media Dia Fábrica | R73: =R72/R7 -> 7200 | S73: =S72/S7 -> 7300 | T73: =T72/T7 -> 7300 | U73: =U72/U7 -> 0 | V73: =V72/V7 -> 3650 | W73: =W72/W7 -> 7300 | X73: =X72/X7 -> 7300 | Y73: =Y72/Y7 -> 7300 | ... AC73: =AC72/AC7 -> 7300 | AF73: =AF72/AF7 -> 7300 | AG73: =AG72/AG7 -> 7300 | AH73: =AH72/AH7 -> 6275.55 | AI73: =AI72/AI7 -> 6750 | AJ73: =AJ72/AJ7 -> 8060 | AK73: =AK72/AK7 -> 7565 | AL73: =AL72/AL7 -> 8000 | AM73: 7000 | AN73: 7500 | AO73: 7000 | AP73: 6500 | AQ73: 7000 | AR73: =AVERAGE(AF73:AQ73) -> 7187.5458 | AT73: 7000 | AU73: =AU72/AU7 -> 6588.4211 | AV73: 6100 | AW73: 6500 | AX73: 6000 | AY73: 7302.0476 | AZ73: 7000 | BA73: =BA72/BA7 -> 7432.7273 | BB73: 7500 | BC73: 7500 | BD73: =BD72/BD7 -> 6471.55 | BE73: =BE72/BE7 -> 6170 | BF73: =AVERAGE(AT73:BE73) -> 6797.0622 | BH73: =BH72/BH7 -> 6838 | BI73: =BI72/BI7 -> 6857.6471 | BJ73: =BJ72/BJ7 -> 6449.5652 | BK73: =BK72/BK7 -> 6242.2222 | BL73: =BL72/BL7 -> 4939.0909 | BM73: =BM72/BM7 -> 6670.2609 | BN73: =BN72/BN7 -> 6556 | BO73: =BO72/BO7 -> 7174 | ... BS73: =BS72/BS7 -> 8858.5714 | BT73: =AVERAGE(BH73:BS73) -> 6879.1268 | BV73: 7000 | BW73: 7000 | BX73: 7000 | BY73: 7200 | BZ73: 7200 | CA73: 7200 | CB73: 7200 | CC73: =CB73 -> 7200 | CD73: 7200 | CE73: 7200 | CF73: 7600 | CG73: 7600 | CJ73: 7500 | CK73: 8200 | CL73: 9000 | CM73: 9000 | CN73: 9000 | CO73: 9000 | CP73: 9000 | CQ73: 9200 | CR73: =CQ73 -> 9200 | CS73: =CR73 -> 9200 | CT73: =CS73 -> 9200 | CU73: =CT73 -> 9200 | CX73: =CU73 -> 9200 | CY73: =CX73 -> 9200 | CZ73: =CY73 -> 9200 | DA73: =CZ73 -> 9200 | DB73: =DA73 -> 9200 | DC73: =DB73 -> 9200 | DD73: =DC73 -> 9200 | DE73: =DD73 -> 9200 | DF73: =DE73 -> 9200 | ... DI73: =DH73 -> 9200
B74: dias trabalhados | S74: 15000 | T74: 15600 | U74: 2000 | V74: 10000 | W74: 30000 | X74: 20000 | Y74: 30000 | Z74: 30000 | AA74: 20000 | AB74: 20000 | AC74: 10000 | AF74: 30000 | AG74: 20000 | AH74: 24960 | AI74: 14040 | AJ74: 19040 | AK74: 12000 | AL74: 14000 | AM74: 13000 | AN74: 13000 | AO74: 0 | AP74: 0 | AQ74: 0 | AR74: =SUM(AF74:AQ74) -> 160040 | AT74: 0 | AU74: 0 | BF74: =SUM(AT74:BE74) -> 0 | BG74: =BF74-AR74 -> -160040 | BT74: =SUM(BH74:BS74) -> 0 | BV74: =BV7 -> 19 | BW74: =BW7 -> 19 | BX74: =BX7 -> 21 | BY74: =BY7 -> 24 | BZ74: =BZ7 -> 23 | CA74: =CA7 -> 22 | CB74: =CB7 -> 25 | CC74: =CC7 -> 24 | ... CG74: =CG7 -> 13 | CH74: =SUM(BV74:CG74) -> 260 | CJ74: =CJ7 -> 22 | CK74: =CK7 -> 23 | CL74: =CL7 -> 19 | CM74: =CM7 -> 20 | CN74: =CN7 -> 21 | CO74: =CO7 -> 21.5 | CV74: 131 | CX74: =CX7 -> 20 | CY74: =CY7 -> 15 | CZ74: =CZ7 -> 19 | DA74: =DA7 -> 20 | DB74: =DB7 -> 21 | DC74: =DC7 -> 20 | DJ74: 131
B75: Total Produção 2024 | T75: 0 | U75: 0 | V75: 0 | W75: 0 | X75: 0 | Y75: 13500 | Z75: 9000 | AA75: 9000 | AB75: 9000 | AC75: 0 | AF75: 13500 | AG75: 13500 | AH75: 2820 | AI75: 0 | AJ75: 0 | AK75: 0 | AL75: 0 | AR75: =SUM(AF75:AQ75) -> 29820 | AW75: 4000 | AX75: 8000 | AY75: 5000 | AZ75: 10000 | BA75: 10000 | BB75: 0 | BC75: 0 | BD75: 0 | BF75: =SUM(AT75:BE75) -> 37000 | BH75: 3000 | BO75: 10000 | BP75: 15000 | BQ75: 20000 | BR75: 15000 | BS75: =7200*9/2 -> 32400 | BT75: =SUM(BH75:BS75) -> 95400 | BV75: =BV78-BV71 -> 21584 | BW75: =BW78-BW71 -> 18963 | BX75: =BX78-BX71 -> -2354 | BY75: =BY78-BY71 -> 5998 | BZ75: =BZ78-BZ71 -> -13737 | CA75: =CA78-CA71 -> -6090 | CB75: =CB78-CB71 -> -2176 | CC75: =CC78-CC71 -> -17344 | ... CG75: =CG78-CG71 -> -98800 | CH75: =SUM(CD75:CG75) -> -123726 | CJ75: =BV78 -> 154584 | CK75: =BW78 -> 151963 | CL75: =BX78 -> 144646 | CM75: =BY78 -> 178798 | CN75: =BZ78 -> 151863 | CO75: =CA78 -> 152310 | CV75: 127800 | CX75: =CJ78 -> 0 | CY75: =CK78 -> 0 | CZ75: =CL78 -> 175111 | DA75: =CM78 -> 0 | DB75: =CN78 -> 0 | DC75: =CO78 -> 0 | DJ75: 127800
B76: Minutos DIARO | AO76: =AO71*9.68 -> 1355200 | AP76: =AP71*9.68 -> 1258400 | AQ76: =AQ71*9.68 -> 968000 | AT76: =AT71*9.68 -> 1287440 | AU76: =AU71*9.68 -> 1211742.4 | AV76: =AV71*9.68 -> 1134767 | AW76: =AW71*9.68 -> 1234200 | AX76: =AX71*9.68 -> 1355200 | AY76: =AY71*9.68 -> 1532760.2 | AZ76: =AZ71*9.68 -> 1475319.1 | BA76: =BA71*9.68 -> 1679673.6 | ... BF76: =BF71*9.68 -> 15883050 | CF76: MOSTRUARIO | CM76: 61884.013 | CN76: =CM76 -> 61884.013 | CO76: =CN76 -> 61884.013 | CP76: =CO76 -> 61884.013 | CQ76: =CP76 -> 61884.013 | CR76: =CQ76 -> 61884.013 | CS76: =CR76 -> 61884.013 | CT76: =CS76 -> 61884.013 | CU76: =CT76 -> 61884.013
B77: MInutos Mensal | CM77: =CM76*CM7 -> 1237680.3 | CN77: =CN76*CN7 -> 1299564.3 | CO77: =CO76*CO7 -> 1330506.3 | CP77: =CP76*CP7 -> 1485216.3 | CQ77: =CQ76*CQ7 -> 1392390.3 | CR77: =CR76*CR7 -> 1330506.3 | CS77: =CS76*CS7 -> 1454274.3 | CT77: =CT76*CT7 -> 1175796.2 | CU77: =CU76*CU7 -> 804492.17
A78: PRODUÇÃO | B78: Realizada | D78: 95972 | E78: 130805 | F78: 121914 | G78: 165455 | H78: 192013 | I78: 167281 | J78: 181409 | K78: 163138 | L78: 169051 | M78: 183254 | P78: =SUM(D78:O78) -> 1570292 | R78: 149582 | S78: 152735 | T78: 107681 | U78: 2974 | V78: 32639 | W78: 153121 | X78: 198635 | Y78: 160489 | Z78: 160893 | AA78: 180999 | AB78: 167265 | AC78: 135424 | AD78: =SUM(R78:AC78) -> 1602437 | AF78: 145616 | AG78: 168450 | AH78: 153291 | AI78: 149378 | AJ78: 196360 | AK78: 170558 | AL78: 171758 | AM78: =SUM(AM79:AM80) -> 168974 | AN78: =SUM(AN79:AN80) -> 144792 | AO78: =SUM(AO79:AO80) -> 141375 | AP78: =SUM(AP79:AP80) -> 143221 | AQ78: =SUM(AQ79:AQ80) -> 85543 | AR78: =SUM(AF78:AQ78) -> 1839316 | AT78: =SUM(AT79:AT80) -> 120211 | AU78: =SUM(AU79:AU80) -> 120216 | AV78: =SUM(AV79:AV80) -> 101053 | AW78: =SUM(AW79:AW80) -> 137388 | AX78: =SUM(AX79:AX80) -> 137400 | AY78: =SUM(AY79:AY80) -> 135412 | AZ78: =SUM(AZ79:AZ80) -> 157032 | BA78: =SUM(BA79:BA80) -> 173287 | ... BE78: =SUM(BE79:BE80) -> 55950 | BF78: =SUM(AT78:BE78) -> 1596631 | BG78: =BF78/AR78-1 -> -0.13194307 | BH78: =SUM(BH79:BH80) -> 138562 | BI78: =SUM(BI79:BI80) -> 109391 | BJ78: =SUM(BJ79:BJ80) -> 160056 | BK78: =SUM(BK79:BK80) -> 124826 | BL78: =SUM(BL79:BL80) -> 151185 | BM78: =SUM(BM79:BM80) -> 134688 | BN78: =SUM(BN79:BN80) -> 157005 | BO78: =SUM(BO79:BO80) -> 151231 | ... BQ78: =SUM(BQ79:BQ80) -> 159215 | BT78: =SUM(BH78:BS78) -> 1429494 | BV78: 154584 | BW78: 151963 | BX78: 144646 | BY78: 178798 | BZ78: 151863 | CA78: 152310 | CB78: =CB79+CB80 -> 177824 | CC78: =CC79+CC80 -> 155456 | CD78: =CD79+CD80 -> 159431 | CE78: 173593 | CF78: 154850 | CG78: =CG79+CG80 -> 0 | CH78: =SUM(BV78:CG78) -> 1755318 | CL78: 175111
B79: Real Fábrica | AF79: 126362 | AG79: 153970 | AH79: 128331 | AI79: 135338 | AJ79: 177312 | AK79: 150818 | AL79: 158858 | AM79: 153933 | AN79: 134244 | AO79: 137435 | AP79: 143221 | AQ79: 85543 | AR79: =SUM(AF79:AQ79) -> 1685365 | AT79: 120211 | AU79: 120216 | AV79: 101053 | AW79: 137388 | AX79: 137400 | AY79: 135412 | AZ79: 157032 | BA79: 172227 | BB79: =157995+8500 -> 166495 | BC79: 153816 | BD79: 138051 | BE79: 55950 | BF79: =SUM(AT79:BE79) -> 1595251 | BH79: 138562 | BI79: 109391 | BJ79: 160056 | BK79: 124826 | BL79: 151185 | BM79: 134688 | BN79: 157005 | BO79: 151231 | BP79: 143335 | BQ79: 159215 | BT79: =SUM(BH79:BS79) -> 1429494 | BV79: 154584 | BW79: 151963 | BX79: 144646 | BY79: 178798 | BZ79: 151863 | CA79: 152310 | CB79: 177824 | CC79: 155456 | CD79: 159431
B80: Real Oficina | AF80: =AF78-AF79 -> 19254 | AG80: =AG78-AG79 -> 14480 | AH80: =AH78-AH79 -> 24960 | AI80: =AI78-AI79 -> 14040 | AJ80: =AJ78-AJ79 -> 19048 | AK80: =AK78-AK79 -> 19740 | AL80: =AL78-AL79 -> 12900 | AM80: 15041 | AN80: 10548 | AO80: 3940 | AP80: 0 | AQ80: 0 | AR80: =SUM(AF80:AQ80) -> 153951 | AT80: 0 | AU80: 0 | AV80: 0 | AW80: 0 | AX80: 0 | AY80: 0 | AZ80: 0 | BA80: 1060 | BB80: 320 | BC80: 0 | BD80: 0 | BF80: =SUM(AT80:BE80) -> 1380 | BT80: =SUM(BH80:BS80) -> 0
A81: Desvio Produção Real-Previsto | AF81: =AF78-AF71 -> -15784 | AG81: =AG78-AG71 -> 2450 | AH81: =AH78-AH71 -> 2820 | AI81: =AI78-AI71 -> 338 | AJ81: =AJ78-AJ71 -> 0 | AK81: =AK78-AK71 -> 7258 | AL81: =AL78-AL71 -> -18242 | AM81: =AM78-AM71 -> 1974 | ... AQ81: =AQ78-AQ71 -> -14457 | AR81: =SUM(AF81:AQ81) -> -44755 | AT81: =AT78-AT71 -> -12789 | AU81: =AU78-AU71 -> -4964 | AV81: =AV78-AV71 -> -16175 | AW81: =AW78-AW71 -> 9888 | AX81: =AX78-AX71 -> -2600 | AY81: =AY78-AY71 -> -22931 | AZ81: =AZ78-AZ71 -> 4623 | BA81: =BA78-BA71 -> -233 | ... BE81: =BE78-BE71 -> -5750 | BF81: =SUM(AT81:BE81) -> -44180 | BH81: =BH78-BH71 -> -1198 | BI81: =BI78-BI71 -> -7189 | BJ81: =BJ78-BJ71 -> 11716 | BK81: =BK78-BK71 -> 12466 | BL81: =BL78-BL71 -> 42525 | BM81: =BM78-BM71 -> -18728 | BN81: =BN78-BN71 -> 19329 | BO81: =BO78-BO71 -> -9423 | ... BQ81: =BQ78-BQ71 -> 2490 | BT81: =SUM(BH81:BS81) -> 38323 | BY81: =BY78-BY71 -> 5998 | BZ81: =BZ78-BZ71 -> -13737 | CA81: =CA78-CA71 -> -6090 | CB81: =CB78-CB71 -> -2176 | CC81: =CC78-CC71 -> -17344 | CD81: =CD78-CD71 -> -13369 | CE81: =CE78-CE71 -> 793 | CF81: =CF78-CF71 -> -12350 | ... CH81: =CH78-CH71 -> -118882 | CJ81: =CJ78-CJ71 -> -165000 | CK81: =CK78-CK71 -> -188600 | CL81: =CL78-CL71 -> 4111 | CM81: =CM78-CM71 -> -180000 | CN81: =CN78-CN71 -> -189000 | CO81: =CO78-CO71 -> -193500 | CP81: =CP78-CP71 -> -216000 | CQ81: =CQ78-CQ71 -> -207000 | ... CV81: =CV78-CV71 -> -2218500 | CX81: =CX78-CX71 -> -184000 | CY81: =CY78-CY71 -> -138000 | CZ81: =CZ78-CZ71 -> -174800 | DA81: =DA78-DA71 -> -184000 | DB81: =DB78-DB71 -> -193200 | DC81: =DC78-DC71 -> -184000 | DD81: =DD78-DD71 -> -211600 | DE81: =DE78-DE71 -> -193200 | ... DJ81: =DJ78-DJ71 -> -2152800
A82: Diferença Produção x Venda | D82: =#REF!-#REF! -> #REF! | E82: =#REF!-#REF! -> #REF! | F82: =#REF!-#REF! -> #REF! | G82: =G71-#REF! -> #REF! | H82: =H71-#REF! -> #REF! | I82: =I71-#REF! -> #REF! | J82: =#REF!-#REF! -> #REF! | K82: =#REF!-#REF! -> #REF! | L82: =L71-L27 -> -24911 | M82: =M71-M27 -> -13674 | N82: =N71-N27 -> 57632 | O82: =O71-O27 -> 74079 | P82: =SUM(D82:O82) -> #REF! | R82: =R71-R27 -> 22222.66 | S82: =S71-S27 -> 17159.674 | T82: =T71-T27 -> -24753.772 | U82: =U71-U27 -> -17814.9 | V82: =V71-V27 -> 1715 | W82: =W71-W27 -> 120430.62 | X82: =X71-X27 -> 43436.667 | Y82: =Y71-Y27 -> -29747.083 | ... AD82: =AD71-AD27 -> 333561.36 | AF82: =AF71-AF27 -> 32754 | AG82: =AG71-AG27 -> -11977 | AH82: =AH71-AH27 -> 76847 | AI82: =AI71-AI27 -> 59682 | AJ82: =AJ71-AJ27 -> 74226 | AK82: =AK71-AK27 -> 14740 | AL82: =AL71-AL27 -> 38005 | AM82: =AM71-AM27 -> -71903 | ... AQ82: =AQ71-AQ27 -> 2160 | AR82: =SUM(AF82:AQ82) -> 9360.6667 | AT82: =AT71-AT27 -> -19749.25 | AU82: =AU71-AU27 -> -43342.103 | AV82: =AV71-AV27 -> -36893.138 | AW82: =AW71-AW27 -> -32095.138 | AX82: =AX71-AX27 -> 19900.034 | AY82: =AY71-AY27 -> 19999.222 | AZ82: =AZ71-AZ27 -> -14264.778 | BA82: =BA71-BA27 -> -68922.296 | ... BE82: =BE71-BE27 -> -10986.613 | BF82: =SUM(AT82:BE82) -> -365754.72 | BH82: =BH71-BH27 -> -12993 | BI82: =BI71-BI27 -> -30242.333 | BJ82: =BJ71-BJ27 -> -23206.074 | BK82: =BK71-BK27 -> -47411.741 | BL82: =BL71-BL27 -> -23836.852 | BM82: =BM71-BM27 -> 23509.741 | BN82: =BN71-BN27 -> -33707.556 | BO82: =BO71-BO27 -> -18896.378 | ... BQ82: =BQ71-BQ27 -> -7140 | BT82: =SUM(BH82:BS82) -> -218977.94 | BY82: =BY71-BY27 -> 13630.769 | BZ82: =BZ71-BZ27 -> 14117.607 | CA82: =CA71-CA27 -> 16957.871 | CB82: =CB71-CB27 -> 3013.7856 | CC82: =CC71-CC27 -> -28501.089 | CD82: =CD71-CD27 -> -40033.04 | CE82: =CE71-CE27 -> -43122.304 | CF82: =CF71-CF27 -> -3915.8422 | CG82: =CG71-CG27 -> 11316.183 | CH82: =CH78-CH69 -> -50665 | CJ82: =CJ71-CJ27 -> -16422.94 | CK82: =CK71-CK27 -> 22747.33 | CL82: =CL71-CL27 -> -14796.68 | CM82: =CM71-CM27 -> 19943.34 | CN82: =CN71-CN27 -> 35198.05 | CO82: =CO71-CO27 -> 73319.12 | CP82: =CP71-CP27 -> -9720.09 | CQ82: =CQ71-CQ27 -> 104.69 | ... CV82: =CV71-CV27 -> 66733.35 | CX82: =CX71-CX27 -> -6494.087 | CY82: =CY71-CY27 -> -36145.303 | CZ82: =CZ71-CZ27 -> -20286.514 | DA82: =DA71-DA27 -> 15940.507 | DB82: =DB71-DB27 -> 31707.952 | DC82: =DC71-DC27 -> 57810.076 | DD82: =DD71-DD27 -> -25406.095 | DE82: =DE71-DE27 -> -24040.076 | ... DJ82: =DJ71-DJ27 -> 195702.83
CA83: =BZ83+CA82 -> 16957.871 | CB83: =CA83+CB82 -> 19971.656 | CC83: =CB83+CC82 -> -8529.433 | CD83: =CC83+CD82 -> -48562.473 | CE83: =CD83+CE82 -> -91684.777 | CF83: =CE83+CF82 -> -95600.619 | CG83: =CF83+CG82 -> -84284.436

Sheet Plano mestre 2025 4 oficina (2)
R1: PLANEJAMENTO FABRICA | AF1: PLANEJAMENTO FABRICA | AT1: PLANEJAMENTO FABRICA | BH1: PLANEJAMENTO FABRICA | BV1: PLANEJAMENTO FABRICA | CH1: Férias 18/12 - 29/12 | CJ1: PLANEJAMENTO FABRICA | CX1: PLANEJAMENTO FABRICA
D2: 2019 | R2: 2020 | AF2: 2021 | AT2: 2022 | BH2: 2023 | BV2: 2024 | CH2: COMPENSAÇÃO 30 ,31 ,02 e 03 | CJ2: /--------------------------------------------2025 | CX2: 2026
A3: Dias Uteis Produção | C3: =A3 -> Dias Uteis Produção | CH3: 12 dias de férias | CJ3: 23 | CK3: 20 | CL3: 21 | CM3: 22 | CN3: 22 | CO3: 21 | CP3: 23 | CQ3: 21 | CR3: 21 | CS3: 23 | CT3: 20 | CU3: 13 | CX3: 23 | CY3: 20 | CZ3: 21 | DA3: 22 | DB3: 22 | DC3: 21 | DD3: 23 | DE3: 21 | DF3: 21 | DG3: 23 | DH3: 20 | DI3: 13
A4: (-) FÉRIAS | C4: =A4 -> (-) FÉRIAS | CH4: 4 dias de compensação | CJ4: 3 | CL4: 1.5 | CX4: 3 | CY4: 5
A5: (+) SABADO | C5: =A5 -> (+) SABADO | CH5: dias de compensação 9/11 , 23/11 , 7/12 e 14/12 | CJ5: 2 | CK5: 3 | CL5: 1.5 | CM5: 0 | CN5: 0 | CO5: 1.5 | CP5: 1 | CQ5: 1.5 | CR5: 1.5 | CS5: 1.5 | CT5: 0 | DA5: 0 | DB5: 0 | DC5: 0 | DD5: 0 | DE5: 0 | DF5: 0 | DG5: 1 | DH5: 0
A6: (-)FERIADO | C6: =A6 -> (-)FERIADO | CG6: 2 grupos a partir de dezembro | CL6: 2 | CM6: 2 | CN6: 1 | CO6: 1 | CR6: 1 | CS6: 1 | CT6: 1 | CZ6: 2 | DA6: 2 | DB6: 1 | DC6: 1 | DF6: 1 | DG6: 1 | DH6: 1
